Workbook

Sheet florauruguaya_V_4
A1: wfo_ID | B1: Hábito | C1: Familia | D1: Column1 | E1: Nombre | F1: Autor | G1: Pub. | H1: Hábito | I1: Formaciones vegetales | J1: Forma de vida | K1: Link stand alone
A2: =VLOOKUP(especies_20260604_152756[[#This Row],[Column1]],output__33[[input_name_string]:[wfo_id2]],2,FALSE) -> wfo-0000646051 | B2: Sufrútice | C2: Acanthaceae | D2: Dicliptera squarrosa Nees | E2: Dicliptera squarrosa | F2: Nees | G2: Fl. Bras. [Martius] 9: 161, 1847. | H2: Sufrútice | I2: Bosques ribereños, Algarrobales, Matorrales mesófilos, Matorrales psamófilos, Pastizales xerófilos | J2: Caméfita | K2: https://florauruguaya.org/taxonomias/dicliptera-squarrosa
A3: =VLOOKUP(especies_20260604_152756[[#This Row],[Column1]],output__33[[input_name_string]:[wfo_id2]],2,FALSE) -> wfo-1200030165 | B3: Hierba perenne | C3: Acanthaceae | D3: Dyschoriste humilis (Nees) Lindau | E3: Dyschoriste humilis | F3: (Nees) Lindau | G3: Bot. Jahrb. Syst. 19(4): 15, 1894. | H3: Hierba perenne | I3: Algarrobales, Matorrales xerófilos, Pastizales xerófilos | J3: Caméfita | K3: https://florauruguaya.org/taxonomias/dyschoriste-humilis
A4: =VLOOKUP(especies_20260604_152756[[#This Row],[Column1]],output__33[[input_name_string]:[wfo_id2]],2,FALSE) -> wfo-0000658315 | B4: Hierba perenne | C4: Acanthaceae | D4: Dyschoriste hygrophiloides (Nees) Kuntze | E4: Dyschoriste hygrophiloides | F4: (Nees) Kuntze | G4: Revis. Gen. Pl. 2: 486, 1891. | H4: Hierba perenne | I4: Pastizales xerófilos, Pastizales mesófilos | K4: https://florauruguaya.org/taxonomias/dyschoriste-hygrophiloides
A5: =VLOOKUP(especies_20260604_152756[[#This Row],[Column1]],output__33[[input_name_string]:[wfo_id2]],2,FALSE) -> wfo-0000726781 | B5: Hierba perenne | C5: Acanthaceae | D5: Hygrophila costata Nees & T.Nees | E5: Hygrophila costata | F5: Nees & T.Nees | G5: Pl. Hort. Bonn. Icon. 7, t. 3, 1824. | H5: Hierba perenne | I5: Bosques ribereños, Bosques higrófilos, Algarrobales, Palmares, Herbazales hidrófilos | J5: Caméfita | K5: https://florauruguaya.org/taxonomias/hygrophila-costata
A6: =VLOOKUP(especies_20260604_152756[[#This Row],[Column1]],output__33[[input_name_string]:[wfo_id2]],2,FALSE) -> wfo-0000726797 | B6: Hierba perenne | C6: Acanthaceae | D6: Hygrophila guianensis Nees | E6: Hygrophila guianensis | F6: Nees | G6: London J. Bot. 4: 634, 1845. | H6: Hierba perenne | I6: Bosques ribereños | K6: https://florauruguaya.org/taxonomias/hygrophila-guianensis
A7: =VLOOKUP(especies_20260604_152756[[#This Row],[Column1]],output__33[[input_name_string]:[wfo_id2]],2,FALSE) -> wfo-0001043972 | B7: Hierba perenne | C7: Acanthaceae | D7: Justicia axillaris (Nees) Lindau | E7: Justicia axillaris | F7: (Nees) Lindau | G7: Nat. Pflanzenfam. [Engler & Prantl] 4(3b): 350, 1895. | H7: Hierba perenne | I7: Matorrales xerófilos, Pastizales xerófilos | K7: https://florauruguaya.org/taxonomias/justicia-axillaris
A8: =VLOOKUP(especies_20260604_152756[[#This Row],[Column1]],output__33[[input_name_string]:[wfo_id2]],2,FALSE) -> wfo-0000354192 | B8: Sufrútice | C8: Acanthaceae | D8: Justicia brasiliana Roth | E8: Justicia brasiliana | F8: Roth | G8: Nov. Pl. Sp. 17, 1821. | H8: Sufrútice | I8: Bosques de quebradas, Bosques ribereños | J8: Caméfita | K8: https://florauruguaya.org/taxonomias/justicia-brasiliana
A9: =VLOOKUP(especies_20260604_152756[[#This Row],[Column1]],output__33[[input_name_string]:[wfo_id2]],2,FALSE) -> wfo-0000354453 | B9: Hierba perenne | C9: Acanthaceae | D9: Justicia comata (L.) Lam. | E9: Justicia comata | F9: (L.) Lam. | G9: Encycl. [J. Lamarck & al.] 1(2): 632, 1785. | H9: Hierba perenne | I9: Bosques ribereños, Herbazales hidrófilos | J9: Caméfita | K9: https://florauruguaya.org/taxonomias/justicia-comata
A10: =VLOOKUP(especies_20260604_152756[[#This Row],[Column1]],output__33[[input_name_string]:[wfo_id2]],2,FALSE) -> wfo-0000355947 | B10: Hierba perenne | C10: Acanthaceae | D10: Justicia laevilinguis (Nees) Lindau | E10: Justicia laevilinguis | F10: (Nees) Lindau | G10: Bot. Jahrb. Syst. 19(4): 20, 1894. | H10: Hierba perenne | I10: Algarrobales, Pastizales higrófilos, Herbazales hidrófilos | J10: Caméfita | K10: https://florauruguaya.org/taxonomias/justicia-laevilinguis
A11: =VLOOKUP(especies_20260604_152756[[#This Row],[Column1]],output__33[[input_name_string]:[wfo_id2]],2,FALSE) -> wfo-0001044021 | B11: Hierba perenne | C11: Acanthaceae | D11: Justicia oblonga (Nees) Lindau | E11: Justicia oblonga | F11: (Nees) Lindau | G11: Nat. Pflanzenfam. [Engler & Prantl] 4(3b): 350, 1895. | H11: Hierba perenne | I11: Bosques ribereños | K11: https://florauruguaya.org/taxonomias/justicia-oblonga
A12: =VLOOKUP(especies_20260604_152756[[#This Row],[Column1]],output__33[[input_name_string]:[wfo_id2]],2,FALSE) -> wfo-0001044033 | B12: Hierba perenne | C12: Acanthaceae | D12: Justicia polygaloides (S.Moore) Lindau | E12: Justicia polygaloides | F12: (S.Moore) Lindau | G12: Bull. Herb. Boissier 2(3): 633, 1933. | H12: Hierba perenne | I12: Pastizales higrófilos | K12: https://florauruguaya.org/taxonomias/justicia-polygaloides
A13: =VLOOKUP(especies_20260604_152756[[#This Row],[Column1]],output__33[[input_name_string]:[wfo_id2]],2,FALSE) -> wfo-0001045288 | B13: Arbusto | C13: Acanthaceae | D13: Justicia tweedieana (Nees) Griseb. | E13: Justicia tweedieana | F13: (Nees) Griseb. | G13: Abh. Königl. Ges. Wiss. Göttingen 19: 225, 1874. | H13: Arbusto | I13: Algarrobales, Pastizales xerófilos, Herbazales halófilos | J13: Nanofanerófita | K13: https://florauruguaya.org/taxonomias/justicia-tweedieana
A14: =VLOOKUP(especies_20260604_152756[[#This Row],[Column1]],output__33[[input_name_string]:[wfo_id2]],2,FALSE) -> wfo-0000398720 | B14: Arbusto | C14: Acanthaceae | D14: Poikilacanthus glandulosus (Nees) Ariza | E14: Poikilacanthus glandulosus | F14: (Nees) Ariza | G14: Kurtziana 17: 159, 1984. | H14: Arbusto | I14: Bosques ribereños, Matorrales mesófilos | J14: Nanofanerófita | K14: https://florauruguaya.org/taxonomias/poikilacanthus-glandulosus
A15: =VLOOKUP(especies_20260604_152756[[#This Row],[Column1]],output__33[[input_name_string]:[wfo_id2]],2,FALSE) -> wfo-0000737403 | B15: Arbusto | C15: Acanthaceae | D15: Ruellia angustiflora (Nees) Lindau ex Rambo | E15: Ruellia angustiflora | F15: (Nees) Lindau ex Rambo | G15: Iheringia, Bot. 12: 23, 1964. | H15: Arbusto | I15: Bosques de quebradas | J15: Nanofanerófita | K15: https://florauruguaya.org/taxonomias/ruellia-angustiflora
A16: =VLOOKUP(especies_20260604_152756[[#This Row],[Column1]],output__33[[input_name_string]:[wfo_id2]],2,FALSE) -> wfo-0001045381 | B16: Hierba perenne | C16: Acanthaceae | D16: Ruellia hygrophila Mart. | E16: Ruellia hygrophila | F16: Mart. | G16: Flora 24(2): 65, 1841. | H16: Hierba perenne | I16: Matorrales xerófilos, Herbazales hidrófilos | J16: Hemicriptófita | K16: https://florauruguaya.org/taxonomias/ruellia-hygrophila
A17: =VLOOKUP(especies_20260604_152756[[#This Row],[Column1]],output__33[[input_name_string]:[wfo_id2]],2,FALSE) -> wfo-0000401879 | B17: Hierba perenne | C17: Acanthaceae | D17: Ruellia hypericoides (Nees) Lindau | E17: Ruellia hypericoides | F17: (Nees) Lindau | G17: Bot. Jahrb. Syst. 19(4): 16, 1894. | H17: Hierba perenne | I17: Pastizales xerófilos | J17: Hemicriptófita | K17: https://florauruguaya.org/taxonomias/ruellia-hypericoides
A18: =VLOOKUP(especies_20260604_152756[[#This Row],[Column1]],output__33[[input_name_string]:[wfo_id2]],2,FALSE) -> wfo-0001045173 | B18: Hierba perenne | C18: Acanthaceae | D18: Ruellia morongii Britton | E18: Ruellia morongii | F18: Britton | G18: Ann. New York Acad. Sci. 7: 192, 1893. | H18: Hierba perenne | I18: Pastizales xerófilos, Pastizales mesófilos | J18: Hemicriptófita | K18: https://florauruguaya.org/taxonomias/ruellia-morongii
A19: =VLOOKUP(especies_20260604_152756[[#This Row],[Column1]],output__33[[input_name_string]:[wfo_id2]],2,FALSE) -> wfo-0000400995 | B19: Hierba perenne | C19: Acanthaceae | D19: Ruellia simplex C.Wright | E19: Ruellia simplex | F19: C.Wright | G19: Anales Acad. Ci. Méd. Habana 6(41): 321, 1870. | H19: Hierba perenne | I19: Bosques ribereños, Algarrobales, Pastizales higrófilos, Herbazales halófilos | J19: Caméfita | K19: https://florauruguaya.org/taxonomias/ruellia-simplex
A20: =VLOOKUP(especies_20260604_152756[[#This Row],[Column1]],output__33[[input_name_string]:[wfo_id2]],2,FALSE) -> wfo-0001045348 | B20: Hierba perenne | C20: Acanthaceae | D20: Stenandrium diphyllum Nees | E20: Stenandrium diphyllum | F20: Nees | G20: Fl. Bras. [Martius] 9: 75, 1847. | H20: Hierba perenne | I20: Matorrales xerófilos, Pastizales xerófilos | J20: Hemicriptófita | K20: https://florauruguaya.org/taxonomias/stenandrium-diphyllum
A21: =VLOOKUP(especies_20260604_152756[[#This Row],[Column1]],output__33[[input_name_string]:[wfo_id2]],2,FALSE) -> wfo-0001044785 | B21: Hierba perenne | C21: Acanthaceae | D21: Stenandrium dulce (Cav.) Nees | E21: Stenandrium dulce | F21: (Cav.) Nees | G21: Prodr. [A. P. de Candolle] 11: 282, 1847. | H21: Hierba perenne | I21: Algarrobales, Palmares, Pastizales xerófilos, Pastizales mesófilos, Herbazales halófilos | J21: Hemicriptófita | K21: https://florauruguaya.org/taxonomias/stenandrium-dulce
A22: =VLOOKUP(especies_20260604_152756[[#This Row],[Column1]],output__33[[input_name_string]:[wfo_id2]],2,FALSE) -> wfo-0001354429 | B22: Hierba perenne | C22: Acanthaceae | D22: Thyrsacanthus sulcatus (Nees) C.Ezcurra & A.L.A.Côrtes | E22: Thyrsacanthus sulcatus | F22: (Nees) C.Ezcurra & A.L.A.Côrtes | G22: Phytotaxa 395(2): 85, 2019. | H22: Hierba perenne | I22: Algarrobales, Herbazales halófilos | K22: https://florauruguaya.org/taxonomias/thyrsacanthus-sulcatus
A23: =VLOOKUP(especies_20260604_152756[[#This Row],[Column1]],output__33[[input_name_string]:[wfo_id2]],2,FALSE) -> wfo-0000515942 | B23: Árbol | C23: Achatocarpaceae | D23: Achatocarpus praecox Griseb. | E23: Achatocarpus praecox | F23: Griseb. | G23: Abh. Königl. Ges. Wiss. Göttingen 24: 32, 1879. | H23: Árbol | I23: Algarrobales | J23: Fanerófita | K23: https://florauruguaya.org/taxonomias/achatocarpus-praecox
A24: =VLOOKUP(especies_20260604_152756[[#This Row],[Column1]],output__33[[input_name_string]:[wfo_id2]],2,FALSE) -> wfo-0000588263 | B24: Hierba perenne | C24: Aizoaceae | D24: Carpobrotus edulis (L.) N.E.Br. | E24: Carpobrotus edulis | F24: (L.) N.E.Br. | G24: Gen. S. Afr. Fl. Pl. 249, 1926. | H24: Hierba perenne | I24: Ambientes urbanos, Matorrales psamófilos, Pastizales xerófilos, Herbazales psamófilos | J24: Caméfita | K24: https://florauruguaya.org/taxonomias/carpobrotus-edulis
A25: =VLOOKUP(especies_20260604_152756[[#This Row],[Column1]],output__33[[input_name_string]:[wfo_id2]],2,FALSE) -> wfo-0000361350 | B25: Sufrútice | C25: Aizoaceae | D25: Lampranthus multiradiatus (Jacq.) N.E.Br. | E25: Lampranthus multiradiatus | F25: (Jacq.) N.E.Br. | G25: Gard. Chron. 3(87): 71, 1830. | H25: Sufrútice | I25: Herbazales psamófilos | K25: https://florauruguaya.org/taxonomias/lampranthus-multiradiatus
A26: =VLOOKUP(especies_20260604_152756[[#This Row],[Column1]],output__33[[input_name_string]:[wfo_id2]],2,FALSE) -> wfo-0001292821 | B26: Hierba perenne | C26: Aizoaceae | D26: Sesuvium sessile Pers. | E26: Sesuvium sessile | F26: Pers. | G26: Syn. Pl. [Persoon] 2(1): 39, 1806. | H26: Hierba perenne | I26: Ambientes urbanos, Herbazales halófilos | J26: Caméfita | K26: https://florauruguaya.org/taxonomias/sesuvium-sessile
A27: =VLOOKUP(especies_20260604_152756[[#This Row],[Column1]],output__33[[input_name_string]:[wfo_id2]],2,FALSE) -> wfo-0000414976 | B27: Hierba perenne | C27: Aizoaceae | D27: Tetragonia tetragonoides (Pall.) Kuntze | E27: Tetragonia tetragonoides | F27: (Pall.) Kuntze | G27: Revis. Gen. Pl. 1: 264, 1891. | H27: Hierba perenne | I27: Herbazales hidrófilos | J27: Caméfita | K27: https://florauruguaya.org/taxonomias/tetragonia-tetragonoides
A28: =VLOOKUP(especies_20260604_152756[[#This Row],[Column1]],output__33[[input_name_string]:[wfo_id2]],2,FALSE) -> wfo-0000755470 | B28: Hierba perenne | C28: Alismataceae | D28: Alisma plantago-aquatica L. | E28: Alisma plantago-aquatica | F28: L. | G28: Sp. Pl. [Linnaeus] 1: 342, 1753. | H28: Hierba perenne | I28: Dulce y salobre | K28: https://florauruguaya.org/taxonomias/alisma-plantago-aquatica
A29: =VLOOKUP(especies_20260604_152756[[#This Row],[Column1]],output__33[[input_name_string]:[wfo_id2]],2,FALSE) -> wfo-0000766394 | B29: Hierba perenne | C29: Alismataceae | D29: Echinodorus floribundus (Seub.) Seub. ex Warm. | E29: Echinodorus floribundus | F29: (Seub.) Seub. ex Warm. | G29: Vidensk. Meddel. Naturhist. Foren. Kjøbenhavn 1872: 113, 1872. | H29: Hierba perenne | I29: Herbazales hidrófilos | J29: Hemicriptófita | K29: https://florauruguaya.org/taxonomias/echinodorus-floribundus
A30: =VLOOKUP(especies_20260604_152756[[#This Row],[Column1]],output__33[[input_name_string]:[wfo_id2]],2,FALSE) -> wfo-0000766401 | B30: Hierba perenne | C30: Alismataceae | D30: Echinodorus grandiflorus (Cham. & Schltdl.) Micheli | E30: Echinodorus grandiflorus | F30: (Cham. & Schltdl.) Micheli | G30: Monogr. Phan. [A.DC. & C.DC.] 3: 57, 1881. | H30: Hierba perenne | I30: Bosques higrófilos, Algarrobales, Palmares, Herbazales hidrófilos, Dulce y salobre | J30: Hemicriptófita | K30: https://florauruguaya.org/taxonomias/echinodorus-grandiflorus
A31: =VLOOKUP(especies_20260604_152756[[#This Row],[Column1]],output__33[[input_name_string]:[wfo_id2]],2,FALSE) -> wfo-0000766423 | B31: Hierba perenne | C31: Alismataceae | D31: Echinodorus longiscapus Arechav. | E31: Echinodorus longiscapus | F31: Arechav. | G31: Anales Mus. Nac. Montevideo 4(1): 67, pl. 2, 1903. | H31: Hierba perenne | I31: Pastizales higrófilos, Herbazales hidrófilos | J31: Hemicriptófita | K31: https://florauruguaya.org/taxonomias/echinodorus-longiscapus
A32: =VLOOKUP(especies_20260604_152756[[#This Row],[Column1]],output__33[[input_name_string]:[wfo_id2]],2,FALSE) -> wfo-0000766491 | B32: Hierba perenne | C32: Alismataceae | D32: Echinodorus uruguayensis Arechav. | E32: Echinodorus uruguayensis | F32: Arechav. | G32: Anales Mus. Nac. Montevideo 4(1): 66, pl. 2, 1903. | H32: Hierba perenne | I32: Dulce y salobre | J32: Hemicriptófita | K32: https://florauruguaya.org/taxonomias/echinodorus-uruguayensis
A33: =VLOOKUP(especies_20260604_152756[[#This Row],[Column1]],output__33[[input_name_string]:[wfo_id2]],2,FALSE) -> wfo-0000834478 | B33: Hierba anual o bienal | C33: Alismataceae | D33: Helanthium tenellum (Mart. ex Schult.f.) Britton | E33: Helanthium tenellum | F33: (Mart. ex Schult.f.) Britton | G33: Man. Fl. N. States [Britton], ed. 2. 54, 1905. | H33: Hierba anual o bienal | I33: Pastizales higrófilos, Herbazales hidrófilos, Dulce y salobre | J33: Terófita | K33: https://florauruguaya.org/taxonomias/helanthium-tenellum
A34: =VLOOKUP(especies_20260604_152756[[#This Row],[Column1]],output__33[[input_name_string]:[wfo_id2]],2,FALSE) -> wfo-0000666030 | B34: Hierba perenne | C34: Alismataceae | D34: Hydrocleys nymphoides (Humb. & Bonpl. ex Willd.) Buchenau | E34: Hydrocleys nymphoides | F34: (Humb. & Bonpl. ex Willd.) Buchenau | G34: Abh. Naturwiss. Vereins Bremen 2: 2, 1871. | H34: Hierba perenne | I34: Pastizales higrófilos, Herbazales hidrófilos, Dulce y salobre | J34: Hidrófita | K34: https://florauruguaya.org/taxonomias/hydrocleys-nymphoides
A35: =VLOOKUP(especies_20260604_152756[[#This Row],[Column1]],output__33[[input_name_string]:[wfo_id2]],2,FALSE) -> wfo-0000666074 | B35: Hierba perenne | C35: Alismataceae | D35: Hydrocleys uruguayensis (Buchenau) Pedersen | E35: Hydrocleys uruguayensis | F35: (Buchenau) Pedersen | G35: Bot. Tidsskr. 57: 41, 1961. | H35: Hierba perenne | I35: Herbazales hidrófilos, Dulce y salobre | K35: https://florauruguaya.org/taxonomias/hydrocleys-uruguayensis
A36: =VLOOKUP(especies_20260604_152756[[#This Row],[Column1]],output__33[[input_name_string]:[wfo_id2]],2,FALSE) -> wfo-0000738022 | B36: Hierba perenne | C36: Alismataceae | D36: Sagittaria montevidensis Cham. & Schltdl. | E36: Sagittaria montevidensis | F36: Cham. & Schltdl. | G36: Linnaea 2: 2, 156, 1827. | H36: Hierba perenne | I36: Algarrobales, Herbazales hidrófilos, Dulce y salobre | J36: Hidrófita | K36: https://florauruguaya.org/taxonomias/sagittaria-montevidensis
A37: =VLOOKUP(especies_20260604_152756[[#This Row],[Column1]],output__33[[input_name_string]:[wfo_id2]],2,FALSE) -> wfo-0000759175 | B37: Hierba perenne | C37: Alstroemeriaceae | D37: Alstroemeria isabellana Herb. | E37: Alstroemeria isabellana | F37: Herb. | G37: Amaryllidaceae 88, t. 6, f. 4-6, 1837. | H37: Hierba perenne | I37: Bosques higrófilos, Pastizales higrófilos | J37: Hemicriptófita | K37: https://florauruguaya.org/taxonomias/alstroemeria-isabellana
A38: =VLOOKUP(especies_20260604_152756[[#This Row],[Column1]],output__33[[input_name_string]:[wfo_id2]],2,FALSE) -> wfo-0000759283 | B38: Hierba perenne | C38: Alstroemeriaceae | D38: Alstroemeria psittacina Lehm. | E38: Alstroemeria psittacina | F38: Lehm. | G38: Sem. Hort. Bot. Hamburg. 1826: 17, 1826. | H38: Hierba perenne | I38: Bosques ribereños | J38: Hemicriptófita | K38: https://florauruguaya.org/taxonomias/alstroemeria-psittacina
A39: =VLOOKUP(especies_20260604_152756[[#This Row],[Column1]],output__33[[input_name_string]:[wfo_id2]],2,FALSE) -> wfo-0000528632 | B39: Hierba perenne | C39: Amaranthaceae | D39: Alternanthera kurtzii Schinz ex Pedersen | E39: Alternanthera kurtzii | F39: Schinz ex Pedersen | G39: Darwiniana 14(2-3): 435, 1967. | H39: Hierba perenne | I39: Bosques ribereños, Algarrobales, Pastizales higrófilos | K39: https://florauruguaya.org/taxonomias/alternanthera-kurtzii
A40: =VLOOKUP(especies_20260604_152756[[#This Row],[Column1]],output__33[[input_name_string]:[wfo_id2]],2,FALSE) -> wfo-0000528686 | B40: Hierba perenne | C40: Amaranthaceae | D40: Alternanthera micrantha R.E.Fr. | E40: Alternanthera micrantha | F40: R.E.Fr. | G40: Ark. Bot. 16(12): 14, 1920. | H40: Hierba perenne | I40: Bosques ribereños | J40: Caméfita | K40: https://florauruguaya.org/taxonomias/alternanthera-micrantha
A41: =VLOOKUP(especies_20260604_152756[[#This Row],[Column1]],output__33[[input_name_string]:[wfo_id2]],2,FALSE) -> wfo-0000528723 | B41: Hierba perenne | C41: Amaranthaceae | D41: Alternanthera paronychioides A.St.-Hil. | E41: Alternanthera paronychioides | F41: A.St.-Hil. | G41: Voy. Distr. Diam. 2: 439, 1833. | H41: Hierba perenne | I41: Pastizales higrófilos | J41: Caméfita | K41: https://florauruguaya.org/taxonomias/alternanthera-paronychioides
A42: =VLOOKUP(especies_20260604_152756[[#This Row],[Column1]],output__33[[input_name_string]:[wfo_id2]],2,FALSE) -> wfo-0000528743 | B42: Hierba perenne | C42: Amaranthaceae | D42: Alternanthera philoxeroides (Mart.) Griseb. | E42: Alternanthera philoxeroides | F42: (Mart.) Griseb. | G42: Abh. Königl. Ges. Wiss. Göttingen 24: 36, 1879. | H42: Hierba perenne | I42: Bosques ribereños, Bosques higrófilos, Palmares, Pastizales higrófilos, Herbazales hidrófilos, Dulce y salobre | J42: Caméfita | K42: https://florauruguaya.org/taxonomias/alternanthera-philoxeroides
A43: =VLOOKUP(especies_20260604_152756[[#This Row],[Column1]],output__33[[input_name_string]:[wfo_id2]],2,FALSE) -> wfo-0000528787 | B43: Hierba perenne | C43: Amaranthaceae | D43: Alternanthera pungens Kunth | E43: Alternanthera pungens | F43: Kunth | G43: Nov. Gen. Sp. [H.B.K.] 2: 206, 1818. | H43: Hierba perenne | I43: Ambientes ruderales | J43: Caméfita | K43: https://florauruguaya.org/taxonomias/alternanthera-pungens
A44: =VLOOKUP(especies_20260604_152756[[#This Row],[Column1]],output__33[[input_name_string]:[wfo_id2]],2,FALSE) -> wfo-0000528801 | B44: Hierba anual o bienal | C44: Amaranthaceae | D44: Alternanthera reineckii Briq. | E44: Alternanthera reineckii | F44: Briq. | G44: Annuaire Conserv. Jard. Bot. Genève 3: 151, 1899. | H44: Hierba anual o bienal | I44: Bosques ribereños, Algarrobales | J44: Terófita | K44: https://florauruguaya.org/taxonomias/alternanthera-reineckii
A45: =VLOOKUP(especies_20260604_152756[[#This Row],[Column1]],output__33[[input_name_string]:[wfo_id2]],2,FALSE) -> wfo-0000530018 | B45: Hierba anual o bienal | C45: Amaranthaceae | D45: Amaranthus albus L. | E45: Amaranthus albus | F45: L. | G45: Syst. Nat., ed. 10. 2: 1268, 1759. | H45: Hierba anual o bienal | I45: Ambientes ruderales | J45: Terófita | K45: https://florauruguaya.org/taxonomias/amaranthus-albus
A46: =VLOOKUP(especies_20260604_152756[[#This Row],[Column1]],output__33[[input_name_string]:[wfo_id2]],2,FALSE) -> wfo-0000530085 | B46: Hierba anual o bienal | C46: Amaranthaceae | D46: Amaranthus blitum L. | E46: Amaranthus blitum | F46: L. | G46: Sp. Pl. [Linnaeus] 2: 990, 1753. | H46: Hierba anual o bienal | I46: Herbazales psamófilos | J46: Terófita | K46: https://florauruguaya.org/taxonomias/amaranthus-blitum
A47: =VLOOKUP(especies_20260604_152756[[#This Row],[Column1]],output__33[[input_name_string]:[wfo_id2]],2,FALSE) -> wfo-0000530163 | B47: Hierba anual o bienal | C47: Amaranthaceae | D47: Amaranthus crispus (Lesp. & Thévenau) A.Braun ex S.Watson & J.M.Coult. | E47: Amaranthus crispus | F47: (Lesp. & Thévenau) A.Braun ex S.Watson & J.M.Coult. | G47: Manual (Gray), ed. 6. 428, 1890. | H47: Hierba anual o bienal | I47: Pastizales mesófilos, Herbazales psamófilos | J47: Terófita | K47: https://florauruguaya.org/taxonomias/amaranthus-crispus
A48: =VLOOKUP(especies_20260604_152756[[#This Row],[Column1]],output__33[[input_name_string]:[wfo_id2]],2,FALSE) -> wfo-0000530173 | B48: Hierba perenne | C48: Amaranthaceae | D48: Amaranthus deflexus L. | E48: Amaranthus deflexus | F48: L. | G48: Mant. Pl. Altera 295, 1771. | H48: Hierba perenne | I48: Ambientes ruderales, Ambientes urbanos, Palmares | J48: Caméfita | K48: https://florauruguaya.org/taxonomias/amaranthus-deflexus
A49: =VLOOKUP(especies_20260604_152756[[#This Row],[Column1]],output__33[[input_name_string]:[wfo_id2]],2,FALSE) -> wfo-0000530251 | B49: Hierba anual o bienal | C49: Amaranthaceae | D49: Amaranthus hybridus L. | E49: Amaranthus hybridus | F49: L. | G49: Sp. Pl. [Linnaeus] 2: 990, 1753. | H49: Hierba anual o bienal | I49: Ambientes ruderales | J49: Terófita | K49: https://florauruguaya.org/taxonomias/amaranthus-hybridus
A50: =VLOOKUP(especies_20260604_152756[[#This Row],[Column1]],output__33[[input_name_string]:[wfo_id2]],2,FALSE) -> wfo-0000530332 | B50: Hierba anual o bienal | C50: Amaranthaceae | D50: Amaranthus lombardoi Hunz. | E50: Amaranthus lombardoi | F50: Hunz. | G50: Bol. Soc. Argent. Bot. 4: 141, fig. 4, 1951. | H50: Hierba anual o bienal | I50: Herbazales hidrófilos | J50: Terófita | K50: https://florauruguaya.org/taxonomias/amaranthus-lombardoi
A51: =VLOOKUP(especies_20260604_152756[[#This Row],[Column1]],output__33[[input_name_string]:[wfo_id2]],2,FALSE) -> wfo-0000530370 | B51: Hierba perenne | C51: Amaranthaceae | D51: Amaranthus muricatus (Moq.) Hieron. | E51: Amaranthus muricatus | F51: (Moq.) Hieron. | G51: Bol. Acad. Nac. Ci. 4(2): 421, 1882. | H51: Hierba perenne | I51: Ambientes ruderales, Ambientes urbanos, Algarrobales | J51: Caméfita | K51: https://florauruguaya.org/taxonomias/amaranthus-muricatus
... A55: =VLOOKUP(especies_20260604_152756[[#This Row],[Column1]],output__33[[input_name_string]:[wfo_id2]],2,FALSE) -> wfo-0000530499 | B55: Hierba anual o bienal | C55: Amaranthaceae | D55: Amaranthus standleyanus Parodi ex Covas | E55: Amaranthus standleyanus | F55: Parodi ex Covas | G55: Darwiniana 5: 339, 1941. | H55: Hierba anual o bienal | I55: Ambientes urbanos, Algarrobales | J55: Terófita | K55: https://florauruguaya.org/taxonomias/amaranthus-standleyanus
A56: =VLOOKUP(especies_20260604_152756[[#This Row],[Column1]],output__33[[input_name_string]:[wfo_id2]],2,FALSE) -> wfo-0000530532 | B56: Hierba anual o bienal | C56: Amaranthaceae | D56: Amaranthus tuberculatus (Moq.) J.D.Sauer | E56: Amaranthus tuberculatus | F56: (Moq.) J.D.Sauer | G56: Madroño 13: 18, 1955. | H56: Hierba anual o bienal | J56: Terófita | K56: https://florauruguaya.org/taxonomias/amaranthus-tuberculatus
A57: =VLOOKUP(especies_20260604_152756[[#This Row],[Column1]],output__33[[input_name_string]:[wfo_id2]],2,FALSE) -> wfo-0000530552 | B57: Hierba anual o bienal | C57: Amaranthaceae | D57: Amaranthus viridis L. | E57: Amaranthus viridis | F57: L. | G57: Sp. Pl., ed. 2. 2: 1405, 1763. | H57: Hierba anual o bienal | I57: Ambientes ruderales, Ambientes urbanos | J57: Terófita | K57: https://florauruguaya.org/taxonomias/amaranthus-viridis
A58: =VLOOKUP(especies_20260604_152756[[#This Row],[Column1]],output__33[[input_name_string]:[wfo_id2]],2,FALSE) -> wfo-0000530556 | B58: Hierba perenne | C58: Amaranthaceae | D58: Amaranthus vulgatissimus Speg. | E58: Amaranthus vulgatissimus | F58: Speg. | G58: Anales Soc. Ci. Argent. 53(1): 281, 1902. | H58: Hierba perenne | I58: Algarrobales | J58: Caméfita | K58: https://florauruguaya.org/taxonomias/amaranthus-vulgatissimus
A59: =VLOOKUP(especies_20260604_152756[[#This Row],[Column1]],output__33[[input_name_string]:[wfo_id2]],2,FALSE) -> wfo-0000556302 | B59: Hierba perenne | C59: Amaranthaceae | D59: Atriplex montevidensis Spreng. | E59: Atriplex montevidensis | F59: Spreng. | G59: Syst. Veg., ed. 16 [Sprengel] 3: 918, 1826. | H59: Hierba perenne | I59: Algarrobales, Herbazales halófilos | J59: Caméfita | K59: https://florauruguaya.org/taxonomias/atriplex-montevidensis
A60: =VLOOKUP(especies_20260604_152756[[#This Row],[Column1]],output__33[[input_name_string]:[wfo_id2]],2,FALSE) -> wfo-0000556421 | B60: Hierba anual o bienal | C60: Amaranthaceae | D60: Atriplex patula L. | E60: Atriplex patula | F60: L. | G60: Sp. Pl. [Linnaeus] 2: 1053, 1753. | H60: Hierba anual o bienal | I60: Herbazales halófilos | J60: Terófita | K60: https://florauruguaya.org/taxonomias/atriplex-patula
A61: =VLOOKUP(especies_20260604_152756[[#This Row],[Column1]],output__33[[input_name_string]:[wfo_id2]],2,FALSE) -> wfo-0000556490 | B61: Hierba anual o bienal | C61: Amaranthaceae | D61: Atriplex prostrata Boucher ex DC. | E61: Atriplex prostrata | F61: Boucher ex DC. | G61: Fl. Franç. [de Candolle & Lamarck], ed. 3. 3: 387, 1805. | H61: Hierba anual o bienal | I61: Herbazales halófilos | J61: Terófita | K61: https://florauruguaya.org/taxonomias/atriplex-prostrata
A62: =VLOOKUP(especies_20260604_152756[[#This Row],[Column1]],output__33[[input_name_string]:[wfo_id2]],2,FALSE) -> wfo-0000561206 | B62: Hierba anual o bienal | C62: Amaranthaceae | D62: Bassia scoparia (L.) A.J.Scott | E62: Bassia scoparia | F62: (L.) A.J.Scott | G62: Feddes Repert. 89(2-3): 108, 1978. | H62: Hierba anual o bienal | I62: Ambientes ruderales | J62: Terófita | K62: https://florauruguaya.org/taxonomias/bassia-scoparia
A63: =VLOOKUP(especies_20260604_152756[[#This Row],[Column1]],output__33[[input_name_string]:[wfo_id2]],2,FALSE) -> wfo-0000564998 | B63: Hierba perenne | C63: Amaranthaceae | D63: Beta vulgaris L. | E63: Beta vulgaris | F63: L. | G63: Sp. Pl. [Linnaeus] 1: 222, 1753. | H63: Hierba perenne | I63: Ambientes urbanos | J63: Caméfita | K63: https://florauruguaya.org/taxonomias/beta-vulgaris
A64: =VLOOKUP(especies_20260604_152756[[#This Row],[Column1]],output__33[[input_name_string]:[wfo_id2]],2,FALSE) -> wfo-0001440519 | B64: Hierba anual o bienal | C64: Amaranthaceae | D64: Chenopodiastrum murale (L.) S.Fuentes, Uotila & Borsch | E64: Chenopodiastrum murale | F64: (L.) S.Fuentes, Uotila & Borsch | G64: Willdenowia 42(1): 14, 2012. | H64: Hierba anual o bienal | I64: Ambientes ruderales, Ambientes urbanos | J64: Terófita | K64: https://florauruguaya.org/taxonomias/chenopodiastrum-murale
A65: =VLOOKUP(especies_20260604_152756[[#This Row],[Column1]],output__33[[input_name_string]:[wfo_id2]],2,FALSE) -> wfo-0000600897 | B65: Hierba anual o bienal | C65: Amaranthaceae | D65: Chenopodium album L. | E65: Chenopodium album | F65: L. | G65: Sp. Pl. [Linnaeus] 1: 219, 1753. | H65: Hierba anual o bienal | I65: Ambientes urbanos | J65: Terófita | K65: https://florauruguaya.org/taxonomias/chenopodium-album
A66: =VLOOKUP(especies_20260604_152756[[#This Row],[Column1]],output__33[[input_name_string]:[wfo_id2]],2,FALSE) -> wfo-0000601305 | B66: Hierba anual o bienal | C66: Amaranthaceae | D66: Chenopodium giganteum D.Don | E66: Chenopodium giganteum | F66: D.Don | G66: Prodr. Fl. Nepal. 75, 1825. | H66: Hierba anual o bienal | I66: Ambientes ruderales | J66: Terófita | K66: https://florauruguaya.org/taxonomias/chenopodium-giganteum
A67: =VLOOKUP(especies_20260604_152756[[#This Row],[Column1]],output__33[[input_name_string]:[wfo_id2]],2,FALSE) -> wfo-0000601364 | B67: Hierba anual o bienal | C67: Amaranthaceae | D67: Chenopodium hircinum Schrad. | E67: Chenopodium hircinum | F67: Schrad. | G67: Index Seminum [Gottingen] 1833: 2, 1833. | H67: Hierba anual o bienal | I67: Ambientes ruderales, Ambientes urbanos | J67: Terófita | K67: https://florauruguaya.org/taxonomias/chenopodium-hircinum
A68: =VLOOKUP(especies_20260604_152756[[#This Row],[Column1]],output__33[[input_name_string]:[wfo_id2]],2,FALSE) -> wfo-0000658867 | B68: Hierba perenne | C68: Amaranthaceae | D68: Dysphania ambrosioides (L.) Mosyakin & Clemants | E68: Dysphania ambrosioides | F68: (L.) Mosyakin & Clemants | G68: Ukrayins&#39;k. Bot. Zhurn. 59(4): 382, 2002. | H68: Hierba perenne | I68: Ambientes ruderales, Ambientes urbanos, Algarrobales, Palmares, Pastizales xerófilos, Pastizales mesófilos | K68: https://florauruguaya.org/taxonomias/dysphania-ambrosioides
A69: =VLOOKUP(especies_20260604_152756[[#This Row],[Column1]],output__33[[input_name_string]:[wfo_id2]],2,FALSE) -> wfo-1000094821 | B69: Hierba perenne | C69: Amaranthaceae | D69: Dysphania bonariensis (Hook.f.) Mosyakin & Clemants ex Sukhor. | E69: Dysphania bonariensis | F69: (Hook.f.) Mosyakin & Clemants ex Sukhor. | G69: Willdenowia 42(2): 175, 2012. | H69: Hierba perenne | I69: Pastizales xerófilos | J69: Caméfita | K69: https://florauruguaya.org/taxonomias/dysphania-bonariensis
A70: =VLOOKUP(especies_20260604_152756[[#This Row],[Column1]],output__33[[input_name_string]:[wfo_id2]],2,FALSE) -> wfo-0000743784 | B70: Hierba perenne | C70: Amaranthaceae | D70: Dysphania burkartii (Aellen) Mosyakin & Clemants | E70: Dysphania burkartii | F70: (Aellen) Mosyakin & Clemants | G70: J. Bot. Res. Inst. Texas 2(1): 428, 2008. | H70: Hierba perenne | I70: Matorrales xerófilos, Pastizales xerófilos | J70: Caméfita | K70: https://florauruguaya.org/taxonomias/dysphania-burkartii
A71: =VLOOKUP(especies_20260604_152756[[#This Row],[Column1]],output__33[[input_name_string]:[wfo_id2]],2,FALSE) -> wfo-0000658883 | B71: Hierba perenne | C71: Amaranthaceae | D71: Dysphania multifida (L.) Mosyakin & Clemants | E71: Dysphania multifida | F71: (L.) Mosyakin & Clemants | G71: Ukrayins&#39;k. Bot. Zhurn. 59(4): 382, 2002. | H71: Hierba perenne | I71: Ambientes ruderales, Ambientes urbanos | J71: Caméfita | K71: https://florauruguaya.org/taxonomias/dysphania-multifida
A72: =VLOOKUP(especies_20260604_152756[[#This Row],[Column1]],output__33[[input_name_string]:[wfo_id2]],2,FALSE) -> wfo-0000743796 | B72: Hierba perenne | C72: Amaranthaceae | D72: Dysphania retusa (Moq.) Mosyakin & Clemants | E72: Dysphania retusa | F72: (Moq.) Mosyakin & Clemants | G72: J. Bot. Res. Inst. Texas 2(1): 428, 2008. | H72: Hierba perenne | I72: Herbazales psamófilos | J72: Caméfita | K72: https://florauruguaya.org/taxonomias/dysphania-retusa
A73: =VLOOKUP(especies_20260604_152756[[#This Row],[Column1]],output__33[[input_name_string]:[wfo_id2]],2,FALSE) -> wfo-0000692606 | B73: Hierba perenne | C73: Amaranthaceae | D73: Froelichia tomentosa (Mart.) Moq. | E73: Froelichia tomentosa | F73: (Mart.) Moq. | G73: Prodr. [A. P. de Candolle] 13(2): 421, 1849. | H73: Hierba perenne | I73: Herbazales psamófilos | J73: Hemicriptófita | K73: https://florauruguaya.org/taxonomias/froelichia-tomentosa
A74: =VLOOKUP(especies_20260604_152756[[#This Row],[Column1]],output__33[[input_name_string]:[wfo_id2]],2,FALSE) -> wfo-0000705896 | B74: Hierba perenne | C74: Amaranthaceae | D74: Gomphrena celosioides Mart. | E74: Gomphrena celosioides | F74: Mart. | G74: Nova Acta Phys.-Med. Acad. Caes. Leop.-Carol. Nat. Cur. 13: 301, 1826. | H74: Hierba perenne | I74: Ambientes ruderales, Ambientes urbanos, Algarrobales, Pastizales xerófilos, Pastizales mesófilos | K74: https://florauruguaya.org/taxonomias/gomphrena-celosioides
A75: =VLOOKUP(especies_20260604_152756[[#This Row],[Column1]],output__33[[input_name_string]:[wfo_id2]],2,FALSE) -> wfo-0000705978 | B75: Sufrútice | C75: Amaranthaceae | D75: Gomphrena elegans Mart. | E75: Gomphrena elegans | F75: Mart. | G75: Nov. Gen. Sp. Pl. [Martius] 2(1): 17, t. 119, 1826. | H75: Sufrútice | I75: Bosques ribereños, Matorrales mesófilos, Pastizales higrófilos | K75: https://florauruguaya.org/taxonomias/gomphrena-elegans
A76: =VLOOKUP(especies_20260604_152756[[#This Row],[Column1]],output__33[[input_name_string]:[wfo_id2]],2,FALSE) -> wfo-0000706038 | B76: Hierba perenne | C76: Amaranthaceae | D76: Gomphrena graminea Moq. | E76: Gomphrena graminea | F76: Moq. | G76: Prodr. [A. P. de Candolle] 13(2): 416, 1849. | H76: Hierba perenne | I76: Matorrales xerófilos, Pastizales xerófilos | J76: Hemicriptófita | K76: https://florauruguaya.org/taxonomias/gomphrena-graminea
A77: =VLOOKUP(especies_20260604_152756[[#This Row],[Column1]],output__33[[input_name_string]:[wfo_id2]],2,FALSE) -> wfo-0000706167 | B77: Hierba perenne | C77: Amaranthaceae | D77: Gomphrena perennis L. | E77: Gomphrena perennis | F77: L. | G77: Sp. Pl. [Linnaeus] 1: 224, 1753. | H77: Hierba perenne | I77: Palmares, Matorrales psamófilos, Pastizales xerófilos, Herbazales psamófilos | J77: Hemicriptófita | K77: https://florauruguaya.org/taxonomias/gomphrena-perennis
A78: =VLOOKUP(especies_20260604_152756[[#This Row],[Column1]],output__33[[input_name_string]:[wfo_id2]],2,FALSE) -> wfo-1000088132 | B78: Hierba perenne | C78: Amaranthaceae | D78: Gomphrena portulacoides (A.St.-Hil.) T.Ortuño & Borsch | E78: Gomphrena portulacoides | F78: (A.St.-Hil.) T.Ortuño & Borsch | G78: Willdenowia 50(3): 366, 2020. | H78: Hierba perenne | I78: Herbazales psamófilos | K78: https://florauruguaya.org/taxonomias/gomphrena-portulacoides
A79: =VLOOKUP(especies_20260604_152756[[#This Row],[Column1]],output__33[[input_name_string]:[wfo_id2]],2,FALSE) -> wfo-0000706206 | B79: Hierba perenne | C79: Amaranthaceae | D79: Gomphrena pulchella Mart. | E79: Gomphrena pulchella | F79: Mart. | G79: Nova Acta Phys.-Med. Acad. Caes. Leop.-Carol. Nat. Cur. 13: 302, 1826. | H79: Hierba perenne | I79: Algarrobales, Herbazales halófilos | J79: Hemicriptófita | K79: https://florauruguaya.org/taxonomias/gomphrena-pulchella
A80: =VLOOKUP(especies_20260604_152756[[#This Row],[Column1]],output__33[[input_name_string]:[wfo_id2]],2,FALSE) -> wfo-0000706261 | B80: Hierba perenne | C80: Amaranthaceae | D80: Gomphrena sellowiana Mart. | E80: Gomphrena sellowiana | F80: Mart. | G80: Nov. Gen. Sp. Pl. [Martius] 2(1): 15, t. 117, 1826. | H80: Hierba perenne | I80: Matorrales xerófilos | K80: https://florauruguaya.org/taxonomias/gomphrena-sellowiana
A81: =VLOOKUP(especies_20260604_152756[[#This Row],[Column1]],output__33[[input_name_string]:[wfo_id2]],2,FALSE) -> wfo-0000706303 | B81: Hierba perenne | C81: Amaranthaceae | D81: Gomphrena uruguayensis Suess. | E81: Gomphrena uruguayensis | F81: Suess. | G81: Lilloa 4: 130, 1939. | H81: Hierba perenne | I81: Pastizales xerófilos | K81: https://florauruguaya.org/taxonomias/gomphrena-uruguayensis
A82: =VLOOKUP(especies_20260604_152756[[#This Row],[Column1]],output__33[[input_name_string]:[wfo_id2]],2,FALSE) -> wfo-0000711756 | B82: Hierba perenne | C82: Amaranthaceae | D82: Guilleminea elongata Mears | E82: Guilleminea elongata | F82: Mears | G82: Sida 3: 145, 1967. | H82: Hierba perenne | I82: Pastizales xerófilos | J82: Caméfita | K82: https://florauruguaya.org/taxonomias/guilleminea-elongata
A83: =VLOOKUP(especies_20260604_152756[[#This Row],[Column1]],output__33[[input_name_string]:[wfo_id2]],2,FALSE) -> wfo-1000085903 | B83: Sufrútice | C83: Amaranthaceae | D83: Holmbergia tweediei (Moq.) Speg. | E83: Holmbergia tweediei | F83: (Moq.) Speg. | G83: Physis [Buenos Aires] 2: 178, 1916. | H83: Sufrútice | I83: Algarrobales, Matorrales mesófilos, Herbazales halófilos | J83: Caméfita | K83: https://florauruguaya.org/taxonomias/holmbergia-tweediei
A84: =VLOOKUP(especies_20260604_152756[[#This Row],[Column1]],output__33[[input_name_string]:[wfo_id2]],2,FALSE) -> wfo-0000732153 | B84: Hierba perenne | C84: Amaranthaceae | D84: Iresine diffusa Humb. & Bonpl. ex Willd. | E84: Iresine diffusa | F84: Humb. & Bonpl. ex Willd. | G84: Sp. Pl., ed. 4 [Willdenow] 4(2): 765, 1806. | H84: Hierba perenne | I84: Bosques ribereños, Algarrobales, Palmares, Matorrales mesófilos, Herbazales hidrófilos | J84: Caméfita | K84: https://florauruguaya.org/taxonomias/iresine-diffusa
A85: =VLOOKUP(especies_20260604_152756[[#This Row],[Column1]],output__33[[input_name_string]:[wfo_id2]],2,FALSE) -> wfo-1000085904 | B85: Hierba anual o bienal | C85: Amaranthaceae | D85: Oxybasis macrosperma (Hook.f.) S.Fuentes, Uotila & Borsch | E85: Oxybasis macrosperma | F85: (Hook.f.) S.Fuentes, Uotila & Borsch | G85: Willdenowia 42(1): 15, 2012. | H85: Hierba anual o bienal | I85: Herbazales halófilos | J85: Terófita | K85: https://florauruguaya.org/taxonomias/oxybasis-macrosperma
A86: =VLOOKUP(especies_20260604_152756[[#This Row],[Column1]],output__33[[input_name_string]:[wfo_id2]],2,FALSE) -> wfo-0000394259 | B86: Hierba perenne | C86: Amaranthaceae | D86: Pfaffia glomerata (Spreng.) Pedersen | E86: Pfaffia glomerata | F86: (Spreng.) Pedersen | G86: Darwiniana 14(2-3): 450, 1967. | H86: Hierba perenne | I86: Algarrobales, Matorrales mesófilos, Pastizales higrófilos | J86: Hemicriptófita | K86: https://florauruguaya.org/taxonomias/pfaffia-glomerata
A87: =VLOOKUP(especies_20260604_152756[[#This Row],[Column1]],output__33[[input_name_string]:[wfo_id2]],2,FALSE) -> wfo-0000394258 | B87: Hierba perenne | C87: Amaranthaceae | D87: Pfaffia gnaphalioides (L.f.) Mart. | E87: Pfaffia gnaphalioides | F87: (L.f.) Mart. | G87: Nov. Gen. Sp. Pl. [Martius] 2(1): 24, 1826. | H87: Hierba perenne | I87: Algarrobales, Palmares, Matorrales xerófilos, Matorrales psamófilos, Pastizales xerófilos, Pastizales mesófilos | J87: Hemicriptófita | K87: https://florauruguaya.org/taxonomias/pfaffia-gnaphalioides
A88: =VLOOKUP(especies_20260604_152756[[#This Row],[Column1]],output__33[[input_name_string]:[wfo_id2]],2,FALSE) -> wfo-0000394294 | B88: Hierba perenne | C88: Amaranthaceae | D88: Pfaffia ninae Pedersen | E88: Pfaffia ninae | F88: Pedersen | G88: Adansonia sér. 3, 19(2): 237, fig. 9, 1997. | H88: Hierba perenne | I88: Matorrales xerófilos, Pastizales xerófilos | K88: https://florauruguaya.org/taxonomias/pfaffia-ninae
A89: =VLOOKUP(especies_20260604_152756[[#This Row],[Column1]],output__33[[input_name_string]:[wfo_id2]],2,FALSE) -> wfo-0000737404 | B89: Hierba perenne | C89: Amaranthaceae | D89: Pfaffia tuberosa (Spreng.) Hicken | E89: Pfaffia tuberosa | F89: (Spreng.) Hicken | G89: Apuntes Hist. Nat. 2: 93, 1910. | H89: Hierba perenne | I89: Algarrobales, Palmares, Matorrales xerófilos, Matorrales psamófilos, Pastizales xerófilos, Pastizales mesófilos, Herbazales psamófilos | J89: Hemicriptófita | K89: https://florauruguaya.org/taxonomias/pfaffia-tuberosa
A90: =VLOOKUP(especies_20260604_152756[[#This Row],[Column1]],output__33[[input_name_string]:[wfo_id2]],2,FALSE) -> wfo-0000435495 | B90: Hierba perenne | C90: Amaranthaceae | D90: Salicornia ambigua Michx. | E90: Salicornia ambigua | F90: Michx. | G90: Fl. Bor. Amer. [Michaux] 1: 2, 1803. | H90: Hierba perenne | I90: Herbazales halófilos | J90: Caméfita | K90: https://florauruguaya.org/taxonomias/salicornia-ambigua
A91: =VLOOKUP(especies_20260604_152756[[#This Row],[Column1]],output__33[[input_name_string]:[wfo_id2]],2,FALSE) -> wfo-0000435928 | B91: Hierba anual o bienal | C91: Amaranthaceae | D91: Salsola kali L. | E91: Salsola kali | F91: L. | G91: Sp. Pl. [Linnaeus] 1: 222, 1753. | H91: Hierba anual o bienal | I91: Herbazales halófilos | J91: Terófita | K91: https://florauruguaya.org/taxonomias/salsola-kali
A92: =VLOOKUP(especies_20260604_152756[[#This Row],[Column1]],output__33[[input_name_string]:[wfo_id2]],2,FALSE) -> wfo-0000756802 | B92: Hierba perenne | C92: Amaryllidaceae | D92: Allium neapolitanum Cirillo | E92: Allium neapolitanum | F92: Cirillo | G92: Pl. Rar. Neapol. 1: 13, 1788. | H92: Hierba perenne | I92: Ambientes urbanos | J92: Geófita | K92: https://florauruguaya.org/taxonomias/allium-neapolitanum
A93: =VLOOKUP(especies_20260604_152756[[#This Row],[Column1]],output__33[[input_name_string]:[wfo_id2]],2,FALSE) -> wfo-0000757618 | B93: Hierba perenne | C93: Amaryllidaceae | D93: Allium triquetrum L. | E93: Allium triquetrum | F93: L. | G93: Sp. Pl. [Linnaeus] 1: 300, 1753. | H93: Hierba perenne | I93: Ambientes urbanos | J93: Geófita | K93: https://florauruguaya.org/taxonomias/allium-triquetrum
A94: =VLOOKUP(especies_20260604_152756[[#This Row],[Column1]],output__33[[input_name_string]:[wfo_id2]],2,FALSE) -> wfo-0000757711 | B94: Hierba perenne | C94: Amaryllidaceae | D94: Allium vineale L. | E94: Allium vineale | F94: L. | G94: Sp. Pl. [Linnaeus] 1: 299, 1753. | H94: Hierba perenne | I94: Ambientes ruderales | J94: Geófita | K94: https://florauruguaya.org/taxonomias/allium-vineale
A95: =VLOOKUP(especies_20260604_152756[[#This Row],[Column1]],output__33[[input_name_string]:[wfo_id2]],2,FALSE) -> wfo-0000759455 | B95: Hierba perenne | C95: Amaryllidaceae | D95: Amaryllis belladonna L. | E95: Amaryllis belladonna | F95: L. | G95: Sp. Pl. [Linnaeus] 1: 293, 1753. | H95: Hierba perenne | I95: Ambientes ruderales, Ambientes urbanos | J95: Geófita | K95: https://florauruguaya.org/taxonomias/amaryllis-belladonna
A96: =VLOOKUP(especies_20260604_152756[[#This Row],[Column1]],output__33[[input_name_string]:[wfo_id2]],2,FALSE) -> wfo-0000764603 | B96: Hierba perenne | C96: Amaryllidaceae | D96: Crinum moorei Hook.f. | E96: Crinum moorei | F96: Hook.f. | G96: Bot. Mag. 100: t. 6113, 1874. | H96: Hierba perenne | I96: Ambientes ruderales, Ambientes urbanos | J96: Geófita | K96: https://florauruguaya.org/taxonomias/crinum-moorei
A97: =VLOOKUP(especies_20260604_152756[[#This Row],[Column1]],output__33[[input_name_string]:[wfo_id2]],2,FALSE) -> wfo-0000659388 | B97: Hierba perenne | C97: Amaryllidaceae | D97: Hippeastrum angustifolium Pax | E97: Hippeastrum angustifolium | F97: Pax | G97: Bot. Jahrb. Syst. 11(3): 331, 1889. | H97: Hierba perenne | I97: Herbazales hidrófilos | J97: Geófita | K97: https://florauruguaya.org/taxonomias/hippeastrum-angustifolium
A98: =VLOOKUP(especies_20260604_152756[[#This Row],[Column1]],output__33[[input_name_string]:[wfo_id2]],2,FALSE) -> wfo-0000661646 | B98: Hierba perenne | C98: Amaryllidaceae | D98: Hippeastrum striatum (Lam.) H.E.Moore | E98: Hippeastrum striatum | F98: (Lam.) H.E.Moore | G98: Baileya 11: 16, 1963. | H98: Hierba perenne | I98: Bosques ribereños | J98: Geófita | K98: https://florauruguaya.org/taxonomias/hippeastrum-striatum
A99: =VLOOKUP(especies_20260604_152756[[#This Row],[Column1]],output__33[[input_name_string]:[wfo_id2]],2,FALSE) -> wfo-0000661874 | B99: Hierba perenne | C99: Amaryllidaceae | D99: Hippeastrum vittatum (L&#39;Hér.) Herb. | E99: Hippeastrum vittatum | F99: (L&#39;Hér.) Herb. | G99: Appendix [Herbert] 31, 1821. | H99: Hierba perenne | I99: Bosques de quebradas | J99: Geófita | K99: https://florauruguaya.org/taxonomias/hippeastrum-vittatum
A100: =VLOOKUP(especies_20260604_152756[[#This Row],[Column1]],output__33[[input_name_string]:[wfo_id2]],2,FALSE) -> wfo-0000672323 | B100: Hierba perenne | C100: Amaryllidaceae | D100: Ipheion recurvifolium (C.H.Wright) Traub | E100: Ipheion recurvifolium | F100: (C.H.Wright) Traub | G100: Pl. Life (Stanford) 9: 69, 1953. | H100: Hierba perenne | I100: Pastizales xerófilos, Pastizales mesófilos | J100: Geófita | K100: https://florauruguaya.org/taxonomias/ipheion-recurvifolium
... A102: =VLOOKUP(especies_20260604_152756[[#This Row],[Column1]],output__33[[input_name_string]:[wfo_id2]],2,FALSE) -> wfo-0001072921 | B102: Hierba perenne | C102: Amaryllidaceae | D102: Ipheion uniflorum (Graham) Raf. | E102: Ipheion uniflorum | F102: (Graham) Raf. | G102: Fl. Tellur. 2: 12, 1837. | H102: Hierba perenne | I102: Ambientes urbanos, Matorrales xerófilos, Matorrales mesófilos, Pastizales xerófilos, Pastizales mesófilos | J102: Geófita | K102: https://florauruguaya.org/taxonomias/ipheion-uniflorum
A103: =VLOOKUP(especies_20260604_152756[[#This Row],[Column1]],output__33[[input_name_string]:[wfo_id2]],2,FALSE) -> wfo-0000700066 | B103: Hierba perenne | C103: Amaryllidaceae | D103: Narcissus tazetta L. | E103: Narcissus tazetta | F103: L. | G103: Fam. Pl. [Adanson] 1: 290, 1753. | H103: Hierba perenne | I103: Ambientes urbanos | K103: https://florauruguaya.org/taxonomias/narcissus-tazetta
A104: =VLOOKUP(especies_20260604_152756[[#This Row],[Column1]],output__33[[input_name_string]:[wfo_id2]],2,FALSE) -> wfo-0000699293 | B104: Hierba perenne | C104: Amaryllidaceae | D104: Nothoscordum arenarium Herter | E104: Nothoscordum arenarium | F104: Herter | G104: Revista Sudamer. Bot. 2: 126, 1935. | H104: Hierba perenne | I104: Bosques ribereños, Herbazales psamófilos | J104: Geófita | K104: https://florauruguaya.org/taxonomias/nothoscordum-arenarium
...

Sheet especies_20260407_163427
A1: Column1 | B1: Column2 | C1: Column3 | D1: Column4 | E1: Column5 | F1: Column6 | G1: Column7 | H1: Column8
A2: Familia | B2: Nombre | C2: Autor | D2: Pub. | E2: Hábito | F2: Formaciones vegetales | G2: Forma de vida | H2: Link stand alone
A3: Acanthaceae | B3: Dicliptera squarrosa | C3: Nees | D3: Fl. Bras. [Martius] 9: 161, 1847. | E3: Sufrútice | F3: Bosques ribereños, Algarrobales, Matorrales mesófilos, Matorrales psamófilos, Pastizales xerófilos | G3: Caméfita | H3: https://florauruguaya.org/taxonomias/dicliptera-squarrosa
A4: Acanthaceae | B4: Dyschoriste humilis | C4: (Nees) Lindau | D4: Bot. Jahrb. Syst. 19(4): 15, 1894. | E4: Hierba perenne | F4: Algarrobales, Matorrales xerófilos, Pastizales xerófilos | G4: Caméfita | H4: https://florauruguaya.org/taxonomias/dyschoriste-humilis
A5: Acanthaceae | B5: Dyschoriste hygrophiloides | C5: (Nees) Kuntze | D5: Revis. Gen. Pl. 2: 486, 1891. | E5: Hierba perenne | F5: Pastizales xerófilos, Pastizales mesófilos | H5: https://florauruguaya.org/taxonomias/dyschoriste-hygrophiloides
A6: Acanthaceae | B6: Hygrophila costata | C6: Nees & T.Nees | D6: Pl. Hort. Bonn. Icon. 7, t. 3, 1824. | E6: Hierba perenne | F6: Bosques ribereños, Bosques higrófilos, Algarrobales, Palmares, Herbazales hidrófilos | G6: Caméfita | H6: https://florauruguaya.org/taxonomias/hygrophila-costata
A7: Acanthaceae | B7: Hygrophila guianensis | C7: Nees | D7: London J. Bot. 4: 634, 1845. | E7: Hierba perenne | F7: Bosques ribereños | H7: https://florauruguaya.org/taxonomias/hygrophila-guianensis
A8: Acanthaceae | B8: Justicia axillaris | C8: (Nees) Lindau | D8: Nat. Pflanzenfam. [Engler & Prantl] 4(3b): 350, 1895. | E8: Hierba perenne | F8: Matorrales xerófilos, Pastizales xerófilos | H8: https://florauruguaya.org/taxonomias/justicia-axillaris
A9: Acanthaceae | B9: Justicia brasiliana | C9: Roth | D9: Nov. Pl. Sp. 17, 1821. | E9: Sufrútice | F9: Bosques de quebradas, Bosques ribereños | G9: Caméfita | H9: https://florauruguaya.org/taxonomias/justicia-brasiliana
A10: Acanthaceae | B10: Justicia comata | C10: (L.) Lam. | D10: Encycl. [J. Lamarck & al.] 1(2): 632, 1785. | E10: Hierba perenne | F10: Bosques ribereños, Herbazales hidrófilos | G10: Caméfita | H10: https://florauruguaya.org/taxonomias/justicia-comata
A11: Acanthaceae | B11: Justicia laevilinguis | C11: (Nees) Lindau | D11: Bot. Jahrb. Syst. 19(4): 20, 1894. | E11: Hierba perenne | F11: Algarrobales, Pastizales higrófilos, Herbazales hidrófilos | G11: Caméfita | H11: https://florauruguaya.org/taxonomias/justicia-laevilinguis
A12: Acanthaceae | B12: Justicia oblonga | C12: (Nees) Lindau | D12: Nat. Pflanzenfam. [Engler & Prantl] 4(3b): 350, 1895. | E12: Hierba perenne | F12: Bosques ribereños | H12: https://florauruguaya.org/taxonomias/justicia-oblonga
A13: Acanthaceae | B13: Justicia polygaloides | C13: (S.Moore) Lindau | D13: Bull. Herb. Boissier 2(3): 633, 1933. | E13: Hierba perenne | F13: Pastizales higrófilos | H13: https://florauruguaya.org/taxonomias/justicia-polygaloides
A14: Acanthaceae | B14: Justicia tweedieana | C14: (Nees) Griseb. | D14: Abh. Königl. Ges. Wiss. Göttingen 19: 225, 1874. | E14: Arbusto | F14: Algarrobales, Pastizales xerófilos, Herbazales halófilos | G14: Nanofanerófita | H14: https://florauruguaya.org/taxonomias/justicia-tweedieana
A15: Acanthaceae | B15: Poikilacanthus glandulosus | C15: (Nees) Ariza | D15: Kurtziana 17: 159, 1984. | E15: Arbusto | F15: Bosques ribereños, Matorrales mesófilos | G15: Nanofanerófita | H15: https://florauruguaya.org/taxonomias/poikilacanthus-glandulosus
A16: Acanthaceae | B16: Ruellia angustiflora | C16: (Nees) Lindau ex Rambo | D16: Iheringia, Bot. 12: 23, 1964. | E16: Arbusto | F16: Bosques de quebradas | G16: Nanofanerófita | H16: https://florauruguaya.org/taxonomias/ruellia-angustiflora
A17: Acanthaceae | B17: Ruellia hygrophila | C17: Mart. | D17: Flora 24(2): 65, 1841. | E17: Hierba perenne | F17: Matorrales xerófilos, Herbazales hidrófilos | G17: Hemicriptófita | H17: https://florauruguaya.org/taxonomias/ruellia-hygrophila
A18: Acanthaceae | B18: Ruellia hypericoides | C18: (Nees) Lindau | D18: Bot. Jahrb. Syst. 19(4): 16, 1894. | E18: Hierba perenne | F18: Pastizales xerófilos | G18: Hemicriptófita | H18: https://florauruguaya.org/taxonomias/ruellia-hypericoides
A19: Acanthaceae | B19: Ruellia morongii | C19: Britton | D19: Ann. New York Acad. Sci. 7: 192, 1893. | E19: Hierba perenne | F19: Pastizales xerófilos, Pastizales mesófilos | G19: Hemicriptófita | H19: https://florauruguaya.org/taxonomias/ruellia-morongii
A20: Acanthaceae | B20: Ruellia simplex | C20: C.Wright | D20: Anales Acad. Ci. Méd. Habana 6(41): 321, 1870. | E20: Hierba perenne | F20: Bosques ribereños, Algarrobales, Pastizales higrófilos, Herbazales halófilos | G20: Caméfita | H20: https://florauruguaya.org/taxonomias/ruellia-simplex
A21: Acanthaceae | B21: Stenandrium diphyllum | C21: Nees | D21: Fl. Bras. [Martius] 9: 75, 1847. | E21: Hierba perenne | F21: Matorrales xerófilos, Pastizales xerófilos | G21: Hemicriptófita | H21: https://florauruguaya.org/taxonomias/stenandrium-diphyllum
A22: Acanthaceae | B22: Stenandrium dulce | C22: (Cav.) Nees | D22: Prodr. [A. P. de Candolle] 11: 282, 1847. | E22: Hierba perenne | F22: Algarrobales, Palmares, Pastizales xerófilos, Pastizales mesófilos, Herbazales halófilos | G22: Hemicriptófita | H22: https://florauruguaya.org/taxonomias/stenandrium-dulce
A23: Acanthaceae | B23: Thyrsacanthus sulcatus | C23: (Nees) C.Ezcurra & A.L.A.Côrtes | D23: Phytotaxa 395(2): 85, 2019. | E23: Hierba perenne | F23: Algarrobales, Herbazales halófilos | H23: https://florauruguaya.org/taxonomias/thyrsacanthus-sulcatus
A24: Achatocarpaceae | B24: Achatocarpus praecox | C24: Griseb. | D24: Abh. Königl. Ges. Wiss. Göttingen 24: 32, 1879. | E24: Árbol | F24: Algarrobales | G24: Fanerófita | H24: https://florauruguaya.org/taxonomias/achatocarpus-praecox
A25: Aizoaceae | B25: Carpobrotus edulis | C25: (L.) N.E.Br. | D25: Gen. S. Afr. Fl. Pl. 249, 1926. | E25: Hierba perenne | F25: Ambientes urbanos, Matorrales psamófilos, Pastizales xerófilos, Herbazales psamófilos | G25: Caméfita | H25: https://florauruguaya.org/taxonomias/carpobrotus-edulis
A26: Aizoaceae | B26: Lampranthus multiradiatus | C26: (Jacq.) N.E.Br. | D26: Gard. Chron. 3(87): 71, 1830. | E26: Sufrútice | F26: Herbazales psamófilos | H26: https://florauruguaya.org/taxonomias/lampranthus-multiradiatus
A27: Aizoaceae | B27: Sesuvium sessile | C27: Pers. | D27: Syn. Pl. [Persoon] 2(1): 39, 1806. | E27: Hierba perenne | F27: Ambientes urbanos, Herbazales halófilos | G27: Caméfita | H27: https://florauruguaya.org/taxonomias/sesuvium-sessile
A28: Aizoaceae | B28: Tetragonia tetragonoides | C28: (Pall.) Kuntze | D28: Revis. Gen. Pl. 1: 264, 1891. | E28: Hierba perenne | F28: Herbazales hidrófilos | G28: Caméfita | H28: https://florauruguaya.org/taxonomias/tetragonia-tetragonoides
A29: Alismataceae | B29: Alisma plantago-aquatica | C29: L. | D29: Sp. Pl. [Linnaeus] 1: 342, 1753. | E29: Hierba perenne | F29: Dulce y salobre | H29: https://florauruguaya.org/taxonomias/alisma-plantago-aquatica
A30: Alismataceae | B30: Echinodorus floribundus | C30: (Seub.) Seub. ex Warm. | D30: Vidensk. Meddel. Naturhist. Foren. Kjøbenhavn 1872: 113, 1872. | E30: Hierba perenne | F30: Herbazales hidrófilos | G30: Hemicriptófita | H30: https://florauruguaya.org/taxonomias/echinodorus-floribundus
A31: Alismataceae | B31: Echinodorus grandiflorus | C31: (Cham. & Schltdl.) Micheli | D31: Monogr. Phan. [A.DC. & C.DC.] 3: 57, 1881. | E31: Hierba perenne | F31: Bosques higrófilos, Algarrobales, Palmares, Herbazales hidrófilos, Dulce y salobre | G31: Hemicriptófita | H31: https://florauruguaya.org/taxonomias/echinodorus-grandiflorus
A32: Alismataceae | B32: Echinodorus longiscapus | C32: Arechav. | D32: Anales Mus. Nac. Montevideo 4(1): 67, pl. 2, 1903. | E32: Hierba perenne | F32: Pastizales higrófilos, Herbazales hidrófilos | G32: Hemicriptófita | H32: https://florauruguaya.org/taxonomias/echinodorus-longiscapus
A33: Alismataceae | B33: Echinodorus uruguayensis | C33: Arechav. | D33: Anales Mus. Nac. Montevideo 4(1): 66, pl. 2, 1903. | E33: Hierba perenne | F33: Dulce y salobre | G33: Hemicriptófita | H33: https://florauruguaya.org/taxonomias/echinodorus-uruguayensis
A34: Alismataceae | B34: Helanthium tenellum | C34: (Mart. ex Schult.f.) Britton | D34: Man. Fl. N. States [Britton], ed. 2. 54, 1905. | E34: Hierba anual o bienal | F34: Pastizales higrófilos, Herbazales hidrófilos, Dulce y salobre | G34: Terófita | H34: https://florauruguaya.org/taxonomias/helanthium-tenellum
A35: Alismataceae | B35: Hydrocleys nymphoides | C35: (Humb. & Bonpl. ex Willd.) Buchenau | D35: Abh. Naturwiss. Vereins Bremen 2: 2, 1871. | E35: Hierba perenne | F35: Pastizales higrófilos, Herbazales hidrófilos, Dulce y salobre | G35: Hidrófita | H35: https://florauruguaya.org/taxonomias/hydrocleys-nymphoides
A36: Alismataceae | B36: Hydrocleys uruguayensis | C36: (Buchenau) Pedersen | D36: Bot. Tidsskr. 57: 41, 1961. | E36: Hierba perenne | F36: Herbazales hidrófilos, Dulce y salobre | H36: https://florauruguaya.org/taxonomias/hydrocleys-uruguayensis
A37: Alismataceae | B37: Sagittaria montevidensis | C37: Cham. & Schltdl. | D37: Linnaea 2: 2, 156, 1827. | E37: Hierba perenne | F37: Algarrobales, Herbazales hidrófilos, Dulce y salobre | G37: Hidrófita | H37: https://florauruguaya.org/taxonomias/sagittaria-montevidensis
A38: Alstroemeriaceae | B38: Alstroemeria isabellana | C38: Herb. | D38: Amaryllidaceae 88, t. 6, f. 4-6, 1837. | E38: Hierba perenne | F38: Bosques higrófilos, Pastizales higrófilos | G38: Hemicriptófita | H38: https://florauruguaya.org/taxonomias/alstroemeria-isabellana
A39: Alstroemeriaceae | B39: Alstroemeria psittacina | C39: Lehm. | D39: Sem. Hort. Bot. Hamburg. 1826: 17, 1826. | E39: Hierba perenne | F39: Bosques ribereños | G39: Hemicriptófita | H39: https://florauruguaya.org/taxonomias/alstroemeria-psittacina
A40: Amaranthaceae | B40: Alternanthera kurtzii | C40: Schinz ex Pedersen | D40: Darwiniana 14(2-3): 435, 1967. | E40: Hierba perenne | F40: Bosques ribereños, Algarrobales, Pastizales higrófilos | H40: https://florauruguaya.org/taxonomias/alternanthera-kurtzii
A41: Amaranthaceae | B41: Alternanthera paronychioides | C41: A.St.-Hil. | D41: Voy. Distr. Diam. 2: 439, 1833. | E41: Hierba perenne | F41: Pastizales higrófilos | G41: Caméfita | H41: https://florauruguaya.org/taxonomias/alternanthera-paronychioides
A42: Amaranthaceae | B42: Alternanthera philoxeroides | C42: (Mart.) Griseb. | D42: Abh. Königl. Ges. Wiss. Göttingen 24: 36, 1879. | E42: Hierba perenne | F42: Bosques ribereños, Bosques higrófilos, Palmares, Pastizales higrófilos, Herbazales hidrófilos, Dulce y salobre | G42: Caméfita | H42: https://florauruguaya.org/taxonomias/alternanthera-philoxeroides
A43: Amaranthaceae | B43: Alternanthera pungens | C43: Kunth | D43: Nov. Gen. Sp. [H.B.K.] 2: 206, 1818. | E43: Hierba perenne | F43: Ambientes ruderales | G43: Caméfita | H43: https://florauruguaya.org/taxonomias/alternanthera-pungens
A44: Amaranthaceae | B44: Alternanthera reineckii | C44: Briq. | D44: Annuaire Conserv. Jard. Bot. Genève 3: 151, 1899. | E44: Hierba anual o bienal | F44: Bosques ribereños, Algarrobales | G44: Terófita | H44: https://florauruguaya.org/taxonomias/alternanthera-reineckii
A45: Amaranthaceae | B45: Amaranthus albus | C45: L. | D45: Syst. Nat., ed. 10. 2: 1268, 1759. | E45: Hierba anual o bienal | F45: Ambientes ruderales | G45: Terófita | H45: https://florauruguaya.org/taxonomias/amaranthus-albus
A46: Amaranthaceae | B46: Amaranthus blitum | C46: L. | D46: Sp. Pl. [Linnaeus] 2: 990, 1753. | E46: Hierba anual o bienal | F46: Herbazales psamófilos | G46: Terófita | H46: https://florauruguaya.org/taxonomias/amaranthus-blitum
A47: Amaranthaceae | B47: Amaranthus crispus | C47: (Lesp. & Thévenau) A.Braun ex S.Watson & J.M.Coult. | D47: Manual (Gray), ed. 6. 428, 1890. | E47: Hierba anual o bienal | F47: Pastizales mesófilos, Herbazales psamófilos | G47: Terófita | H47: https://florauruguaya.org/taxonomias/amaranthus-crispus
A48: Amaranthaceae | B48: Amaranthus deflexus | C48: L. | D48: Mant. Pl. Altera 295, 1771. | E48: Hierba perenne | F48: Ambientes ruderales, Ambientes urbanos, Palmares | G48: Caméfita | H48: https://florauruguaya.org/taxonomias/amaranthus-deflexus
A49: Amaranthaceae | B49: Amaranthus hybridus | C49: L. | D49: Sp. Pl. [Linnaeus] 2: 990, 1753. | E49: Hierba anual o bienal | F49: Ambientes ruderales | G49: Terófita | H49: https://florauruguaya.org/taxonomias/amaranthus-hybridus
A50: Amaranthaceae | B50: Amaranthus lombardoi | C50: Hunz. | D50: Bol. Soc. Argent. Bot. 4: 141, fig. 4, 1951. | E50: Hierba anual o bienal | F50: Herbazales hidrófilos | G50: Terófita | H50: https://florauruguaya.org/taxonomias/amaranthus-lombardoi
A51: Amaranthaceae | B51: Amaranthus muricatus | C51: (Moq.) Hieron. | D51: Bol. Acad. Nac. Ci. 4(2): 421, 1882. | E51: Hierba perenne | F51: Ambientes ruderales, Ambientes urbanos, Algarrobales | G51: Caméfita | H51: https://florauruguaya.org/taxonomias/amaranthus-muricatus
A52: Amaranthaceae | B52: Amaranthus palmeri | C52: S.Watson | D52: Proc. Amer. Acad. Arts 12: 274, 1877. | E52: Hierba anual o bienal | F52: Ambientes ruderales | G52: Terófita | H52: https://florauruguaya.org/taxonomias/amaranthus-palmeri
... A55: Amaranthaceae | B55: Amaranthus standleyanus | C55: Parodi ex Covas | D55: Darwiniana 5: 339, 1941. | E55: Hierba anual o bienal | F55: Ambientes urbanos, Algarrobales | G55: Terófita | H55: https://florauruguaya.org/taxonomias/amaranthus-standleyanus
A56: Amaranthaceae | B56: Amaranthus tuberculatus | C56: (Moq.) J.D.Sauer | D56: Madroño 13: 18, 1955. | E56: Hierba anual o bienal | G56: Terófita | H56: https://florauruguaya.org/taxonomias/amaranthus-tuberculatus
A57: Amaranthaceae | B57: Amaranthus viridis | C57: L. | D57: Sp. Pl., ed. 2. 2: 1405, 1763. | E57: Hierba anual o bienal | F57: Ambientes ruderales, Ambientes urbanos | G57: Terófita | H57: https://florauruguaya.org/taxonomias/amaranthus-viridis
A58: Amaranthaceae | B58: Amaranthus vulgatissimus | C58: Speg. | D58: Anales Soc. Ci. Argent. 53(1): 281, 1902. | E58: Hierba perenne | F58: Algarrobales | G58: Caméfita | H58: https://florauruguaya.org/taxonomias/amaranthus-vulgatissimus
A59: Amaranthaceae | B59: Atriplex montevidensis | C59: Spreng. | D59: Syst. Veg., ed. 16 [Sprengel] 3: 918, 1826. | E59: Hierba perenne | F59: Algarrobales, Herbazales halófilos | G59: Caméfita | H59: https://florauruguaya.org/taxonomias/atriplex-montevidensis
A60: Amaranthaceae | B60: Atriplex patula | C60: L. | D60: Sp. Pl. [Linnaeus] 2: 1053, 1753. | E60: Hierba anual o bienal | F60: Herbazales halófilos | G60: Terófita | H60: https://florauruguaya.org/taxonomias/atriplex-patula
A61: Amaranthaceae | B61: Atriplex prostrata | C61: Boucher ex DC. | D61: Fl. Franç. [de Candolle & Lamarck], ed. 3. 3: 387, 1805. | E61: Hierba anual o bienal | F61: Herbazales halófilos | G61: Terófita | H61: https://florauruguaya.org/taxonomias/atriplex-prostrata
A62: Amaranthaceae | B62: Bassia scoparia | C62: (L.) A.J.Scott | D62: Feddes Repert. 89(2-3): 108, 1978. | E62: Hierba anual o bienal | F62: Ambientes ruderales | G62: Terófita | H62: https://florauruguaya.org/taxonomias/bassia-scoparia
A63: Amaranthaceae | B63: Beta vulgaris | C63: L. | D63: Sp. Pl. [Linnaeus] 1: 222, 1753. | E63: Hierba perenne | F63: Ambientes urbanos | G63: Caméfita | H63: https://florauruguaya.org/taxonomias/beta-vulgaris
A64: Amaranthaceae | B64: Chenopodiastrum murale | C64: (L.) S.Fuentes, Uotila & Borsch | D64: Willdenowia 42(1): 14, 2012. | E64: Hierba anual o bienal | F64: Ambientes ruderales, Ambientes urbanos | G64: Terófita | H64: https://florauruguaya.org/taxonomias/chenopodiastrum-murale
A65: Amaranthaceae | B65: Chenopodium album | C65: L. | D65: Sp. Pl. [Linnaeus] 1: 219, 1753. | E65: Hierba anual o bienal | F65: Ambientes urbanos | G65: Terófita | H65: https://florauruguaya.org/taxonomias/chenopodium-album
A66: Amaranthaceae | B66: Chenopodium giganteum | C66: D.Don | D66: Prodr. Fl. Nepal. 75, 1825. | E66: Hierba anual o bienal | F66: Ambientes ruderales | G66: Terófita | H66: https://florauruguaya.org/taxonomias/chenopodium-giganteum
A67: Amaranthaceae | B67: Chenopodium hircinum | C67: Schrad. | D67: Index Seminum [Gottingen] 1833: 2, 1833. | E67: Hierba anual o bienal | F67: Ambientes ruderales, Ambientes urbanos | G67: Terófita | H67: https://florauruguaya.org/taxonomias/chenopodium-hircinum
A68: Amaranthaceae | B68: Dysphania ambrosioides | C68: (L.) Mosyakin & Clemants | D68: Ukrayins&#39;k. Bot. Zhurn. 59(4): 382, 2002. | E68: Hierba perenne | F68: Ambientes ruderales, Ambientes urbanos, Algarrobales, Palmares, Pastizales xerófilos, Pastizales mesófilos | H68: https://florauruguaya.org/taxonomias/dysphania-ambrosioides
A69: Amaranthaceae | B69: Dysphania bonariensis | C69: (Hook.f.) Mosyakin & Clemants ex Sukhor. | D69: Willdenowia 42(2): 175, 2012. | E69: Hierba perenne | F69: Pastizales xerófilos | G69: Caméfita | H69: https://florauruguaya.org/taxonomias/dysphania-bonariensis
A70: Amaranthaceae | B70: Dysphania burkartii | C70: (Aellen) Mosyakin & Clemants | D70: J. Bot. Res. Inst. Texas 2(1): 428, 2008. | E70: Hierba perenne | F70: Matorrales xerófilos, Pastizales xerófilos | G70: Caméfita | H70: https://florauruguaya.org/taxonomias/dysphania-burkartii
A71: Amaranthaceae | B71: Dysphania multifida | C71: (L.) Mosyakin & Clemants | D71: Ukrayins&#39;k. Bot. Zhurn. 59(4): 382, 2002. | E71: Hierba perenne | F71: Ambientes ruderales, Ambientes urbanos | G71: Caméfita | H71: https://florauruguaya.org/taxonomias/dysphania-multifida
A72: Amaranthaceae | B72: Dysphania retusa | C72: (Moq.) Mosyakin & Clemants | D72: J. Bot. Res. Inst. Texas 2(1): 428, 2008. | E72: Hierba perenne | F72: Herbazales psamófilos | G72: Caméfita | H72: https://florauruguaya.org/taxonomias/dysphania-retusa
A73: Amaranthaceae | B73: Froelichia tomentosa | C73: (Mart.) Moq. | D73: Prodr. [A. P. de Candolle] 13(2): 421, 1849. | E73: Hierba perenne | F73: Herbazales psamófilos | G73: Hemicriptófita | H73: https://florauruguaya.org/taxonomias/froelichia-tomentosa
A74: Amaranthaceae | B74: Gomphrena celosioides | C74: Mart. | D74: Nova Acta Phys.-Med. Acad. Caes. Leop.-Carol. Nat. Cur. 13: 301, 1826. | E74: Hierba perenne | F74: Ambientes ruderales, Ambientes urbanos, Algarrobales, Pastizales xerófilos, Pastizales mesófilos | H74: https://florauruguaya.org/taxonomias/gomphrena-celosioides
A75: Amaranthaceae | B75: Gomphrena elegans | C75: Mart. | D75: Nov. Gen. Sp. Pl. [Martius] 2(1): 17, t. 119, 1826. | E75: Sufrútice | F75: Bosques ribereños, Matorrales mesófilos, Pastizales higrófilos | H75: https://florauruguaya.org/taxonomias/gomphrena-elegans
A76: Amaranthaceae | B76: Gomphrena graminea | C76: Moq. | D76: Prodr. [A. P. de Candolle] 13(2): 416, 1849. | E76: Hierba perenne | F76: Matorrales xerófilos, Pastizales xerófilos | G76: Hemicriptófita | H76: https://florauruguaya.org/taxonomias/gomphrena-graminea
A77: Amaranthaceae | B77: Gomphrena perennis | C77: L. | D77: Sp. Pl. [Linnaeus] 1: 224, 1753. | E77: Hierba perenne | F77: Palmares, Matorrales psamófilos, Pastizales xerófilos, Herbazales psamófilos | G77: Hemicriptófita | H77: https://florauruguaya.org/taxonomias/gomphrena-perennis
A78: Amaranthaceae | B78: Gomphrena portulacoides | C78: (A.St.-Hil.) T.Ortuño & Borsch | D78: Willdenowia 50(3): 366, 2020. | E78: Hierba perenne | F78: Herbazales psamófilos | H78: https://florauruguaya.org/taxonomias/gomphrena-portulacoides
A79: Amaranthaceae | B79: Gomphrena pulchella | C79: Mart. | D79: Nova Acta Phys.-Med. Acad. Caes. Leop.-Carol. Nat. Cur. 13: 302, 1826. | E79: Hierba perenne | F79: Algarrobales, Herbazales halófilos | G79: Hemicriptófita | H79: https://florauruguaya.org/taxonomias/gomphrena-pulchella
A80: Amaranthaceae | B80: Gomphrena sellowiana | C80: Mart. | D80: Nov. Gen. Sp. Pl. [Martius] 2(1): 15, t. 117, 1826. | E80: Hierba perenne | F80: Matorrales xerófilos | H80: https://florauruguaya.org/taxonomias/gomphrena-sellowiana
A81: Amaranthaceae | B81: Gomphrena uruguayensis | C81: Suess. | D81: Lilloa 4: 130, 1939. | E81: Hierba perenne | F81: Pastizales xerófilos | H81: https://florauruguaya.org/taxonomias/gomphrena-uruguayensis
A82: Amaranthaceae | B82: Guilleminea elongata | C82: Mears | D82: Sida 3: 145, 1967. | E82: Hierba perenne | F82: Pastizales xerófilos | G82: Caméfita | H82: https://florauruguaya.org/taxonomias/guilleminea-elongata
A83: Amaranthaceae | B83: Holmbergia tweediei | C83: (Moq.) Speg. | D83: Physis [Buenos Aires] 2: 178, 1916. | E83: Sufrútice | F83: Algarrobales, Matorrales mesófilos, Herbazales halófilos | G83: Caméfita | H83: https://florauruguaya.org/taxonomias/holmbergia-tweediei
A84: Amaranthaceae | B84: Iresine diffusa | C84: Humb. & Bonpl. ex Willd. | D84: Sp. Pl., ed. 4 [Willdenow] 4(2): 765, 1806. | E84: Hierba perenne | F84: Bosques ribereños, Algarrobales, Palmares, Matorrales mesófilos, Herbazales hidrófilos | G84: Caméfita | H84: https://florauruguaya.org/taxonomias/iresine-diffusa
A85: Amaranthaceae | B85: Oxybasis macrosperma | C85: (Hook.f.) S.Fuentes, Uotila & Borsch | D85: Willdenowia 42(1): 15, 2012. | E85: Hierba anual o bienal | F85: Herbazales halófilos | G85: Terófita | H85: https://florauruguaya.org/taxonomias/oxybasis-macrosperma
A86: Amaranthaceae | B86: Pfaffia glomerata | C86: (Spreng.) Pedersen | D86: Darwiniana 14(2-3): 450, 1967. | E86: Hierba perenne | F86: Algarrobales, Matorrales mesófilos, Pastizales higrófilos | G86: Hemicriptófita | H86: https://florauruguaya.org/taxonomias/pfaffia-glomerata
A87: Amaranthaceae | B87: Pfaffia gnaphalioides | C87: (L.f.) Mart. | D87: Nov. Gen. Sp. Pl. [Martius] 2(1): 24, 1826. | E87: Hierba perenne | F87: Algarrobales, Palmares, Matorrales xerófilos, Matorrales psamófilos, Pastizales xerófilos, Pastizales mesófilos | G87: Hemicriptófita | H87: https://florauruguaya.org/taxonomias/pfaffia-gnaphalioides
A88: Amaranthaceae | B88: Pfaffia ninae | C88: Pedersen | D88: Adansonia sér. 3, 19(2): 237, fig. 9, 1997. | E88: Hierba perenne | F88: Matorrales xerófilos, Pastizales xerófilos | H88: https://florauruguaya.org/taxonomias/pfaffia-ninae
A89: Amaranthaceae | B89: Pfaffia tuberosa | C89: (Spreng.) Hicken | D89: Apuntes Hist. Nat. 2: 93, 1910. | E89: Hierba perenne | F89: Algarrobales, Palmares, Matorrales xerófilos, Matorrales psamófilos, Pastizales xerófilos, Pastizales mesófilos, Herbazales psamófilos | G89: Hemicriptófita | H89: https://florauruguaya.org/taxonomias/pfaffia-tuberosa
A90: Amaranthaceae | B90: Salicornia ambigua | C90: Michx. | D90: Fl. Bor. Amer. [Michaux] 1: 2, 1803. | E90: Hierba perenne | F90: Herbazales halófilos | G90: Caméfita | H90: https://florauruguaya.org/taxonomias/salicornia-ambigua
A91: Amaranthaceae | B91: Salsola kali | C91: L. | D91: Sp. Pl. [Linnaeus] 1: 222, 1753. | E91: Hierba anual o bienal | F91: Herbazales halófilos | G91: Terófita | H91: https://florauruguaya.org/taxonomias/salsola-kali
A92: Amaryllidaceae | B92: Allium neapolitanum | C92: Cirillo | D92: Pl. Rar. Neapol. 1: 13, 1788. | E92: Hierba perenne | F92: Ambientes urbanos | G92: Geófita | H92: https://florauruguaya.org/taxonomias/allium-neapolitanum
A93: Amaryllidaceae | B93: Allium triquetrum | C93: L. | D93: Sp. Pl. [Linnaeus] 1: 300, 1753. | E93: Hierba perenne | F93: Ambientes urbanos | G93: Geófita | H93: https://florauruguaya.org/taxonomias/allium-triquetrum
A94: Amaryllidaceae | B94: Allium vineale | C94: L. | D94: Sp. Pl. [Linnaeus] 1: 299, 1753. | E94: Hierba perenne | F94: Ambientes ruderales | G94: Geófita | H94: https://florauruguaya.org/taxonomias/allium-vineale
A95: Amaryllidaceae | B95: Amaryllis belladonna | C95: L. | D95: Sp. Pl. [Linnaeus] 1: 293, 1753. | E95: Hierba perenne | F95: Ambientes ruderales, Ambientes urbanos | G95: Geófita | H95: https://florauruguaya.org/taxonomias/amaryllis-belladonna
A96: Amaryllidaceae | B96: Crinum moorei | C96: Hook.f. | D96: Bot. Mag. 100: t. 6113, 1874. | E96: Hierba perenne | F96: Ambientes ruderales, Ambientes urbanos | G96: Geófita | H96: https://florauruguaya.org/taxonomias/crinum-moorei
A97: Amaryllidaceae | B97: Hippeastrum angustifolium | C97: Pax | D97: Bot. Jahrb. Syst. 11(3): 331, 1889. | E97: Hierba perenne | F97: Herbazales hidrófilos | G97: Geófita | H97: https://florauruguaya.org/taxonomias/hippeastrum-angustifolium
A98: Amaryllidaceae | B98: Hippeastrum striatum | C98: (Lam.) H.E.Moore | D98: Baileya 11: 16, 1963. | E98: Hierba perenne | F98: Bosques ribereños | G98: Geófita | H98: https://florauruguaya.org/taxonomias/hippeastrum-striatum
A99: Amaryllidaceae | B99: Hippeastrum vittatum | C99: (L&#39;Hér.) Herb. | D99: Appendix [Herbert] 31, 1821. | E99: Hierba perenne | F99: Bosques de quebradas | G99: Geófita | H99: https://florauruguaya.org/taxonomias/hippeastrum-vittatum
A100: Amaryllidaceae | B100: Ipheion recurvifolium | C100: (C.H.Wright) Traub | D100: Pl. Life (Stanford) 9: 69, 1953. | E100: Hierba perenne | F100: Pastizales xerófilos, Pastizales mesófilos | G100: Geófita | H100: https://florauruguaya.org/taxonomias/ipheion-recurvifolium
... A102: Amaryllidaceae | B102: Ipheion uniflorum | C102: (Graham) Raf. | D102: Fl. Tellur. 2: 12, 1837. | E102: Hierba perenne | F102: Ambientes urbanos, Matorrales xerófilos, Matorrales mesófilos, Pastizales xerófilos, Pastizales mesófilos | G102: Geófita | H102: https://florauruguaya.org/taxonomias/ipheion-uniflorum
A103: Amaryllidaceae | B103: Narcissus tazetta | C103: L. | D103: Fam. Pl. [Adanson] 1: 290, 1753. | E103: Hierba perenne | F103: Ambientes urbanos | H103: https://florauruguaya.org/taxonomias/narcissus-tazetta
...

Sheet candidates (3)
A1: score | B1: wfo_id | C1: wfo_full_name | D1: wfo_check | E1: input_name_string | F1: wfo_id | G1: wfo_full_name
A2: 2 | B2: wfo-0000658310 | C2: Dyschoriste humilis Lindau | D2: unplaced | E2: Dyschoriste humilis (Nees) Lindau | F2: wfo-0000658310 | G2: Dyschoriste humilis Lindau
A3: 1 | B3: wfo-1200030165 | C3: Dyschoriste humilis Lindau | D3: Code/Plantae/Pteridobiotina/Angiosperms/Lamiales/Acanthaceae/Dyschoriste/humilis | E3: Dyschoriste humilis (Nees) Lindau | F3: wfo-1200030165 | G3: Dyschoriste humilis Lindau
A4: 1 | B4: wfo-0000726781 | C4: Hygrophila costata Nees | D4: Code/Plantae/Pteridobiotina/Angiosperms/Lamiales/Acanthaceae/Hygrophila/costata | E4: Hygrophila costata Nees & T.Nees | F4: wfo-0000726781 | G4: Hygrophila costata Nees
A5: 1 | B5: wfo-0000766394 | C5: Echinodorus floribundus Seub. ex Warm. | D5: Code/Plantae/Pteridobiotina/Angiosperms/Alismatales/Alismataceae/Aquarius/floribundus$Echinodorus/floribundus | E5: Echinodorus floribundus (Seub.) Seub. ex Warm. | F5: wfo-0000766394 | G5: Echinodorus floribundus Seub. ex Warm.
A6: 2 | B6: wfo-0000530163 | C6: Amaranthus crispus (Lesp. & Thévenau) A.Braun ex J.M.Coult. & S.Watson | D6: Code/Plantae/Pteridobiotina/Angiosperms/Caryophyllales/Amaranthaceae/Amarantheae/Amaranthus/crispus | E6: Amaranthus crispus (Lesp. & Thévenau) A.Braun ex S.Watson & J.M.Coult. | F6: wfo-0000530163 | G6: Amaranthus crispus (Lesp. & Thévenau) A.Braun ex J.M.Coult. & S.Watson
A7: 1 | B7: wfo-0001046238 | C7: Amaranthus crispus Terrac. | D7: unplaced | E7: Amaranthus crispus (Lesp. & Thévenau) A.Braun ex S.Watson & J.M.Coult. | F7: wfo-0001046238 | G7: Amaranthus crispus Terrac.
A8: 1 | B8: wfo-0000743782 | C8: Dysphania bonariensis (Hook.f.) Mosyakin & Clemants | D8: Code/Plantae/Pteridobiotina/Angiosperms/Caryophyllales/Chenopodiaceae/Chenopodioideae/Atripliceae/Chenopodium/haumanii$Dysphania/bonariensis | E8: Dysphania bonariensis (Hook.f.) Mosyakin & Clemants ex Sukhor. | F8: wfo-0000743782 | G8: Dysphania bonariensis (Hook.f.) Mosyakin & Clemants
A9: 1 | B9: wfo-1000085903 | C9: Holmbergia tweediei Speg. | D9: unplaced | E9: Holmbergia tweediei (Moq.) Speg. | F9: wfo-1000085903 | G9: Holmbergia tweediei Speg.
A10: 1 | B10: wfo-0000661874 | C10: Hippeastrum vittatum (L'Hér.) Herb. | D10: Code/Plantae/Pteridobiotina/Angiosperms/Asparagales/Amaryllidaceae/Hippeastrum/vittatum | E10: Hippeastrum vittatum (L&#39;Hér.) Herb. | F10: wfo-0000661874 | G10: Hippeastrum vittatum (L'Hér.) Herb.
A11: 1 | B11: wfo-0000752531 | C11: Zephyranthes brachyandra (Baker) Backer & Beknopte | D11: Code/Plantae/Pteridobiotina/Angiosperms/Asparagales/Amaryllidaceae/Habranthus/brachyandrus$Zephyranthes/brachyandra | E11: Zephyranthes brachyandra (Baker) Backer | F11: wfo-0000752531 | G11: Zephyranthes brachyandra (Baker) Backer & Beknopte
A12: 1 | B12: wfo-0000753709 | C12: Zephyranthes caerulea Baker | D12: Code/Plantae/Pteridobiotina/Angiosperms/Asparagales/Amaryllidaceae/Habranthus/caeruleus$Zephyranthes/caerulea | E12: Zephyranthes caerulea (Griseb.) Baker | F12: wfo-0000753709 | G12: Zephyranthes caerulea Baker
A13: 1 | B13: wfo-0000752452 | C13: Zephyranthes mesochloa Herb. | D13: Code/Plantae/Pteridobiotina/Angiosperms/Asparagales/Amaryllidaceae/Zephyranthes/mesochloa | E13: Zephyranthes mesochloa Herb. in Lindl. | F13: wfo-0000752452 | G13: Zephyranthes mesochloa Herb.
... A582: 1 | B582: wfo-0001146331 | C582: Porlieria microphylla (Baill.) Descole, O'Donell & Lourteig | D582: Code/Plantae/Pteridobiotina/Angiosperms/Zygophyllales/Zygophyllaceae/Porlieria/microphylla | E582: Porlieria microphylla (Baill.) Descole, O&#39;Donell & Lourteig | F582: wfo-0001146331 | G582: Porlieria microphylla (Baill.) Descole, O'Donell & Lourteig

Sheet output (33)
A1: wfo_id | B1: wfo_full_name | C1: wfo_check | D1: input_name_string | E1: wfo_id2
A2: wfo-0000646051 | B2: Dicliptera squarrosa Nees | C2: Code/Plantae/Pteridobiotina/Angiosperms/Lamiales/Acanthaceae/Dicliptera/squarrosa | D2: Dicliptera squarrosa Nees | E2: wfo-0000646051
A3: wfo-1200030165 | B3: Dyschoriste humilis (Nees) Lindau | C3: 2 candidates found. | D3: Dyschoriste humilis (Nees) Lindau | E3: wfo-1200030165
A4: wfo-0000658315 | B4: Dyschoriste hygrophiloides (Nees) Kuntze | C4: Code/Plantae/Pteridobiotina/Angiosperms/Lamiales/Acanthaceae/Dyschoriste/hygrophiloides | D4: Dyschoriste hygrophiloides (Nees) Kuntze | E4: wfo-0000658315
A5: wfo-0000726781 | B5: Hygrophila costata Nees | C5: 1 candidates found. | D5: Hygrophila costata Nees & T.Nees | E5: wfo-0000726781
A6: wfo-0000726797 | B6: Hygrophila guianensis Nees | C6: Code/Plantae/Pteridobiotina/Angiosperms/Lamiales/Acanthaceae/Hygrophila/guianensis | D6: Hygrophila guianensis Nees | E6: wfo-0000726797
A7: wfo-0001043972 | B7: Justicia axillaris (Nees) Lindau | C7: Code/Plantae/Pteridobiotina/Angiosperms/Lamiales/Acanthaceae/Justicia/axillaris | D7: Justicia axillaris (Nees) Lindau | E7: wfo-0001043972
A8: wfo-0000354192 | B8: Justicia brasiliana Roth | C8: Code/Plantae/Pteridobiotina/Angiosperms/Lamiales/Acanthaceae/Justicia/brasiliana | D8: Justicia brasiliana Roth | E8: wfo-0000354192
A9: wfo-0000354453 | B9: Justicia comata (L.) Lam. | C9: Code/Plantae/Pteridobiotina/Angiosperms/Lamiales/Acanthaceae/Dianthera/comata$Justicia/comata | D9: Justicia comata (L.) Lam. | E9: wfo-0000354453
A10: wfo-0000355947 | B10: Justicia laevilinguis (Nees) Lindau | C10: Code/Plantae/Pteridobiotina/Angiosperms/Lamiales/Acanthaceae/Dianthera/laevilinguis$Justicia/laevilinguis | D10: Justicia laevilinguis (Nees) Lindau | E10: wfo-0000355947
A11: wfo-0001044021 | B11: Justicia oblonga (Nees) Lindau | C11: Code/Plantae/Pteridobiotina/Angiosperms/Lamiales/Acanthaceae/Dianthera/oblonga$Justicia/oblonga | D11: Justicia oblonga (Nees) Lindau | E11: wfo-0001044021
A12: wfo-0001044033 | B12: Justicia polygaloides (S.Moore) Lindau | C12: Code/Plantae/Pteridobiotina/Angiosperms/Lamiales/Acanthaceae/Dianthera/polygaloides$Justicia/polygaloides | D12: Justicia polygaloides (S.Moore) Lindau | E12: wfo-0001044033
... A315: wfo-0000574288 | B315: Tillandsia arequitae (André) André ex Mez | C315: Code/Plantae/Pteridobiotina/Angiosperms/Poales/Bromeliaceae/Tillandsia/arequitae | D315: Tillandsia arequitae (André) André ex Mez | E315: wfo-0000574288
A316: wfo-0000573817 | C316: 1 candidates found. | D316: Tillandsia aëranthos (Loisel.) L.B.Sm. | E316: wfo-0000573817
A317: wfo-0000574723 | B317: Tillandsia bandensis Baker | C317: Code/Plantae/Pteridobiotina/Angiosperms/Poales/Bromeliaceae/Tillandsia/bandensis | D317: Tillandsia bandensis Baker | E317: wfo-0000574723
A318: wfo-0000575760 | B318: Tillandsia capillaris Ruiz & Pav. | C318: Code/Plantae/Pteridobiotina/Angiosperms/Poales/Bromeliaceae/Tillandsia/capillaris | D318: Tillandsia capillaris Ruiz & Pav. | E318: wfo-0000575760
A319: wfo-1000090353 | B319: Tillandsia cleistopetala Rossado | C319: unplaced | D319: Tillandsia cleistopetala Rossado | E319: wfo-1000090353
A320: wfo-0000577840 | B320: Tillandsia duratii Vis. | C320: Code/Plantae/Pteridobiotina/Angiosperms/Poales/Bromeliaceae/Tillandsia/duratii | D320: Tillandsia duratii Vis. | E320: wfo-0000577840
A321: wfo-0000578751 | B321: Tillandsia geminiflora Brongn. | C321: Code/Plantae/Pteridobiotina/Angiosperms/Poales/Bromeliaceae/Tillandsia/geminiflora | D321: Tillandsia geminiflora Brongn. | E321: wfo-0000578751
A322: wfo-0000580176 | B322: Tillandsia ixioides Griseb. | C322: Code/Plantae/Pteridobiotina/Angiosperms/Poales/Bromeliaceae/Tillandsia/ixioides | D322: Tillandsia ixioides Griseb. | E322: wfo-0000580176
A323: wfo-0000580809 | B323: Tillandsia loliacea Mart. ex Schult. & Schult.f. | C323: Code/Plantae/Pteridobiotina/Angiosperms/Poales/Bromeliaceae/Tillandsia/loliacea | D323: Tillandsia loliacea Mart. ex Schult. & Schult.f. | E323: wfo-0000580809
A324: wfo-0000583812 | B324: Tillandsia recurvata (L.) L. | C324: Code/Plantae/Pteridobiotina/Angiosperms/Poales/Bromeliaceae/Tillandsia/recurvata | D324: Tillandsia recurvata (L.) L. | E324: wfo-0000583812
A325: wfo-0000583868 | B325: Tillandsia recurvifolia Hook. | C325: Code/Plantae/Pteridobiotina/Angiosperms/Poales/Bromeliaceae/Tillandsia/recurvifolia | D325: Tillandsia recurvifolia Hook. | E325: wfo-0000583868
A326: wfo-0000585601 | B326: Tillandsia stricta Sol. ex Ker Gawl. | C326: Code/Plantae/Pteridobiotina/Angiosperms/Poales/Bromeliaceae/Tillandsia/stricta | D326: Tillandsia stricta Sol. ex Ker Gawl. | E326: wfo-0000585601
A327: wfo-0000585931 | B327: Tillandsia tricholepis Baker | C327: Code/Plantae/Pteridobiotina/Angiosperms/Poales/Bromeliaceae/Tillandsia/tricholepis | D327: Tillandsia tricholepis Baker | E327: wfo-0000585931
A328: wfo-1000007958 | B328: Tillandsia uruguayensis Rossado | C328: Code/Plantae/Pteridobiotina/Angiosperms/Poales/Bromeliaceae/Tillandsia/uruguayensis | D328: Tillandsia uruguayensis Rossado | E328: wfo-1000007958
... A341: wfo-0000691765 | B341: Frailea phaeodisca (Speg.) Backeb. & F.M.Knuth | C341: Code/Plantae/Pteridobiotina/Angiosperms/Caryophyllales/Cactaceae/Frailea/phaeodisca | D341: Frailea phaeodisca (Speg.) Backeb. & F.M.Knuth | E341: wfo-0000691765
A342: =VLOOKUP(output__33[[#This Row],[input_name_string]],'candidates (3)'!E$2:G$582,2,FALSE) -> wfo-0000691773 | B342: =VLOOKUP(output__33[[#This Row],[input_name_string]],'candidates (3)'!E$2:G$582,3,FALSE) -> Frailea pumila (Lem.) Britton & Rose | C342: 1 candidates found. | D342: Frailea pumila Britton & Rose | E342: wfo-0000691773
A343: =VLOOKUP(output__33[[#This Row],[input_name_string]],'candidates (3)'!E$2:G$582,2,FALSE) -> wfo-0000691782 | B343: =VLOOKUP(output__33[[#This Row],[input_name_string]],'candidates (3)'!E$2:G$582,3,FALSE) -> Frailea pygmaea (Speg.) Britton & Rose | C343: 1 candidates found. | D343: Frailea pygmaea Britton & Rose | E343: wfo-0000691782
A344: =VLOOKUP(output__33[[#This Row],[input_name_string]],'candidates (3)'!E$2:G$582,2,FALSE) -> wfo-0000691803 | B344: =VLOOKUP(output__33[[#This Row],[input_name_string]],'candidates (3)'!E$2:G$582,3,FALSE) -> Frailea schilinzkyana (F.Haage) Britton & Rose | C344: 1 candidates found. | D344: Frailea schilinzkyana (F.Haage & K.Schum.) Britton & Rose | E344: wfo-0000691803
A345: wfo-0000712444 | B345: Gymnocalycium denudatum (Link & Otto) Pfeiff. ex Mittler | C345: Code/Plantae/Pteridobiotina/Angiosperms/Caryophyllales/Cactaceae/Gymnocalycium/denudatum | D345: Gymnocalycium denudatum (Link & Otto) Pfeiff. ex Mittler | E345: wfo-0000712444
A346: =VLOOKUP(output__33[[#This Row],[input_name_string]],'candidates (3)'!E$2:G$582,2,FALSE) -> wfo-0000712493 | B346: =VLOOKUP(output__33[[#This Row],[input_name_string]],'candidates (3)'!E$2:G$582,3,FALSE) -> Gymnocalycium hyptiacanthum (Lem.) Britton & Rose | C346: 1 candidates found. | D346: Gymnocalycium hyptiacanthum Britton & Rose | E346: wfo-0000712493
A347: wfo-0000712674 | B347: Gymnocalycium schroederianum Osten | C347: Code/Plantae/Pteridobiotina/Angiosperms/Caryophyllales/Cactaceae/Gymnocalycium/schroederianum | D347: Gymnocalycium schroederianum Osten | E347: wfo-0000712674
A348: wfo-0000715881 | B348: Harrisia bonplandii (Parm. ex Pfeiff.) Britton & Rose | C348: Code/Plantae/Pteridobiotina/Angiosperms/Caryophyllales/Cactaceae/Harrisia/bonplandii | D348: Harrisia bonplandii (Parm. ex Pfeiff.) Britton & Rose | E348: wfo-0000715881
A349: wfo-0001287227 | B349: Harrisia martinii (Labour.) Britton | C349: Code/Plantae/Pteridobiotina/Angiosperms/Caryophyllales/Cactaceae/Harrisia/martinii | D349: Harrisia martinii (Labour.) Britton | E349: wfo-0001287227
A350: wfo-0001289289 | B350: Harrisia pomanensis (F.A.C.Weber ex K.Schum.) Britton & Rose | C350: Code/Plantae/Pteridobiotina/Angiosperms/Caryophyllales/Cactaceae/Harrisia/pomanensis | D350: Harrisia pomanensis (F.A.C.Weber ex K.Schum.) Britton & Rose | E350: wfo-0001289289
A351: wfo-0001239324 | B351: Lepismium aculeatum (F.A.C.Weber) Barthlott | C351: Code/Plantae/Pteridobiotina/Angiosperms/Caryophyllales/Cactaceae/Lepismium/lumbricoides/aculeatum$Lepismium/aculeatum | D351: Lepismium aculeatum (F.A.C.Weber) Barthlott | E351: wfo-0001239324
A352: wfo-0000357990 | B352: Lepismium cruciforme (Vell.) Miq. | C352: Code/Plantae/Pteridobiotina/Angiosperms/Caryophyllales/Cactaceae/Lepismium/cruciforme | D352: Lepismium cruciforme (Vell.) Miq. | E352: wfo-0000357990
A353: wfo-0000357993 | B353: Lepismium lumbricoides (Lem.) Barthlott | C353: Code/Plantae/Pteridobiotina/Angiosperms/Caryophyllales/Cactaceae/Lepismium/lumbricoides | D353: Lepismium lumbricoides (Lem.) Barthlott | E353: wfo-0000357993
A354: wfo-0001433069 | B354: Opuntia arechavaletae Speg. | C354: Code/Plantae/Pteridobiotina/Angiosperms/Caryophyllales/Cactaceae/Opuntia/arechavaletae | D354: Opuntia arechavaletae Speg. | E354: wfo-0001433069
A355: wfo-0001287228 | B355: Opuntia aurantiaca Lindl. | C355: Code/Plantae/Pteridobiotina/Angiosperms/Caryophyllales/Cactaceae/Opuntia/aurantiaca | D355: Opuntia aurantiaca Lindl. | E355: wfo-0001287228
A356: wfo-0001289329 | B356: Opuntia bonaerensis Speg. | C356: Code/Plantae/Pteridobiotina/Angiosperms/Caryophyllales/Cactaceae/Opuntia/bonaerensis | D356: Opuntia bonaerensis Speg. | E356: wfo-0001289329
A357: wfo-0000386497 | B357: Opuntia canterae Arechav. | C357: Code/Plantae/Pteridobiotina/Angiosperms/Caryophyllales/Cactaceae/Opuntia/canterae | D357: Opuntia canterae Arechav. | E357: wfo-0000386497
A358: wfo-0001289105 | B358: Opuntia elata Link & Otto ex Salm-Dyck | C358: Code/Plantae/Pteridobiotina/Angiosperms/Caryophyllales/Cactaceae/Opuntia/elata | D358: Opuntia elata Salm-Dyck | E358: wfo-0001289105
A359: wfo-0001256652 | B359: Opuntia megapotamica Arechav. | C359: Code/Plantae/Pteridobiotina/Angiosperms/Caryophyllales/Cactaceae/Opuntia/megapotamica | D359: Opuntia megapotamica Arechav. | E359: wfo-0001256652
A360: =VLOOKUP(output__33[[#This Row],[input_name_string]],'candidates (3)'!E$2:G$582,2,FALSE) -> wfo-0000386588 | B360: =VLOOKUP(output__33[[#This Row],[input_name_string]],'candidates (3)'!E$2:G$582,3,FALSE) -> Opuntia monacantha (Willd.) Haw. | C360: 1 candidates found. | D360: Opuntia monacantha Haw. | E360: wfo-0000386588
A361: wfo-0001287950 | B361: Opuntia retrorsa Speg. | C361: Code/Plantae/Pteridobiotina/Angiosperms/Caryophyllales/Cactaceae/Opuntia/retrorsa | D361: Opuntia retrorsa Speg. | E361: wfo-0001287950
A362: =VLOOKUP(output__33[[#This Row],[input_name_string]],'[1]output (34)'!$D$3:$F$36,2,FALSE) -> wfo-0001433330 | B362: =VLOOKUP(output__33[[#This Row],[input_name_string]],'[1]output (34)'!$D$3:$F$36,3,FALSE) -> Opuntia rioplatense Font | C362: 10 candidates found. | D362: Opuntia rioplatensis Font | E362: wfo-0001433330
A363: wfo-0001289360 | B363: Opuntia sulphurea Gillies ex Salm-Dyck | C363: Code/Plantae/Pteridobiotina/Angiosperms/Caryophyllales/Cactaceae/Opuntia/sulphurea | D363: Opuntia sulphurea Gillies ex Salm-Dyck | E363: wfo-0001289360
A364: wfo-0001256004 | B364: Parodia allosiphon (Marchesi) N.P.Taylor | C364: Code/Plantae/Pteridobiotina/Angiosperms/Caryophyllales/Cactaceae/Parodia/allosiphon | D364: Parodia allosiphon (Marchesi) N.P.Taylor | E364: wfo-0001256004
A365: wfo-0001256006 | B365: Parodia buiningii (Buxb.) N.P.Taylor | C365: Code/Plantae/Pteridobiotina/Angiosperms/Caryophyllales/Cactaceae/Parodia/buiningii | D365: Parodia buiningii (Buxb.) N.P.Taylor | E365: wfo-0001256006
A366: wfo-0001256011 | B366: Parodia concinna (Monv.) N.P.Taylor | C366: Code/Plantae/Pteridobiotina/Angiosperms/Caryophyllales/Cactaceae/Parodia/concinna | D366: Parodia concinna (Monv.) N.P.Taylor | E366: wfo-0001256011
A367: wfo-1000065055 | B367: Parodia erinaceus (Haw.) N.P.Taylor | C367: unplaced | D367: Parodia erinaceus (Haw.) N.P.Taylor | E367: wfo-1000065055
A368: wfo-1000064778 | B368: Parodia gladiata (V.Gapon & Ponomareva) M.H.J.van der Meer | C368: unplaced | D368: Parodia gladiata (V.Gapon & Ponomareva) M.H.J.van der Meer | E368: wfo-1000064778
A369: wfo-0001256027 | B369: Parodia herteri (Werderm.) N.P.Taylor | C369: Code/Plantae/Pteridobiotina/Angiosperms/Caryophyllales/Cactaceae/Parodia/herteri | D369: Parodia herteri (Wederm.) N.P.Taylor | E369: wfo-0001256027
A370: wfo-0001252386 | B370: Parodia langsdorfii (Lehm.) D.R.Hunt | C370: Code/Plantae/Pteridobiotina/Angiosperms/Caryophyllales/Cactaceae/Parodia/langsdorfii | D370: Parodia langsdorfii (Lehm.) D.R.Hunt | E370: wfo-0001252386
A371: wfo-0001220117 | B371: Parodia linkii (Lehm.) R.Kiesling | C371: Code/Plantae/Pteridobiotina/Angiosperms/Caryophyllales/Cactaceae/Parodia/linkii | D371: Parodia linkii (Lehm.) R.Kiesling | E371: wfo-0001220117
A372: wfo-0001433473 | B372: Parodia maldonadensis (Herter) Hofacker | C372: Code/Plantae/Pteridobiotina/Angiosperms/Caryophyllales/Cactaceae/Parodia/maldonadensis | D372: Parodia maldonadensis (Herter) Hofacker | E372: wfo-0001433473
A373: wfo-0001220110 | B373: Parodia mammulosa (Lem.) N.P.Taylor | C373: Code/Plantae/Pteridobiotina/Angiosperms/Caryophyllales/Cactaceae/Parodia/mammulosa | D373: Parodia mammulosa (Lehm.) N.P.Taylor | E373: wfo-0001220110
A374: wfo-0001256047 | B374: Parodia mueller-melchersii (Frič ex Backeb.) N.P.Taylor | C374: Code/Plantae/Pteridobiotina/Angiosperms/Caryophyllales/Cactaceae/Parodia/mueller-melchersii | D374: Parodia mueller-melchersii (Backeb.) N.P.Taylor | E374: wfo-0001256047
... A380: wfo-0001256073 | B380: Parodia scopa (Spreng.) N.P.Taylor | C380: Code/Plantae/Pteridobiotina/Angiosperms/Caryophyllales/Cactaceae/Parodia/scopa | D380: Parodia scopa (Spreng.) N.P.Taylor | E380: wfo-0001256073
A381: =VLOOKUP(output__33[[#This Row],[input_name_string]],'candidates (3)'!E$2:G$582,2,FALSE) -> wfo-0001252392 | B381: =VLOOKUP(output__33[[#This Row],[input_name_string]],'candidates (3)'!E$2:G$582,3,FALSE) -> Parodia tabularis (F.Cels ex Rümpler) D.R.Hunt | C381: 1 candidates found. | D381: Parodia tabularis (J.F.Cels ex Rümpler) D.R.Hunt | E381: wfo-0001252392
A382: wfo-0001252394 | B382: Parodia tenuicylindrica (F.Ritter) D.R.Hunt | C382: Code/Plantae/Pteridobiotina/Angiosperms/Caryophyllales/Cactaceae/Parodia/tenuicylindrica | D382: Parodia tenuicylindrica (F.Ritter) D.R.Hunt | E382: wfo-0001252394
A383: wfo-0001256087 | B383: Parodia turbinata (Arechav.) Hofacker | C383: Code/Plantae/Pteridobiotina/Angiosperms/Caryophyllales/Cactaceae/Parodia/erinacea$Parodia/turbinata | D383: Parodia turbinata (Arechav.) Hofacker | E383: wfo-0001256087
A384: wfo-0001220108 | B384: Parodia turecekiana R.Kiesling | C384: Code/Plantae/Pteridobiotina/Angiosperms/Caryophyllales/Cactaceae/Parodia/mammulosa$Parodia/turecekiana | D384: Parodia turecekiana R.Kiesling | E384: wfo-0001220108
A385: wfo-0001256090 | B385: Parodia werdermanniana (Herter) N.P.Taylor | C385: Code/Plantae/Pteridobiotina/Angiosperms/Caryophyllales/Cactaceae/Parodia/werdermanniana | D385: Parodia werdermanniana (Herter) N.P.Taylor | E385: wfo-0001256090
A386: wfo-0000398441 | B386: Pereskia aculeata Mill. | C386: Code/Plantae/Pteridobiotina/Angiosperms/Caryophyllales/Cactaceae/Pereskia/aculeata | D386: Pereskia aculeata Mill. | E386: wfo-0000398441
A387: wfo-0001287949 | B387: Pereskia nemorosa Rojas Acosta | C387: Code/Plantae/Pteridobiotina/Angiosperms/Caryophyllales/Cactaceae/Pereskia/nemorosa | D387: Pereskia nemorosa Rojas Acosta | E387: wfo-0001287949
A388: wfo-0000399868 | B388: Rhipsalis cereuscula Haw. | C388: Code/Plantae/Pteridobiotina/Angiosperms/Caryophyllales/Cactaceae/Rhipsalis/cereuscula | D388: Rhipsalis cereuscula Haw. | E388: wfo-0000399868
A389: wfo-0000399687 | B389: Rhipsalis floccosa Salm-Dyck ex Pfeiff. | C389: Code/Plantae/Pteridobiotina/Angiosperms/Caryophyllales/Cactaceae/Rhipsalis/floccosa | D389: Rhipsalis floccosa Salm-Dyck ex Pfeiff. | E389: wfo-0000399687
A390: wfo-0000579804 | B390: Calceolaria parviflora Gillies ex Benth. | C390: Code/Plantae/Pteridobiotina/Angiosperms/Lamiales/Calceolariaceae/Calceolaria/parviflora | D390: Calceolaria parviflora Gillies ex Benth. | E390: wfo-0000579804
A391: wfo-0000516581 | B391: Acicarpha obtusisepala Marchesi | C391: Code/Plantae/Pteridobiotina/Angiosperms/Asterales/Calyceraceae/Acicarpha/obtusisepala | D391: Acicarpha obtusisepala Marchesi | E391: wfo-0000516581
A392: wfo-0000516583 | B392: Acicarpha procumbens Less. | C392: Code/Plantae/Pteridobiotina/Angiosperms/Asterales/Calyceraceae/Acicarpha/procumbens | D392: Acicarpha procumbens Less. | E392: wfo-0000516583
A393: wfo-0000516592 | B393: Acicarpha tribuloides Juss. | C393: Code/Plantae/Pteridobiotina/Angiosperms/Asterales/Calyceraceae/Acicarpha/tribuloides | D393: Acicarpha tribuloides Juss. | E393: wfo-0000516592
... A421: wfo-0001291617 | B421: Cardionema ramosissimum (Weinm.) A.Nelson & J.F.Macbr. | C421: Code/Plantae/Pteridobiotina/Angiosperms/Caryophyllales/Caryophyllaceae/Polycarpaeae/Cardionema/ramosissimum | D421: Cardionema ramosissimum (Weinm.) A.Nelson & J.F.Macbr. | E421: wfo-0001291617
A422: =VLOOKUP(output__33[[#This Row],[input_name_string]],'[1]output (34)'!$D$3:$F$36,2,FALSE) -> wfo-0000595394 | B422: =VLOOKUP(output__33[[#This Row],[input_name_string]],'[1]output (34)'!$D$3:$F$36,3,FALSE) -> Cerastium commersonianum Ser. | C422: 10 candidates found. | D422: Cerastium commersonianum Ser. in DC. | E422: wfo-0000595394
A423: wfo-0000595484 | B423: Cerastium dicrotrichum Fenzl ex Rohrb. | C423: Code/Plantae/Pteridobiotina/Angiosperms/Caryophyllales/Caryophyllaceae/Alsineae/Cerastium/dicrotrichum | D423: Cerastium dicrotrichum Fenzl ex Rohrb. | E423: wfo-0000595484
A424: wfo-0000595603 | B424: Cerastium glomeratum Thuill. | C424: Code/Plantae/Pteridobiotina/Angiosperms/Caryophyllales/Caryophyllaceae/Alsineae/Cerastium/glomeratum | D424: Cerastium glomeratum Thuill. | E424: wfo-0000595603
A425: wfo-0000595672 | B425: Cerastium humifusum Cambess. | C425: Code/Plantae/Pteridobiotina/Angiosperms/Caryophyllales/Caryophyllaceae/Alsineae/Cerastium/humifusum | D425: Cerastium humifusum Cambess. | E425: wfo-0000595672
A426: wfo-1000094822 | B426: Cerastium parvum (Pedersen) M.T.Sharples & E.A.Tripp | C426: 10 candidates found. | D426: Cerastium parvum (Pedersen) M.T.Sharples & E.A.Tripp | E426: wfo-1000094822
A427: wfo-0000596083 | B427: Cerastium rivulare Cambess. | C427: Code/Plantae/Pteridobiotina/Angiosperms/Caryophyllales/Caryophyllaceae/Alsineae/Cerastium/rivulare | D427: Cerastium rivulare Cambess. | E427: wfo-0000596083
A428: wfo-0000596084 | B428: Cerastium rivulariastrum Möschl & Pedersen | C428: Code/Plantae/Pteridobiotina/Angiosperms/Caryophyllales/Caryophyllaceae/Alsineae/Cerastium/rivulariastrum | D428: Cerastium rivulariastrum Möschl & Pedersen | E428: wfo-0000596084
A429: wfo-0000621849 | B429: Corrigiola andina Planch. & Triana | C429: Code/Plantae/Pteridobiotina/Angiosperms/Caryophyllales/Caryophyllaceae/Corrigioleae/Corrigiola/andina | D429: Corrigiola andina Planch. & Triana | E429: wfo-0000621849
A430: =VLOOKUP(output__33[[#This Row],[input_name_string]],'candidates (3)'!E$2:G$582,2,FALSE) -> wfo-0000657240 | B430: =VLOOKUP(output__33[[#This Row],[input_name_string]],'candidates (3)'!E$2:G$582,3,FALSE) -> Drymaria cordata Willd. ex Schult. | C430: 1 candidates found. | D430: Drymaria cordata (L.) Willd. ex Schult. | E430: wfo-0000657240
A431: wfo-0000713816 | B431: Gypsophila vaccaria (L.) Sm. | C431: Code/Plantae/Pteridobiotina/Angiosperms/Caryophyllales/Caryophyllaceae/Caryophylleae/Gypsophila/vaccaria | D431: Gypsophila vaccaria (L.) Sm. | E431: wfo-0000713816
A432: wfo-1000085924 | B432: Paronychia brasiliana DC. | C432: unplaced | D432: Paronychia brasiliana DC. | E432: wfo-1000085924
A433: wfo-0001292325 | B433: Paronychia communis Cambess. | C433: Code/Plantae/Pteridobiotina/Angiosperms/Caryophyllales/Caryophyllaceae/Paronychieae/Paronychia/communis | D433: Paronychia communis Cambess. | E433: wfo-0001292325
A434: wfo-0001292369 | B434: Paronychia setigera (Gillies ex Hook. & Arn.) F.Herm. | C434: Code/Plantae/Pteridobiotina/Angiosperms/Caryophyllales/Caryophyllaceae/Paronychieae/Paronychia/setigera | D434: Paronychia setigera (Gillies ex Hook. & Arn.) F.Herm. | E434: wfo-0001292369
A435: wfo-0000395614 | B435: Polycarpon tetraphyllum (L.) L. | C435: Code/Plantae/Pteridobiotina/Angiosperms/Caryophyllales/Caryophyllaceae/Polycarpaeae/Polycarpon/tetraphyllum | D435: Polycarpon tetraphyllum (L.) L. | E435: wfo-0000395614
A436: wfo-0000438405 | B436: Sagina apetala Ard. | C436: Code/Plantae/Pteridobiotina/Angiosperms/Caryophyllales/Caryophyllaceae/Sagineae/Sagina/apetala | D436: Sagina apetala Ard. | E436: wfo-0000438405
A437: =VLOOKUP(output__33[[#This Row],[input_name_string]],'candidates (3)'!E$2:G$582,2,FALSE) -> wfo-0001292390 | B437: =VLOOKUP(output__33[[#This Row],[input_name_string]],'candidates (3)'!E$2:G$582,3,FALSE) -> Sagina humifusa (Cambess.) Fenzl ex Rohrb. | C437: 1 candidates found. | D437: Sagina humifusa (Cambess.) Fenzl & Rohrb. | E437: wfo-0001292390
A438: wfo-0000438211 | B438: Saponaria officinalis L. | C438: Code/Plantae/Pteridobiotina/Angiosperms/Caryophyllales/Caryophyllaceae/Caryophylleae/Saponaria/officinalis | D438: Saponaria officinalis L. | E438: wfo-0000438211
A439: wfo-0000441933 | B439: Scleranthus annuus L. | C439: Code/Plantae/Pteridobiotina/Angiosperms/Caryophyllales/Caryophyllaceae/Sclerantheae/Scleranthus/annuus | D439: Scleranthus annuus L. | E439: wfo-0000441933
A440: wfo-0001291298 | B440: Silene antirrhina L. | C440: Code/Plantae/Pteridobiotina/Angiosperms/Caryophyllales/Caryophyllaceae/Sileneae/Silene/antirrhina | D440: Silene antirrhina L. | E440: wfo-0001291298
A441: wfo-0000440573 | B441: Silene gallica L. | C441: Code/Plantae/Pteridobiotina/Angiosperms/Caryophyllales/Caryophyllaceae/Sileneae/Silene/gallica | D441: Silene gallica L. | E441: wfo-0000440573
A442: wfo-0000440688 | B442: Silene micropetala Lag. | C442: Code/Plantae/Pteridobiotina/Angiosperms/Caryophyllales/Caryophyllaceae/Sileneae/Silene/micropetala | D442: Silene micropetala Lag. | E442: wfo-0000440688
A443: wfo-0000439880 | B443: Spergula arvensis L. | C443: Code/Plantae/Pteridobiotina/Angiosperms/Caryophyllales/Caryophyllaceae/Sperguleae/Spergula/arvensis | D443: Spergula arvensis L. | E443: wfo-0000439880
A444: wfo-0001291622 | B444: Spergula grandis Pers. | C444: Code/Plantae/Pteridobiotina/Angiosperms/Caryophyllales/Caryophyllaceae/Sperguleae/Spergula/grandis | D444: Spergula grandis Pers. | E444: wfo-0001291622
A445: wfo-0000433735 | B445: Spergularia bocconei (Scheele) Graebn. | C445: Code/Plantae/Pteridobiotina/Angiosperms/Caryophyllales/Caryophyllaceae/Sperguleae/Spergularia/bocconei | D445: Spergularia bocconei (Scheele) Graebn. | E445: wfo-0000433735
A446: wfo-0001291418 | B446: Spergularia levis Cambess. | C446: Code/Plantae/Pteridobiotina/Angiosperms/Caryophyllales/Caryophyllaceae/Sperguleae/Spergula/levis$Spergularia/levis | D446: Spergularia levis Cambess. | E446: wfo-0001291418
...

Sheet florauruguaya_V_4_habit
A1: wfo_ID | B1: Hábito | C1: Familia | D1: Column1 | E1: Nombre | F1: Autor | G1: Pub. | H1: BibliographicCitation | I1: url
A2: =VLOOKUP(especies_20260604_1527564[[#This Row],[Column1]],output__33[[input_name_string]:[wfo_id2]],2,FALSE) -> wfo-0000646051 | B2: Sufrútice | C2: Acanthaceae | D2: Dicliptera squarrosa Nees | E2: Dicliptera squarrosa | F2: Nees | G2: Fl. Bras. [Martius] 9: 161, 1847. | H2: Marchesi, E., Mailhos, A., & Bonifacino, J. M. (2026). Flora Uruguaya: Flora Vascular del Uruguay. ISSN 3121-2050, V. 1.3. [Data set]. Zenodo. https://doi.org/10.5281/zenodo.20547117 | I2: https://florauruguaya.org/taxonomias/dicliptera-squarrosa
A3: =VLOOKUP(especies_20260604_1527564[[#This Row],[Column1]],output__33[[input_name_string]:[wfo_id2]],2,FALSE) -> wfo-1200030165 | B3: Hierba perenne | C3: Acanthaceae | D3: Dyschoriste humilis (Nees) Lindau | E3: Dyschoriste humilis | F3: (Nees) Lindau | G3: Bot. Jahrb. Syst. 19(4): 15, 1894. | H3: Marchesi, E., Mailhos, A., & Bonifacino, J. M. (2026). Flora Uruguaya: Flora Vascular del Uruguay. ISSN 3121-2050, V. 1.3. [Data set]. Zenodo. https://doi.org/10.5281/zenodo.20547117 | I3: https://florauruguaya.org/taxonomias/dyschoriste-humilis
A4: =VLOOKUP(especies_20260604_1527564[[#This Row],[Column1]],output__33[[input_name_string]:[wfo_id2]],2,FALSE) -> wfo-0000658315 | B4: Hierba perenne | C4: Acanthaceae | D4: Dyschoriste hygrophiloides (Nees) Kuntze | E4: Dyschoriste hygrophiloides | F4: (Nees) Kuntze | G4: Revis. Gen. Pl. 2: 486, 1891. | H4: Marchesi, E., Mailhos, A., & Bonifacino, J. M. (2026). Flora Uruguaya: Flora Vascular del Uruguay. ISSN 3121-2050, V. 1.3. [Data set]. Zenodo. https://doi.org/10.5281/zenodo.20547117 | I4: https://florauruguaya.org/taxonomias/dyschoriste-hygrophiloides
A5: =VLOOKUP(especies_20260604_1527564[[#This Row],[Column1]],output__33[[input_name_string]:[wfo_id2]],2,FALSE) -> wfo-0000726781 | B5: Hierba perenne | C5: Acanthaceae | D5: Hygrophila costata Nees & T.Nees | E5: Hygrophila costata | F5: Nees & T.Nees | G5: Pl. Hort. Bonn. Icon. 7, t. 3, 1824. | H5: Marchesi, E., Mailhos, A., & Bonifacino, J. M. (2026). Flora Uruguaya: Flora Vascular del Uruguay. ISSN 3121-2050, V. 1.3. [Data set]. Zenodo. https://doi.org/10.5281/zenodo.20547117 | I5: https://florauruguaya.org/taxonomias/hygrophila-costata
A6: =VLOOKUP(especies_20260604_1527564[[#This Row],[Column1]],output__33[[input_name_string]:[wfo_id2]],2,FALSE) -> wfo-0000726797 | B6: Hierba perenne | C6: Acanthaceae | D6: Hygrophila guianensis Nees | E6: Hygrophila guianensis | F6: Nees | G6: London J. Bot. 4: 634, 1845. | H6: Marchesi, E., Mailhos, A., & Bonifacino, J. M. (2026). Flora Uruguaya: Flora Vascular del Uruguay. ISSN 3121-2050, V. 1.3. [Data set]. Zenodo. https://doi.org/10.5281/zenodo.20547117 | I6: https://florauruguaya.org/taxonomias/hygrophila-guianensis
A7: =VLOOKUP(especies_20260604_1527564[[#This Row],[Column1]],output__33[[input_name_string]:[wfo_id2]],2,FALSE) -> wfo-0001043972 | B7: Hierba perenne | C7: Acanthaceae | D7: Justicia axillaris (Nees) Lindau | E7: Justicia axillaris | F7: (Nees) Lindau | G7: Nat. Pflanzenfam. [Engler & Prantl] 4(3b): 350, 1895. | H7: Marchesi, E., Mailhos, A., & Bonifacino, J. M. (2026). Flora Uruguaya: Flora Vascular del Uruguay. ISSN 3121-2050, V. 1.3. [Data set]. Zenodo. https://doi.org/10.5281/zenodo.20547117 | I7: https://florauruguaya.org/taxonomias/justicia-axillaris
A8: =VLOOKUP(especies_20260604_1527564[[#This Row],[Column1]],output__33[[input_name_string]:[wfo_id2]],2,FALSE) -> wfo-0000354192 | B8: Sufrútice | C8: Acanthaceae | D8: Justicia brasiliana Roth | E8: Justicia brasiliana | F8: Roth | G8: Nov. Pl. Sp. 17, 1821. | H8: Marchesi, E., Mailhos, A., & Bonifacino, J. M. (2026). Flora Uruguaya: Flora Vascular del Uruguay. ISSN 3121-2050, V. 1.3. [Data set]. Zenodo. https://doi.org/10.5281/zenodo.20547117 | I8: https://florauruguaya.org/taxonomias/justicia-brasiliana
A9: =VLOOKUP(especies_20260604_1527564[[#This Row],[Column1]],output__33[[input_name_string]:[wfo_id2]],2,FALSE) -> wfo-0000354453 | B9: Hierba perenne | C9: Acanthaceae | D9: Justicia comata (L.) Lam. | E9: Justicia comata | F9: (L.) Lam. | G9: Encycl. [J. Lamarck & al.] 1(2): 632, 1785. | H9: Marchesi, E., Mailhos, A., & Bonifacino, J. M. (2026). Flora Uruguaya: Flora Vascular del Uruguay. ISSN 3121-2050, V. 1.3. [Data set]. Zenodo. https://doi.org/10.5281/zenodo.20547117 | I9: https://florauruguaya.org/taxonomias/justicia-comata
A10: =VLOOKUP(especies_20260604_1527564[[#This Row],[Column1]],output__33[[input_name_string]:[wfo_id2]],2,FALSE) -> wfo-0000355947 | B10: Hierba perenne | C10: Acanthaceae | D10: Justicia laevilinguis (Nees) Lindau | E10: Justicia laevilinguis | F10: (Nees) Lindau | G10: Bot. Jahrb. Syst. 19(4): 20, 1894. | H10: Marchesi, E., Mailhos, A., & Bonifacino, J. M. (2026). Flora Uruguaya: Flora Vascular del Uruguay. ISSN 3121-2050, V. 1.3. [Data set]. Zenodo. https://doi.org/10.5281/zenodo.20547117 | I10: https://florauruguaya.org/taxonomias/justicia-laevilinguis
A11: =VLOOKUP(especies_20260604_1527564[[#This Row],[Column1]],output__33[[input_name_string]:[wfo_id2]],2,FALSE) -> wfo-0001044021 | B11: Hierba perenne | C11: Acanthaceae | D11: Justicia oblonga (Nees) Lindau | E11: Justicia oblonga | F11: (Nees) Lindau | G11: Nat. Pflanzenfam. [Engler & Prantl] 4(3b): 350, 1895. | H11: Marchesi, E., Mailhos, A., & Bonifacino, J. M. (2026). Flora Uruguaya: Flora Vascular del Uruguay. ISSN 3121-2050, V. 1.3. [Data set]. Zenodo. https://doi.org/10.5281/zenodo.20547117 | I11: https://florauruguaya.org/taxonomias/justicia-oblonga
A12: =VLOOKUP(especies_20260604_1527564[[#This Row],[Column1]],output__33[[input_name_string]:[wfo_id2]],2,FALSE) -> wfo-0001044033 | B12: Hierba perenne | C12: Acanthaceae | D12: Justicia polygaloides (S.Moore) Lindau | E12: Justicia polygaloides | F12: (S.Moore) Lindau | G12: Bull. Herb. Boissier 2(3): 633, 1933. | H12: Marchesi, E., Mailhos, A., & Bonifacino, J. M. (2026). Flora Uruguaya: Flora Vascular del Uruguay. ISSN 3121-2050, V. 1.3. [Data set]. Zenodo. https://doi.org/10.5281/zenodo.20547117 | I12: https://florauruguaya.org/taxonomias/justicia-polygaloides
A13: =VLOOKUP(especies_20260604_1527564[[#This Row],[Column1]],output__33[[input_name_string]:[wfo_id2]],2,FALSE) -> wfo-0001045288 | B13: Arbusto | C13: Acanthaceae | D13: Justicia tweedieana (Nees) Griseb. | E13: Justicia tweedieana | F13: (Nees) Griseb. | G13: Abh. Königl. Ges. Wiss. Göttingen 19: 225, 1874. | H13: Marchesi, E., Mailhos, A., & Bonifacino, J. M. (2026). Flora Uruguaya: Flora Vascular del Uruguay. ISSN 3121-2050, V. 1.3. [Data set]. Zenodo. https://doi.org/10.5281/zenodo.20547117 | I13: https://florauruguaya.org/taxonomias/justicia-tweedieana
... A1447: =VLOOKUP(especies_20260604_1527564[[#This Row],[Column1]],output__33[[input_name_string]:[wfo_id2]],2,FALSE) -> wfo-0000867414 | B1447: Hierba anual o bienal | C1447: Gramineae | D1447: Eragrostis barrelieri Daveau | E1447: Eragrostis barrelieri | F1447: Daveau | G1447: J. Bot. (Morot) 8: 289, 1894. | H1447: Marchesi, E., Mailhos, A., & Bonifacino, J. M. (2026). Flora Uruguaya: Flora Vascular del Uruguay. ISSN 3121-2050, V. 1.3. [Data set]. Zenodo. https://doi.org/10.5281/zenodo.20547117 | I1447: https://florauruguaya.org/taxonomias/eragrostis-barrelieri
A1448: =VLOOKUP(especies_20260604_1527564[[#This Row],[Column1]],output__33[[input_name_string]:[wfo_id2]],2,FALSE) -> #N/A | B1448: Hierba perenne | C1448: Gramineae | D1448: Eragrostis cataclasta | E1448: Eragrostis cataclasta | G1448: Fl. Ilustr. Entre Rios 2: 189, 1969. | H1448: Marchesi, E., Mailhos, A., & Bonifacino, J. M. (2026). Flora Uruguaya: Flora Vascular del Uruguay. ISSN 3121-2050, V. 1.3. [Data set]. Zenodo. https://doi.org/10.5281/zenodo.20547117 | I1448: https://florauruguaya.org/taxonomias/eragrostis-cataclasta
A1449: =VLOOKUP(especies_20260604_1527564[[#This Row],[Column1]],output__33[[input_name_string]:[wfo_id2]],2,FALSE) -> wfo-0000867548 | B1449: Hierba anual o bienal | C1449: Gramineae | D1449: Eragrostis cilianensis (All.) Vignolo ex Janch. | E1449: Eragrostis cilianensis | F1449: (All.) Vignolo ex Janch. | G1449: Mitt. Naturwiss. Vereins Univ. Wien 5(9): 110, 1907. | H1449: Marchesi, E., Mailhos, A., & Bonifacino, J. M. (2026). Flora Uruguaya: Flora Vascular del Uruguay. ISSN 3121-2050, V. 1.3. [Data set]. Zenodo. https://doi.org/10.5281/zenodo.20547117 | I1449: https://florauruguaya.org/taxonomias/eragrostis-cilianensis
A1450: =VLOOKUP(especies_20260604_1527564[[#This Row],[Column1]],output__33[[input_name_string]:[wfo_id2]],2,FALSE) -> wfo-0000867617 | B1450: Hierba perenne | C1450: Gramineae | D1450: Eragrostis curvula (Schrad.) Nees | E1450: Eragrostis curvula | F1450: (Schrad.) Nees | G1450: Fl. Afr. Austral. Ill. 397, 1841. | H1450: Marchesi, E., Mailhos, A., & Bonifacino, J. M. (2026). Flora Uruguaya: Flora Vascular del Uruguay. ISSN 3121-2050, V. 1.3. [Data set]. Zenodo. https://doi.org/10.5281/zenodo.20547117 | I1450: https://florauruguaya.org/taxonomias/eragrostis-curvula
A1451: =VLOOKUP(especies_20260604_1527564[[#This Row],[Column1]],output__33[[input_name_string]:[wfo_id2]],2,FALSE) -> wfo-0000867855 | B1451: Hierba anual o bienal | C1451: Gramineae | D1451: Eragrostis hypnoides (Lam.) Britton, Sterns & Poggenb. | E1451: Eragrostis hypnoides | F1451: (Lam.) Britton, Sterns & Poggenb. | G1451: Prelim. Cat. 69, 1888. | H1451: Marchesi, E., Mailhos, A., & Bonifacino, J. M. (2026). Flora Uruguaya: Flora Vascular del Uruguay. ISSN 3121-2050, V. 1.3. [Data set]. Zenodo. https://doi.org/10.5281/zenodo.20547117 | I1451: https://florauruguaya.org/taxonomias/eragrostis-hypnoides
A1452: =VLOOKUP(especies_20260604_1527564[[#This Row],[Column1]],output__33[[input_name_string]:[wfo_id2]],2,FALSE) -> wfo-0000867890 | B1452: Hierba anual o bienal | C1452: Gramineae | D1452: Eragrostis japonica (Thunb.) Trin. | E1452: Eragrostis japonica | F1452: (Thunb.) Trin. | G1452: Mém. Acad. Imp. Sci. Saint-Pétersbourg, Sér. 6, Sci. Math., Seconde Pt. Sci. Nat. 1: 405, 1830. | H1452: Marchesi, E., Mailhos, A., & Bonifacino, J. M. (2026). Flora Uruguaya: Flora Vascular del Uruguay. ISSN 3121-2050, V. 1.3. [Data set]. Zenodo. https://doi.org/10.5281/zenodo.20547117 | I1452: https://florauruguaya.org/taxonomias/eragrostis-japonica
A1453: =VLOOKUP(especies_20260604_1527564[[#This Row],[Column1]],output__33[[input_name_string]:[wfo_id2]],2,FALSE) -> wfo-0000867982 | B1453: Hierba perenne | C1453: Gramineae | D1453: Eragrostis lugens Nees | E1453: Eragrostis lugens | F1453: Nees | G1453: Fl. Bras. Enum. Pl. 2(1): 507, 1829. | H1453: Marchesi, E., Mailhos, A., & Bonifacino, J. M. (2026). Flora Uruguaya: Flora Vascular del Uruguay. ISSN 3121-2050, V. 1.3. [Data set]. Zenodo. https://doi.org/10.5281/zenodo.20547117 | I1453: https://florauruguaya.org/taxonomias/eragrostis-lugens
A1454: =VLOOKUP(especies_20260604_1527564[[#This Row],[Column1]],output__33[[input_name_string]:[wfo_id2]],2,FALSE) -> wfo-0000868049 | B1454: Hierba anual o bienal | C1454: Gramineae | D1454: Eragrostis mexicana (Hornem.) Link | E1454: Eragrostis mexicana | F1454: (Hornem.) Link | G1454: Hort. Berol. [Link] 1: 190, 1827. | H1454: Marchesi, E., Mailhos, A., & Bonifacino, J. M. (2026). Flora Uruguaya: Flora Vascular del Uruguay. ISSN 3121-2050, V. 1.3. [Data set]. Zenodo. https://doi.org/10.5281/zenodo.20547117 | I1454: https://florauruguaya.org/taxonomias/eragrostis-mexicana
A1455: =VLOOKUP(especies_20260604_1527564[[#This Row],[Column1]],output__33[[input_name_string]:[wfo_id2]],2,FALSE) -> wfo-0000868064 | B1455: Hierba anual o bienal | C1455: Gramineae | D1455: Eragrostis minor Host | E1455: Eragrostis minor | F1455: Host | G1455: Icon. Descr. Gram. Austriac. 4: 15, 1809. | H1455: Marchesi, E., Mailhos, A., & Bonifacino, J. M. (2026). Flora Uruguaya: Flora Vascular del Uruguay. ISSN 3121-2050, V. 1.3. [Data set]. Zenodo. https://doi.org/10.5281/zenodo.20547117 | I1455: https://florauruguaya.org/taxonomias/eragrostis-minor
A1456: =VLOOKUP(especies_20260604_1527564[[#This Row],[Column1]],output__33[[input_name_string]:[wfo_id2]],2,FALSE) -> wfo-0000868110 | B1456: Hierba perenne | C1456: Gramineae | D1456: Eragrostis neesii Trin. | E1456: Eragrostis neesii | F1456: Trin. | G1456: Mém. Acad. Imp. Sci. Saint-Pétersbourg, Sér. 6, Sci. Math., Seconde Pt. Sci. Nat. 1: 405, 1830. | H1456: Marchesi, E., Mailhos, A., & Bonifacino, J. M. (2026). Flora Uruguaya: Flora Vascular del Uruguay. ISSN 3121-2050, V. 1.3. [Data set]. Zenodo. https://doi.org/10.5281/zenodo.20547117 | I1456: https://florauruguaya.org/taxonomias/eragrostis-neesii
A1457: =VLOOKUP(especies_20260604_1527564[[#This Row],[Column1]],output__33[[input_name_string]:[wfo_id2]],2,FALSE) -> wfo-0000868188 | B1457: Hierba anual o bienal | C1457: Gramineae | D1457: Eragrostis pectinacea (Michx.) Nees | E1457: Eragrostis pectinacea | F1457: (Michx.) Nees | G1457: Fl. Afr. Austral. Ill. 406, 1841. | H1457: Marchesi, E., Mailhos, A., & Bonifacino, J. M. (2026). Flora Uruguaya: Flora Vascular del Uruguay. ISSN 3121-2050, V. 1.3. [Data set]. Zenodo. https://doi.org/10.5281/zenodo.20547117 | I1457: https://florauruguaya.org/taxonomias/eragrostis-pectinacea
A1458: =VLOOKUP(especies_20260604_1527564[[#This Row],[Column1]],output__33[[input_name_string]:[wfo_id2]],2,FALSE) -> wfo-0000868200 | B1458: Hierba perenne | C1458: Gramineae | D1458: Eragrostis perennis Döll | E1458: Eragrostis perennis | F1458: Döll | G1458: Fl. Bras. [Martius] 2(3): 144, 1878. | H1458: Marchesi, E., Mailhos, A., & Bonifacino, J. M. (2026). Flora Uruguaya: Flora Vascular del Uruguay. ISSN 3121-2050, V. 1.3. [Data set]. Zenodo. https://doi.org/10.5281/zenodo.20547117 | I1458: https://florauruguaya.org/taxonomias/eragrostis-perennis
A1459: =VLOOKUP(especies_20260604_1527564[[#This Row],[Column1]],output__33[[input_name_string]:[wfo_id2]],2,FALSE) -> wfo-0000868222 | B1459: Hierba anual o bienal | C1459: Gramineae | D1459: Eragrostis pilosa (L.) P.Beauv. | E1459: Eragrostis pilosa | F1459: (L.) P.Beauv. | G1459: Ess. Agrostogr. 71, 1812. | H1459: Marchesi, E., Mailhos, A., & Bonifacino, J. M. (2026). Flora Uruguaya: Flora Vascular del Uruguay. ISSN 3121-2050, V. 1.3. [Data set]. Zenodo. https://doi.org/10.5281/zenodo.20547117 | I1459: https://florauruguaya.org/taxonomias/eragrostis-pilosa
A1460: =VLOOKUP(especies_20260604_1527564[[#This Row],[Column1]],output__33[[input_name_string]:[wfo_id2]],2,FALSE) -> wfo-0000868250 | B1460: Hierba perenne | C1460: Gramineae | D1460: Eragrostis plana Nees | E1460: Eragrostis plana | F1460: Nees | G1460: Fl. Afr. Austral. Ill. 390, 1841. | H1460: Marchesi, E., Mailhos, A., & Bonifacino, J. M. (2026). Flora Uruguaya: Flora Vascular del Uruguay. ISSN 3121-2050, V. 1.3. [Data set]. Zenodo. https://doi.org/10.5281/zenodo.20547117 | I1460: https://florauruguaya.org/taxonomias/eragrostis-plana
... A1884: =VLOOKUP(especies_20260604_1527564[[#This Row],[Column1]],output__33[[input_name_string]:[wfo_id2]],2,FALSE) -> wfo-0000216782 | B1884: Hierba perenne | C1884: Labiatae | D1884: Hyptis lappacea Benth. | E1884: Hyptis lappacea | F1884: Benth. | G1884: Labiat. Gen. Spec. 103, 1833. | H1884: Marchesi, E., Mailhos, A., & Bonifacino, J. M. (2026). Flora Uruguaya: Flora Vascular del Uruguay. ISSN 3121-2050, V. 1.3. [Data set]. Zenodo. https://doi.org/10.5281/zenodo.20547117 | I1884: https://florauruguaya.org/taxonomias/hyptis-lappacea
A1885: =VLOOKUP(especies_20260604_1527564[[#This Row],[Column1]],output__33[[input_name_string]:[wfo_id2]],2,FALSE) -> wfo-0000216818 | B1885: Hierba anual o bienal | C1885: Labiatae | D1885: Hyptis lorentziana O.Hoffm. | E1885: Hyptis lorentziana | F1885: O.Hoffm. | H1885: Marchesi, E., Mailhos, A., & Bonifacino, J. M. (2026). Flora Uruguaya: Flora Vascular del Uruguay. ISSN 3121-2050, V. 1.3. [Data set]. Zenodo. https://doi.org/10.5281/zenodo.20547117 | I1885: https://florauruguaya.org/taxonomias/hyptis-lorentziana
A1886: =VLOOKUP(especies_20260604_1527564[[#This Row],[Column1]],output__33[[input_name_string]:[wfo_id2]],2,FALSE) -> wfo-0000216872 | B1886: Hierba perenne | C1886: Labiatae | D1886: Hyptis muelleri Briq. | E1886: Hyptis muelleri | F1886: Briq. | G1886: Bull. Soc. Bot. Genève 5: 112, 1889. | H1886: Marchesi, E., Mailhos, A., & Bonifacino, J. M. (2026). Flora Uruguaya: Flora Vascular del Uruguay. ISSN 3121-2050, V. 1.3. [Data set]. Zenodo. https://doi.org/10.5281/zenodo.20547117 | I1886: https://florauruguaya.org/taxonomias/hyptis-muelleri
A1887: =VLOOKUP(especies_20260604_1527564[[#This Row],[Column1]],output__33[[input_name_string]:[wfo_id2]],2,FALSE) -> wfo-0000222440 | B1887: Hierba anual o bienal | C1887: Labiatae | D1887: Lamium amplexicaule L. | E1887: Lamium amplexicaule | F1887: L. | G1887: Sp. Pl. [Linnaeus] 2: 579, 1753. | H1887: Marchesi, E., Mailhos, A., & Bonifacino, J. M. (2026). Flora Uruguaya: Flora Vascular del Uruguay. ISSN 3121-2050, V. 1.3. [Data set]. Zenodo. https://doi.org/10.5281/zenodo.20547117 | I1887: https://florauruguaya.org/taxonomias/lamium-amplexicaule
A1888: =VLOOKUP(especies_20260604_1527564[[#This Row],[Column1]],output__33[[input_name_string]:[wfo_id2]],2,FALSE) -> wfo-0000224580 | B1888: Hierba anual o bienal | C1888: Labiatae | D1888: Leonotis leonurus (L.) R.Br. | E1888: Leonotis leonurus | F1888: (L.) R.Br. | G1888: Hort. Kew., ed. 2 [W.T. Aiton] 3: 410, 1811. | H1888: Marchesi, E., Mailhos, A., & Bonifacino, J. M. (2026). Flora Uruguaya: Flora Vascular del Uruguay. ISSN 3121-2050, V. 1.3. [Data set]. Zenodo. https://doi.org/10.5281/zenodo.20547117 | I1888: https://florauruguaya.org/taxonomias/leonotis-leonurus
A1889: =VLOOKUP(especies_20260604_1527564[[#This Row],[Column1]],output__33[[input_name_string]:[wfo_id2]],2,FALSE) -> wfo-0000224588 | B1889: Hierba anual o bienal | C1889: Labiatae | D1889: Leonotis nepetifolia (L.) R.Br. | E1889: Leonotis nepetifolia | F1889: (L.) R.Br. | G1889: Hort. Kew., ed. 2 [W.T. Aiton] 3: 409, 1811. | H1889: Marchesi, E., Mailhos, A., & Bonifacino, J. M. (2026). Flora Uruguaya: Flora Vascular del Uruguay. ISSN 3121-2050, V. 1.3. [Data set]. Zenodo. https://doi.org/10.5281/zenodo.20547117 | I1889: https://florauruguaya.org/taxonomias/leonotis-nepetifolia
A1890: =VLOOKUP(especies_20260604_1527564[[#This Row],[Column1]],output__33[[input_name_string]:[wfo_id2]],2,FALSE) -> wfo-0000224677 | B1890: Hierba anual o bienal | C1890: Labiatae | D1890: Leonurus japonicus Houtt. | E1890: Leonurus japonicus | F1890: Houtt. | G1890: Nat. hist.. | H1890: Marchesi, E., Mailhos, A., & Bonifacino, J. M. (2026). Flora Uruguaya: Flora Vascular del Uruguay. ISSN 3121-2050, V. 1.3. [Data set]. Zenodo. https://doi.org/10.5281/zenodo.20547117 | I1890: https://florauruguaya.org/taxonomias/leonurus-japonicus
A1891: =VLOOKUP(especies_20260604_1527564[[#This Row],[Column1]],output__33[[input_name_string]:[wfo_id2]],2,FALSE) -> wfo-0000236711 | B1891: Hierba perenne | C1891: Labiatae | D1891: Marrubium vulgare L. | E1891: Marrubium vulgare | F1891: L. | G1891: Sp. Pl. [Linnaeus] 2: 583, 1753. | H1891: Marchesi, E., Mailhos, A., & Bonifacino, J. M. (2026). Flora Uruguaya: Flora Vascular del Uruguay. ISSN 3121-2050, V. 1.3. [Data set]. Zenodo. https://doi.org/10.5281/zenodo.20547117 | I1891: https://florauruguaya.org/taxonomias/marrubium-vulgare
A1892: =VLOOKUP(especies_20260604_1527564[[#This Row],[Column1]],output__33[[input_name_string]:[wfo_id2]],2,FALSE) -> wfo-0000240053 | B1892: Hierba perenne | C1892: Labiatae | D1892: Melissa officinalis L. | E1892: Melissa officinalis | F1892: L. | G1892: Sp. Pl. [Linnaeus] 2: 592, 1753. | H1892: Marchesi, E., Mailhos, A., & Bonifacino, J. M. (2026). Flora Uruguaya: Flora Vascular del Uruguay. ISSN 3121-2050, V. 1.3. [Data set]. Zenodo. https://doi.org/10.5281/zenodo.20547117 | I1892: https://florauruguaya.org/taxonomias/melissa-officinalis
A1893: =VLOOKUP(especies_20260604_1527564[[#This Row],[Column1]],output__33[[input_name_string]:[wfo_id2]],2,FALSE) -> wfo-0000240328 | B1893: Hierba perenne | C1893: Labiatae | D1893: Mentha aquatica L. | E1893: Mentha aquatica | F1893: L. | G1893: Sp. Pl. [Linnaeus] 2: 576, 1753. | H1893: Marchesi, E., Mailhos, A., & Bonifacino, J. M. (2026). Flora Uruguaya: Flora Vascular del Uruguay. ISSN 3121-2050, V. 1.3. [Data set]. Zenodo. https://doi.org/10.5281/zenodo.20547117 | I1893: https://florauruguaya.org/taxonomias/mentha-aquatica
A1894: =VLOOKUP(especies_20260604_1527564[[#This Row],[Column1]],output__33[[input_name_string]:[wfo_id2]],2,FALSE) -> wfo-0000241235 | B1894: Hierba perenne | C1894: Labiatae | D1894: Mentha pulegium L. | E1894: Mentha pulegium | F1894: L. | G1894: Sp. Pl. [Linnaeus] 2: 577, 1753. | H1894: Marchesi, E., Mailhos, A., & Bonifacino, J. M. (2026). Flora Uruguaya: Flora Vascular del Uruguay. ISSN 3121-2050, V. 1.3. [Data set]. Zenodo. https://doi.org/10.5281/zenodo.20547117 | I1894: https://florauruguaya.org/taxonomias/mentha-pulegium
A1895: =VLOOKUP(especies_20260604_1527564[[#This Row],[Column1]],output__33[[input_name_string]:[wfo_id2]],2,FALSE) -> wfo-0000241298 | B1895: Hierba perenne | C1895: Labiatae | D1895: Mentha rotundifolia (L.) Huds. | E1895: Mentha rotundifolia | F1895: (L.) Huds. | G1895: Fl. Angl. [Hudson] 221, 1762. | H1895: Marchesi, E., Mailhos, A., & Bonifacino, J. M. (2026). Flora Uruguaya: Flora Vascular del Uruguay. ISSN 3121-2050, V. 1.3. [Data set]. Zenodo. https://doi.org/10.5281/zenodo.20547117 | I1895: https://florauruguaya.org/taxonomias/mentha-rotundifolia
A1896: =VLOOKUP(especies_20260604_1527564[[#This Row],[Column1]],output__33[[input_name_string]:[wfo_id2]],2,FALSE) -> wfo-0000241390 | B1896: Hierba perenne | C1896: Labiatae | D1896: Mentha spicata L. | E1896: Mentha spicata | F1896: L. | G1896: Sp. Pl. [Linnaeus] 2: 576, 1753. | H1896: Marchesi, E., Mailhos, A., & Bonifacino, J. M. (2026). Flora Uruguaya: Flora Vascular del Uruguay. ISSN 3121-2050, V. 1.3. [Data set]. Zenodo. https://doi.org/10.5281/zenodo.20547117 | I1896: https://florauruguaya.org/taxonomias/mentha-spicata
A1897: =VLOOKUP(especies_20260604_1527564[[#This Row],[Column1]],output__33[[input_name_string]:[wfo_id2]],2,FALSE) -> wfo-0000253253 | B1897: Hierba perenne | C1897: Labiatae | D1897: Ocimum carnosum (Spreng.) Link & Otto ex Benth. | E1897: Ocimum carnosum | F1897: (Spreng.) Link & Otto ex Benth. | G1897: Labiat. Gen. Spec. 11, 1832. | H1897: Marchesi, E., Mailhos, A., & Bonifacino, J. M. (2026). Flora Uruguaya: Flora Vascular del Uruguay. ISSN 3121-2050, V. 1.3. [Data set]. Zenodo. https://doi.org/10.5281/zenodo.20547117 | I1897: https://florauruguaya.org/taxonomias/ocimum-carnosum
... A2020: =VLOOKUP(especies_20260604_1527564[[#This Row],[Column1]],output__33[[input_name_string]:[wfo_id2]],2,FALSE) -> wfo-0000212180 | B2020: Hierba perenne | C2020: Leguminosae | D2020: Lotus corniculatus L. | E2020: Lotus corniculatus | F2020: L. | G2020: Sp. Pl. [Linnaeus] 2: 775, 1753. | H2020: Marchesi, E., Mailhos, A., & Bonifacino, J. M. (2026). Flora Uruguaya: Flora Vascular del Uruguay. ISSN 3121-2050, V. 1.3. [Data set]. Zenodo. https://doi.org/10.5281/zenodo.20547117 | I2020: https://florauruguaya.org/taxonomias/lotus-corniculatus
A2021: =VLOOKUP(especies_20260604_1527564[[#This Row],[Column1]],output__33[[input_name_string]:[wfo_id2]],2,FALSE) -> #N/A | B2021: Hierba anual o bienal | C2021: Leguminosae | D2021: Lotus suaveolens | E2021: Lotus suaveolens | G2021: Syn. Pl. [Persoon] 2(2): 354, 1807. | H2021: Marchesi, E., Mailhos, A., & Bonifacino, J. M. (2026). Flora Uruguaya: Flora Vascular del Uruguay. ISSN 3121-2050, V. 1.3. [Data set]. Zenodo. https://doi.org/10.5281/zenodo.20547117 | I2021: https://florauruguaya.org/taxonomias/lotus-suaveolens
A2022: =VLOOKUP(especies_20260604_1527564[[#This Row],[Column1]],output__33[[input_name_string]:[wfo_id2]],2,FALSE) -> wfo-0001053826 | B2022: Hierba perenne | C2022: Leguminosae | D2022: Lotus tenuis Waldst. & Kit. ex Willd. | E2022: Lotus tenuis | F2022: Waldst. & Kit. ex Willd. | G2022: Enum. Pl. [Willdenow] 2: 797, 1809. | H2022: Marchesi, E., Mailhos, A., & Bonifacino, J. M. (2026). Flora Uruguaya: Flora Vascular del Uruguay. ISSN 3121-2050, V. 1.3. [Data set]. Zenodo. https://doi.org/10.5281/zenodo.20547117 | I2022: https://florauruguaya.org/taxonomias/lotus-tenuis
A2023: =VLOOKUP(especies_20260604_1527564[[#This Row],[Column1]],output__33[[input_name_string]:[wfo_id2]],2,FALSE) -> wfo-0000174682 | B2023: Hierba anual o bienal | C2023: Leguminosae | D2023: Lupinus albescens Hook. & Arn. | E2023: Lupinus albescens | F2023: Hook. & Arn. | G2023: Bot. Misc. 3: 201, 1830. | H2023: Marchesi, E., Mailhos, A., & Bonifacino, J. M. (2026). Flora Uruguaya: Flora Vascular del Uruguay. ISSN 3121-2050, V. 1.3. [Data set]. Zenodo. https://doi.org/10.5281/zenodo.20547117 | I2023: https://florauruguaya.org/taxonomias/lupinus-albescens
A2024: =VLOOKUP(especies_20260604_1527564[[#This Row],[Column1]],output__33[[input_name_string]:[wfo_id2]],2,FALSE) -> wfo-0000174699 | B2024: Hierba anual o bienal | C2024: Leguminosae | D2024: Lupinus bracteolaris Desr. | E2024: Lupinus bracteolaris | F2024: Desr. | G2024: Encycl. [J. Lamarck & al.] 3(2): 622, 1792. | H2024: Marchesi, E., Mailhos, A., & Bonifacino, J. M. (2026). Flora Uruguaya: Flora Vascular del Uruguay. ISSN 3121-2050, V. 1.3. [Data set]. Zenodo. https://doi.org/10.5281/zenodo.20547117 | I2024: https://florauruguaya.org/taxonomias/lupinus-bracteolaris
A2025: =VLOOKUP(especies_20260604_1527564[[#This Row],[Column1]],output__33[[input_name_string]:[wfo_id2]],2,FALSE) -> wfo-0000184670 | B2025: Hierba anual o bienal | C2025: Leguminosae | D2025: Lupinus heptaphyllus (Vell.) Hassl. | E2025: Lupinus heptaphyllus | F2025: (Vell.) Hassl. | G2025: Repert. Spec. Nov. Regni Veg. 16: 158, 1919. | H2025: Marchesi, E., Mailhos, A., & Bonifacino, J. M. (2026). Flora Uruguaya: Flora Vascular del Uruguay. ISSN 3121-2050, V. 1.3. [Data set]. Zenodo. https://doi.org/10.5281/zenodo.20547117 | I2025: https://florauruguaya.org/taxonomias/lupinus-heptaphyllus
A2026: =VLOOKUP(especies_20260604_1527564[[#This Row],[Column1]],output__33[[input_name_string]:[wfo_id2]],2,FALSE) -> wfo-0000174723 | B2026: Hierba perenne | C2026: Leguminosae | D2026: Lupinus lanatus Benth. | E2026: Lupinus lanatus | F2026: Benth. | G2026: Fl. Bras. [Martius] 15(1): 16, 1859. | H2026: Marchesi, E., Mailhos, A., & Bonifacino, J. M. (2026). Flora Uruguaya: Flora Vascular del Uruguay. ISSN 3121-2050, V. 1.3. [Data set]. Zenodo. https://doi.org/10.5281/zenodo.20547117 | I2026: https://florauruguaya.org/taxonomias/lupinus-lanatus
A2027: =VLOOKUP(especies_20260604_1527564[[#This Row],[Column1]],output__33[[input_name_string]:[wfo_id2]],2,FALSE) -> wfo-0000174729 | B2027: Hierba anual o bienal | C2027: Leguminosae | D2027: Lupinus linearis Desr. | E2027: Lupinus linearis | F2027: Desr. | G2027: Encycl. [J. Lamarck & al.] 3(2): 625, 1792. | H2027: Marchesi, E., Mailhos, A., & Bonifacino, J. M. (2026). Flora Uruguaya: Flora Vascular del Uruguay. ISSN 3121-2050, V. 1.3. [Data set]. Zenodo. https://doi.org/10.5281/zenodo.20547117 | I2027: https://florauruguaya.org/taxonomias/lupinus-linearis
A2028: =VLOOKUP(especies_20260604_1527564[[#This Row],[Column1]],output__33[[input_name_string]:[wfo_id2]],2,FALSE) -> wfo-0000174740 | B2028: Hierba perenne | C2028: Leguminosae | D2028: Lupinus multiflorus Desr. | E2028: Lupinus multiflorus | F2028: Desr. | G2028: Encycl. [J. Lamarck & al.] 3(2): 624, 1792. | H2028: Marchesi, E., Mailhos, A., & Bonifacino, J. M. (2026). Flora Uruguaya: Flora Vascular del Uruguay. ISSN 3121-2050, V. 1.3. [Data set]. Zenodo. https://doi.org/10.5281/zenodo.20547117 | I2028: https://florauruguaya.org/taxonomias/lupinus-multiflorus
A2029: =VLOOKUP(especies_20260604_1527564[[#This Row],[Column1]],output__33[[input_name_string]:[wfo_id2]],2,FALSE) -> wfo-0000169168 | B2029: Hierba anual o bienal | C2029: Leguminosae | D2029: Lupinus paraguariensis Chodat & Hassl. | E2029: Lupinus paraguariensis | F2029: Chodat & Hassl. | G2029: Bull. Herb. Boissier sér. 2, 4: 836, 1904. | H2029: Marchesi, E., Mailhos, A., & Bonifacino, J. M. (2026). Flora Uruguaya: Flora Vascular del Uruguay. ISSN 3121-2050, V. 1.3. [Data set]. Zenodo. https://doi.org/10.5281/zenodo.20547117 | I2029: https://florauruguaya.org/taxonomias/lupinus-paraguariensis
A2030: =VLOOKUP(especies_20260604_1527564[[#This Row],[Column1]],output__33[[input_name_string]:[wfo_id2]],2,FALSE) -> wfo-0000169338 | B2030: Árbol | C2030: Leguminosae | D2030: Machaerium paraguariense Hassl. | E2030: Machaerium paraguariense | F2030: Hassl. | G2030: Bull. Herb. Boissier sér. 2, 7: 358, 1907. | H2030: Marchesi, E., Mailhos, A., & Bonifacino, J. M. (2026). Flora Uruguaya: Flora Vascular del Uruguay. ISSN 3121-2050, V. 1.3. [Data set]. Zenodo. https://doi.org/10.5281/zenodo.20547117 | I2030: https://florauruguaya.org/taxonomias/machaerium-paraguariense
A2031: =VLOOKUP(especies_20260604_1527564[[#This Row],[Column1]],output__33[[input_name_string]:[wfo_id2]],2,FALSE) -> wfo-0000169421 | B2031: Hierba anual o bienal | C2031: Leguminosae | D2031: Macroptilium erythroloma (Mart. ex Benth.) Urb. | E2031: Macroptilium erythroloma | F2031: (Mart. ex Benth.) Urb. | G2031: Symb. Antill. [Urban] 9(4): 457, 1928. | H2031: Marchesi, E., Mailhos, A., & Bonifacino, J. M. (2026). Flora Uruguaya: Flora Vascular del Uruguay. ISSN 3121-2050, V. 1.3. [Data set]. Zenodo. https://doi.org/10.5281/zenodo.20547117 | I2031: https://florauruguaya.org/taxonomias/macroptilium-erythroloma
A2032: =VLOOKUP(especies_20260604_1527564[[#This Row],[Column1]],output__33[[input_name_string]:[wfo_id2]],2,FALSE) -> wfo-0000181730 | B2032: Hierba anual o bienal | C2032: Leguminosae | D2032: Macroptilium lathyroides (L.) Urb. | E2032: Macroptilium lathyroides | F2032: (L.) Urb. | G2032: Symb. Antill. [Urban] 9(4): 457, 1928. | H2032: Marchesi, E., Mailhos, A., & Bonifacino, J. M. (2026). Flora Uruguaya: Flora Vascular del Uruguay. ISSN 3121-2050, V. 1.3. [Data set]. Zenodo. https://doi.org/10.5281/zenodo.20547117 | I2032: https://florauruguaya.org/taxonomias/macroptilium-lathyroides
A2033: =VLOOKUP(especies_20260604_1527564[[#This Row],[Column1]],output__33[[input_name_string]:[wfo_id2]],2,FALSE) -> wfo-0000169424 | B2033: Hierba perenne | C2033: Leguminosae | D2033: Macroptilium prostratum (Benth.) Urb. | E2033: Macroptilium prostratum | F2033: (Benth.) Urb. | G2033: Symb. Antill. [Urban] 9(4): 457, 1928. | H2033: Marchesi, E., Mailhos, A., & Bonifacino, J. M. (2026). Flora Uruguaya: Flora Vascular del Uruguay. ISSN 3121-2050, V. 1.3. [Data set]. Zenodo. https://doi.org/10.5281/zenodo.20547117 | I2033: https://florauruguaya.org/taxonomias/macroptilium-prostratum
... A2305: =VLOOKUP(especies_20260604_1527564[[#This Row],[Column1]],output__33[[input_name_string]:[wfo_id2]],2,FALSE) -> wfo-0001076988 | B2305: Sufrútice | C2305: Malvaceae | D2305: Sida potentilloides A.St.-Hil. | E2305: Sida potentilloides | F2305: A.St.-Hil. | G2305: Fl. Bras. Merid. [A. St.-Hil.] 1(5): 178, 1827. | H2305: Marchesi, E., Mailhos, A., & Bonifacino, J. M. (2026). Flora Uruguaya: Flora Vascular del Uruguay. ISSN 3121-2050, V. 1.3. [Data set]. Zenodo. https://doi.org/10.5281/zenodo.20547117 | I2305: https://florauruguaya.org/taxonomias/sida-potentilloides
A2306: =VLOOKUP(especies_20260604_1527564[[#This Row],[Column1]],output__33[[input_name_string]:[wfo_id2]],2,FALSE) -> wfo-0001077885 | B2306: Sufrútice | C2306: Malvaceae | D2306: Sida regnellii R.E.Fr. | E2306: Sida regnellii | F2306: R.E.Fr. | H2306: Marchesi, E., Mailhos, A., & Bonifacino, J. M. (2026). Flora Uruguaya: Flora Vascular del Uruguay. ISSN 3121-2050, V. 1.3. [Data set]. Zenodo. https://doi.org/10.5281/zenodo.20547117 | I2306: https://florauruguaya.org/taxonomias/sida-regnellii
A2307: =VLOOKUP(especies_20260604_1527564[[#This Row],[Column1]],output__33[[input_name_string]:[wfo_id2]],2,FALSE) -> wfo-0000505360 | B2307: Sufrútice | C2307: Malvaceae | D2307: Sida rhombifolia L. | E2307: Sida rhombifolia | F2307: L. | G2307: Sp. Pl. [Linnaeus] 2: 684, 1753. | H2307: Marchesi, E., Mailhos, A., & Bonifacino, J. M. (2026). Flora Uruguaya: Flora Vascular del Uruguay. ISSN 3121-2050, V. 1.3. [Data set]. Zenodo. https://doi.org/10.5281/zenodo.20547117 | I2307: https://florauruguaya.org/taxonomias/sida-rhombifolia
A2308: =VLOOKUP(especies_20260604_1527564[[#This Row],[Column1]],output__33[[input_name_string]:[wfo_id2]],2,FALSE) -> wfo-0000505218 | B2308: Sufrútice | C2308: Malvaceae | D2308: Sida spinosa L. | E2308: Sida spinosa | F2308: L. | G2308: Sp. Pl. [Linnaeus] 2: 683, 1753. | H2308: Marchesi, E., Mailhos, A., & Bonifacino, J. M. (2026). Flora Uruguaya: Flora Vascular del Uruguay. ISSN 3121-2050, V. 1.3. [Data set]. Zenodo. https://doi.org/10.5281/zenodo.20547117 | I2308: https://florauruguaya.org/taxonomias/sida-spinosa
A2309: =VLOOKUP(especies_20260604_1527564[[#This Row],[Column1]],output__33[[input_name_string]:[wfo_id2]],2,FALSE) -> wfo-0000505474 | B2309: Sufrútice | C2309: Malvaceae | D2309: Sida tuberculata R.E.Fr. | E2309: Sida tuberculata | F2309: R.E.Fr. | G2309: Kungl. Svenska Vetenskapsakad. Handl. n.f., 42(12): 33, t. 3, 1908. | H2309: Marchesi, E., Mailhos, A., & Bonifacino, J. M. (2026). Flora Uruguaya: Flora Vascular del Uruguay. ISSN 3121-2050, V. 1.3. [Data set]. Zenodo. https://doi.org/10.5281/zenodo.20547117 | I2309: https://florauruguaya.org/taxonomias/sida-tuberculata
A2310: =VLOOKUP(especies_20260604_1527564[[#This Row],[Column1]],output__33[[input_name_string]:[wfo_id2]],2,FALSE) -> wfo-0000505486 | B2310: Hierba perenne | C2310: Malvaceae | D2310: Sida urens L. | E2310: Sida urens | F2310: L. | G2310: Syst. Nat., ed. 10. 2: 1145, 1759. | H2310: Marchesi, E., Mailhos, A., & Bonifacino, J. M. (2026). Flora Uruguaya: Flora Vascular del Uruguay. ISSN 3121-2050, V. 1.3. [Data set]. Zenodo. https://doi.org/10.5281/zenodo.20547117 | I2310: https://florauruguaya.org/taxonomias/sida-urens
A2311: =VLOOKUP(especies_20260604_1527564[[#This Row],[Column1]],output__33[[input_name_string]:[wfo_id2]],2,FALSE) -> wfo-0001268111 | B2311: Hierba perenne | C2311: Malvaceae | D2311: Sida variegata (Griseb.) Krapov. | E2311: Sida variegata | F2311: (Griseb.) Krapov. | G2311: Bol. Soc. Argent. Bot. 4(3): 187, 1952. | H2311: Marchesi, E., Mailhos, A., & Bonifacino, J. M. (2026). Flora Uruguaya: Flora Vascular del Uruguay. ISSN 3121-2050, V. 1.3. [Data set]. Zenodo. https://doi.org/10.5281/zenodo.20547117 | I2311: https://florauruguaya.org/taxonomias/sida-variegata
A2312: =VLOOKUP(especies_20260604_1527564[[#This Row],[Column1]],output__33[[input_name_string]:[wfo_id2]],2,FALSE) -> wfo-0001077015 | B2312: Sufrútice | C2312: Malvaceae | D2312: Sphaeralcea bonariensis (Cav.) Griseb. | E2312: Sphaeralcea bonariensis | F2312: (Cav.) Griseb. | G2312: Abh. Königl. Ges. Wiss. Göttingen 19: 92, 1874. | H2312: Marchesi, E., Mailhos, A., & Bonifacino, J. M. (2026). Flora Uruguaya: Flora Vascular del Uruguay. ISSN 3121-2050, V. 1.3. [Data set]. Zenodo. https://doi.org/10.5281/zenodo.20547117 | I2312: https://florauruguaya.org/taxonomias/sphaeralcea-bonariensis
A2313: =VLOOKUP(especies_20260604_1527564[[#This Row],[Column1]],output__33[[input_name_string]:[wfo_id2]],2,FALSE) -> wfo-0000505400 | B2313: Hierba perenne | C2313: Malvaceae | D2313: Sphaeralcea decipiens (A.St.-Hil. & Naudin) Krapov. | E2313: Sphaeralcea decipiens | F2313: (A.St.-Hil. & Naudin) Krapov. | G2313: Lilloa 17: 216, 1950. | H2313: Marchesi, E., Mailhos, A., & Bonifacino, J. M. (2026). Flora Uruguaya: Flora Vascular del Uruguay. ISSN 3121-2050, V. 1.3. [Data set]. Zenodo. https://doi.org/10.5281/zenodo.20547117 | I2313: https://florauruguaya.org/taxonomias/sphaeralcea-decipiens
A2314: =VLOOKUP(especies_20260604_1527564[[#This Row],[Column1]],output__33[[input_name_string]:[wfo_id2]],2,FALSE) -> wfo-0000427342 | B2314: Hierba perenne | C2314: Malvaceae | D2314: Waltheria communis A.St.-Hil. | E2314: Waltheria communis | F2314: A.St.-Hil. | G2314: Fl. Bras. Merid. [A. St.-Hil.] 1(4): 155, 1825. | H2314: Marchesi, E., Mailhos, A., & Bonifacino, J. M. (2026). Flora Uruguaya: Flora Vascular del Uruguay. ISSN 3121-2050, V. 1.3. [Data set]. Zenodo. https://doi.org/10.5281/zenodo.20547117 | I2314: https://florauruguaya.org/taxonomias/waltheria-communis
A2315: =VLOOKUP(especies_20260604_1527564[[#This Row],[Column1]],output__33[[input_name_string]:[wfo_id2]],2,FALSE) -> wfo-0001327819 | B2315: Hierba perenne | C2315: Malvaceae | D2315: Wissadula glechomifolia (A.St.-Hil.) R.E.Fr. | E2315: Wissadula glechomifolia | F2315: (A.St.-Hil.) R.E.Fr. | G2315: Kongl. Svenska Vetensk.-Akad. Handl. n.f., 43(4): 79, t. 3, 7, 1908. | H2315: Marchesi, E., Mailhos, A., & Bonifacino, J. M. (2026). Flora Uruguaya: Flora Vascular del Uruguay. ISSN 3121-2050, V. 1.3. [Data set]. Zenodo. https://doi.org/10.5281/zenodo.20547117 | I2315: https://florauruguaya.org/taxonomias/wissadula-glechomifolia
A2316: =VLOOKUP(especies_20260604_1527564[[#This Row],[Column1]],output__33[[input_name_string]:[wfo_id2]],2,FALSE) -> wfo-0000467850 | B2316: Hierba perenne | C2316: Marantaceae | D2316: Maranta sobolifera L.Andersson | E2316: Maranta sobolifera | F2316: L.Andersson | G2316: Nordic J. Bot. 6: 742, 1986. | H2316: Marchesi, E., Mailhos, A., & Bonifacino, J. M. (2026). Flora Uruguaya: Flora Vascular del Uruguay. ISSN 3121-2050, V. 1.3. [Data set]. Zenodo. https://doi.org/10.5281/zenodo.20547117 | I2316: https://florauruguaya.org/taxonomias/maranta-sobolifera
A2317: =VLOOKUP(especies_20260604_1527564[[#This Row],[Column1]],output__33[[input_name_string]:[wfo_id2]],2,FALSE) -> wfo-0000570363 | B2317: Hierba perenne | C2317: Marantaceae | D2317: Thalia geniculata L. | E2317: Thalia geniculata | F2317: L. | G2317: Sp. Pl. [Linnaeus] 2: 1193, 1753. | H2317: Marchesi, E., Mailhos, A., & Bonifacino, J. M. (2026). Flora Uruguaya: Flora Vascular del Uruguay. ISSN 3121-2050, V. 1.3. [Data set]. Zenodo. https://doi.org/10.5281/zenodo.20547117 | I2317: https://florauruguaya.org/taxonomias/thalia-geniculata
A2318: =VLOOKUP(especies_20260604_1527564[[#This Row],[Column1]],output__33[[input_name_string]:[wfo_id2]],2,FALSE) -> wfo-0000570413 | B2318: Hierba perenne | C2318: Marantaceae | D2318: Thalia multiflora Horkel ex Körn. | E2318: Thalia multiflora | F2318: Horkel ex Körn. | G2318: Bull. Soc. Imp. Naturalistes Moscou 35(1): 76, 1862. | H2318: Marchesi, E., Mailhos, A., & Bonifacino, J. M. (2026). Flora Uruguaya: Flora Vascular del Uruguay. ISSN 3121-2050, V. 1.3. [Data set]. Zenodo. https://doi.org/10.5281/zenodo.20547117 | I2318: https://florauruguaya.org/taxonomias/thalia-multiflora
... A3158: =VLOOKUP(especies_20260604_1527564[[#This Row],[Column1]],output__33[[input_name_string]:[wfo_id2]],2,FALSE) -> wfo-0000457857 | B3158: Hierba anual o bienal | C3158: Zygophyllaceae | D3158: Tribulus terrestris L. | E3158: Tribulus terrestris | F3158: L. | G3158: Sp. Pl. [Linnaeus] 1: 387, 1753. | H3158: Marchesi, E., Mailhos, A., & Bonifacino, J. M. (2026). Flora Uruguaya: Flora Vascular del Uruguay. ISSN 3121-2050, V. 1.3. [Data set]. Zenodo. https://doi.org/10.5281/zenodo.20547117 | I3158: https://florauruguaya.org/taxonomias/tribulus-terrestris

Sheet florauruguaya_V_4_habitat
A1: wfo_ID | B1: Formaciones vegetales | C1: Familia | D1: Column1 | E1: Nombre | F1: Autor | G1: Pub. | H1: biblographicCitation | I1: url
A2: =VLOOKUP(especies_20260604_15275645[[#This Row],[Column1]],output__33[[input_name_string]:[wfo_id2]],2,FALSE) -> wfo-0000646051 | B2: Bosques ribereños, Algarrobales, Matorrales mesófilos, Matorrales psamófilos, Pastizales xerófilos | C2: Acanthaceae | D2: Dicliptera squarrosa Nees | E2: Dicliptera squarrosa | F2: Nees | G2: Fl. Bras. [Martius] 9: 161, 1847. | H2: Marchesi, E., Mailhos, A., & Bonifacino, J. M. (2026). Flora Uruguaya: Flora Vascular del Uruguay. ISSN 3121-2050, V. 1.3. [Data set]. Zenodo. https://doi.org/10.5281/zenodo.20547117 | I2: https://florauruguaya.org/taxonomias/dicliptera-squarrosa
A3: =VLOOKUP(especies_20260604_15275645[[#This Row],[Column1]],output__33[[input_name_string]:[wfo_id2]],2,FALSE) -> wfo-1200030165 | B3: Algarrobales, Matorrales xerófilos, Pastizales xerófilos | C3: Acanthaceae | D3: Dyschoriste humilis (Nees) Lindau | E3: Dyschoriste humilis | F3: (Nees) Lindau | G3: Bot. Jahrb. Syst. 19(4): 15, 1894. | H3: Marchesi, E., Mailhos, A., & Bonifacino, J. M. (2026). Flora Uruguaya: Flora Vascular del Uruguay. ISSN 3121-2050, V. 1.3. [Data set]. Zenodo. https://doi.org/10.5281/zenodo.20547117 | I3: https://florauruguaya.org/taxonomias/dyschoriste-humilis
A4: =VLOOKUP(especies_20260604_15275645[[#This Row],[Column1]],output__33[[input_name_string]:[wfo_id2]],2,FALSE) -> wfo-0000658315 | B4: Pastizales xerófilos, Pastizales mesófilos | C4: Acanthaceae | D4: Dyschoriste hygrophiloides (Nees) Kuntze | E4: Dyschoriste hygrophiloides | F4: (Nees) Kuntze | G4: Revis. Gen. Pl. 2: 486, 1891. | H4: Marchesi, E., Mailhos, A., & Bonifacino, J. M. (2026). Flora Uruguaya: Flora Vascular del Uruguay. ISSN 3121-2050, V. 1.3. [Data set]. Zenodo. https://doi.org/10.5281/zenodo.20547117 | I4: https://florauruguaya.org/taxonomias/dyschoriste-hygrophiloides
A5: =VLOOKUP(especies_20260604_15275645[[#This Row],[Column1]],output__33[[input_name_string]:[wfo_id2]],2,FALSE) -> wfo-0000726781 | B5: Bosques ribereños, Bosques higrófilos, Algarrobales, Palmares, Herbazales hidrófilos | C5: Acanthaceae | D5: Hygrophila costata Nees & T.Nees | E5: Hygrophila costata | F5: Nees & T.Nees | G5: Pl. Hort. Bonn. Icon. 7, t. 3, 1824. | H5: Marchesi, E., Mailhos, A., & Bonifacino, J. M. (2026). Flora Uruguaya: Flora Vascular del Uruguay. ISSN 3121-2050, V. 1.3. [Data set]. Zenodo. https://doi.org/10.5281/zenodo.20547117 | I5: https://florauruguaya.org/taxonomias/hygrophila-costata
A6: =VLOOKUP(especies_20260604_15275645[[#This Row],[Column1]],output__33[[input_name_string]:[wfo_id2]],2,FALSE) -> wfo-0000726797 | B6: Bosques ribereños | C6: Acanthaceae | D6: Hygrophila guianensis Nees | E6: Hygrophila guianensis | F6: Nees | G6: London J. Bot. 4: 634, 1845. | H6: Marchesi, E., Mailhos, A., & Bonifacino, J. M. (2026). Flora Uruguaya: Flora Vascular del Uruguay. ISSN 3121-2050, V. 1.3. [Data set]. Zenodo. https://doi.org/10.5281/zenodo.20547117 | I6: https://florauruguaya.org/taxonomias/hygrophila-guianensis
A7: =VLOOKUP(especies_20260604_15275645[[#This Row],[Column1]],output__33[[input_name_string]:[wfo_id2]],2,FALSE) -> wfo-0001043972 | B7: Matorrales xerófilos, Pastizales xerófilos | C7: Acanthaceae | D7: Justicia axillaris (Nees) Lindau | E7: Justicia axillaris | F7: (Nees) Lindau | G7: Nat. Pflanzenfam. [Engler & Prantl] 4(3b): 350, 1895. | H7: Marchesi, E., Mailhos, A., & Bonifacino, J. M. (2026). Flora Uruguaya: Flora Vascular del Uruguay. ISSN 3121-2050, V. 1.3. [Data set]. Zenodo. https://doi.org/10.5281/zenodo.20547117 | I7: https://florauruguaya.org/taxonomias/justicia-axillaris
A8: =VLOOKUP(especies_20260604_15275645[[#This Row],[Column1]],output__33[[input_name_string]:[wfo_id2]],2,FALSE) -> wfo-0000354192 | B8: Bosques de quebradas, Bosques ribereños | C8: Acanthaceae | D8: Justicia brasiliana Roth | E8: Justicia brasiliana | F8: Roth | G8: Nov. Pl. Sp. 17, 1821. | H8: Marchesi, E., Mailhos, A., & Bonifacino, J. M. (2026). Flora Uruguaya: Flora Vascular del Uruguay. ISSN 3121-2050, V. 1.3. [Data set]. Zenodo. https://doi.org/10.5281/zenodo.20547117 | I8: https://florauruguaya.org/taxonomias/justicia-brasiliana
A9: =VLOOKUP(especies_20260604_15275645[[#This Row],[Column1]],output__33[[input_name_string]:[wfo_id2]],2,FALSE) -> wfo-0000354453 | B9: Bosques ribereños, Herbazales hidrófilos | C9: Acanthaceae | D9: Justicia comata (L.) Lam. | E9: Justicia comata | F9: (L.) Lam. | G9: Encycl. [J. Lamarck & al.] 1(2): 632, 1785. | H9: Marchesi, E., Mailhos, A., & Bonifacino, J. M. (2026). Flora Uruguaya: Flora Vascular del Uruguay. ISSN 3121-2050, V. 1.3. [Data set]. Zenodo. https://doi.org/10.5281/zenodo.20547117 | I9: https://florauruguaya.org/taxonomias/justicia-comata
A10: =VLOOKUP(especies_20260604_15275645[[#This Row],[Column1]],output__33[[input_name_string]:[wfo_id2]],2,FALSE) -> wfo-0000355947 | B10: Algarrobales, Pastizales higrófilos, Herbazales hidrófilos | C10: Acanthaceae | D10: Justicia laevilinguis (Nees) Lindau | E10: Justicia laevilinguis | F10: (Nees) Lindau | G10: Bot. Jahrb. Syst. 19(4): 20, 1894. | H10: Marchesi, E., Mailhos, A., & Bonifacino, J. M. (2026). Flora Uruguaya: Flora Vascular del Uruguay. ISSN 3121-2050, V. 1.3. [Data set]. Zenodo. https://doi.org/10.5281/zenodo.20547117 | I10: https://florauruguaya.org/taxonomias/justicia-laevilinguis
A11: =VLOOKUP(especies_20260604_15275645[[#This Row],[Column1]],output__33[[input_name_string]:[wfo_id2]],2,FALSE) -> wfo-0001044021 | B11: Bosques ribereños | C11: Acanthaceae | D11: Justicia oblonga (Nees) Lindau | E11: Justicia oblonga | F11: (Nees) Lindau | G11: Nat. Pflanzenfam. [Engler & Prantl] 4(3b): 350, 1895. | H11: Marchesi, E., Mailhos, A., & Bonifacino, J. M. (2026). Flora Uruguaya: Flora Vascular del Uruguay. ISSN 3121-2050, V. 1.3. [Data set]. Zenodo. https://doi.org/10.5281/zenodo.20547117 | I11: https://florauruguaya.org/taxonomias/justicia-oblonga
A12: =VLOOKUP(especies_20260604_15275645[[#This Row],[Column1]],output__33[[input_name_string]:[wfo_id2]],2,FALSE) -> wfo-0001044033 | B12: Pastizales higrófilos | C12: Acanthaceae | D12: Justicia polygaloides (S.Moore) Lindau | E12: Justicia polygaloides | F12: (S.Moore) Lindau | G12: Bull. Herb. Boissier 2(3): 633, 1933. | H12: Marchesi, E., Mailhos, A., & Bonifacino, J. M. (2026). Flora Uruguaya: Flora Vascular del Uruguay. ISSN 3121-2050, V. 1.3. [Data set]. Zenodo. https://doi.org/10.5281/zenodo.20547117 | I12: https://florauruguaya.org/taxonomias/justicia-polygaloides
A13: =VLOOKUP(especies_20260604_15275645[[#This Row],[Column1]],output__33[[input_name_string]:[wfo_id2]],2,FALSE) -> wfo-0001045288 | B13: Algarrobales, Pastizales xerófilos, Herbazales halófilos | C13: Acanthaceae | D13: Justicia tweedieana (Nees) Griseb. | E13: Justicia tweedieana | F13: (Nees) Griseb. | G13: Abh. Königl. Ges. Wiss. Göttingen 19: 225, 1874. | H13: Marchesi, E., Mailhos, A., & Bonifacino, J. M. (2026). Flora Uruguaya: Flora Vascular del Uruguay. ISSN 3121-2050, V. 1.3. [Data set]. Zenodo. https://doi.org/10.5281/zenodo.20547117 | I13: https://florauruguaya.org/taxonomias/justicia-tweedieana
... A1406: =VLOOKUP(especies_20260604_15275645[[#This Row],[Column1]],output__33[[input_name_string]:[wfo_id2]],2,FALSE) -> wfo-0000867414 | B1406: Ambientes ruderales | C1406: Gramineae | D1406: Eragrostis barrelieri Daveau | E1406: Eragrostis barrelieri | F1406: Daveau | G1406: J. Bot. (Morot) 8: 289, 1894. | H1406: Marchesi, E., Mailhos, A., & Bonifacino, J. M. (2026). Flora Uruguaya: Flora Vascular del Uruguay. ISSN 3121-2050, V. 1.3. [Data set]. Zenodo. https://doi.org/10.5281/zenodo.20547117 | I1406: https://florauruguaya.org/taxonomias/eragrostis-barrelieri
A1407: =VLOOKUP(especies_20260604_15275645[[#This Row],[Column1]],output__33[[input_name_string]:[wfo_id2]],2,FALSE) -> #N/A | B1407: Algarrobales, Pastizales higrófilos, Herbazales psamófilos | C1407: Gramineae | D1407: Eragrostis cataclasta | E1407: Eragrostis cataclasta | G1407: Fl. Ilustr. Entre Rios 2: 189, 1969. | H1407: Marchesi, E., Mailhos, A., & Bonifacino, J. M. (2026). Flora Uruguaya: Flora Vascular del Uruguay. ISSN 3121-2050, V. 1.3. [Data set]. Zenodo. https://doi.org/10.5281/zenodo.20547117 | I1407: https://florauruguaya.org/taxonomias/eragrostis-cataclasta
A1408: =VLOOKUP(especies_20260604_15275645[[#This Row],[Column1]],output__33[[input_name_string]:[wfo_id2]],2,FALSE) -> wfo-0000867548 | B1408: Ambientes ruderales, Ambientes urbanos | C1408: Gramineae | D1408: Eragrostis cilianensis (All.) Vignolo ex Janch. | E1408: Eragrostis cilianensis | F1408: (All.) Vignolo ex Janch. | G1408: Mitt. Naturwiss. Vereins Univ. Wien 5(9): 110, 1907. | H1408: Marchesi, E., Mailhos, A., & Bonifacino, J. M. (2026). Flora Uruguaya: Flora Vascular del Uruguay. ISSN 3121-2050, V. 1.3. [Data set]. Zenodo. https://doi.org/10.5281/zenodo.20547117 | I1408: https://florauruguaya.org/taxonomias/eragrostis-cilianensis
A1409: =VLOOKUP(especies_20260604_15275645[[#This Row],[Column1]],output__33[[input_name_string]:[wfo_id2]],2,FALSE) -> wfo-0000867617 | B1409: Pastizales mesófilos | C1409: Gramineae | D1409: Eragrostis curvula (Schrad.) Nees | E1409: Eragrostis curvula | F1409: (Schrad.) Nees | G1409: Fl. Afr. Austral. Ill. 397, 1841. | H1409: Marchesi, E., Mailhos, A., & Bonifacino, J. M. (2026). Flora Uruguaya: Flora Vascular del Uruguay. ISSN 3121-2050, V. 1.3. [Data set]. Zenodo. https://doi.org/10.5281/zenodo.20547117 | I1409: https://florauruguaya.org/taxonomias/eragrostis-curvula
A1410: =VLOOKUP(especies_20260604_15275645[[#This Row],[Column1]],output__33[[input_name_string]:[wfo_id2]],2,FALSE) -> wfo-0000867855 | B1410: Herbazales hidrófilos | C1410: Gramineae | D1410: Eragrostis hypnoides (Lam.) Britton, Sterns & Poggenb. | E1410: Eragrostis hypnoides | F1410: (Lam.) Britton, Sterns & Poggenb. | G1410: Prelim. Cat. 69, 1888. | H1410: Marchesi, E., Mailhos, A., & Bonifacino, J. M. (2026). Flora Uruguaya: Flora Vascular del Uruguay. ISSN 3121-2050, V. 1.3. [Data set]. Zenodo. https://doi.org/10.5281/zenodo.20547117 | I1410: https://florauruguaya.org/taxonomias/eragrostis-hypnoides
A1411: =VLOOKUP(especies_20260604_15275645[[#This Row],[Column1]],output__33[[input_name_string]:[wfo_id2]],2,FALSE) -> wfo-0000867890 | B1411: Bosques ribereños | C1411: Gramineae | D1411: Eragrostis japonica (Thunb.) Trin. | E1411: Eragrostis japonica | F1411: (Thunb.) Trin. | G1411: Mém. Acad. Imp. Sci. Saint-Pétersbourg, Sér. 6, Sci. Math., Seconde Pt. Sci. Nat. 1: 405, 1830. | H1411: Marchesi, E., Mailhos, A., & Bonifacino, J. M. (2026). Flora Uruguaya: Flora Vascular del Uruguay. ISSN 3121-2050, V. 1.3. [Data set]. Zenodo. https://doi.org/10.5281/zenodo.20547117 | I1411: https://florauruguaya.org/taxonomias/eragrostis-japonica
A1412: =VLOOKUP(especies_20260604_15275645[[#This Row],[Column1]],output__33[[input_name_string]:[wfo_id2]],2,FALSE) -> wfo-0000867982 | B1412: Ambientes ruderales, Ambientes urbanos, Palmares, Pastizales xerófilos, Pastizales mesófilos | C1412: Gramineae | D1412: Eragrostis lugens Nees | E1412: Eragrostis lugens | F1412: Nees | G1412: Fl. Bras. Enum. Pl. 2(1): 507, 1829. | H1412: Marchesi, E., Mailhos, A., & Bonifacino, J. M. (2026). Flora Uruguaya: Flora Vascular del Uruguay. ISSN 3121-2050, V. 1.3. [Data set]. Zenodo. https://doi.org/10.5281/zenodo.20547117 | I1412: https://florauruguaya.org/taxonomias/eragrostis-lugens
A1413: =VLOOKUP(especies_20260604_15275645[[#This Row],[Column1]],output__33[[input_name_string]:[wfo_id2]],2,FALSE) -> wfo-0000868049 | B1413: Ambientes ruderales, Ambientes urbanos | C1413: Gramineae | D1413: Eragrostis mexicana (Hornem.) Link | E1413: Eragrostis mexicana | F1413: (Hornem.) Link | G1413: Hort. Berol. [Link] 1: 190, 1827. | H1413: Marchesi, E., Mailhos, A., & Bonifacino, J. M. (2026). Flora Uruguaya: Flora Vascular del Uruguay. ISSN 3121-2050, V. 1.3. [Data set]. Zenodo. https://doi.org/10.5281/zenodo.20547117 | I1413: https://florauruguaya.org/taxonomias/eragrostis-mexicana
A1414: =VLOOKUP(especies_20260604_15275645[[#This Row],[Column1]],output__33[[input_name_string]:[wfo_id2]],2,FALSE) -> wfo-0000868064 | B1414: Ambientes ruderales | C1414: Gramineae | D1414: Eragrostis minor Host | E1414: Eragrostis minor | F1414: Host | G1414: Icon. Descr. Gram. Austriac. 4: 15, 1809. | H1414: Marchesi, E., Mailhos, A., & Bonifacino, J. M. (2026). Flora Uruguaya: Flora Vascular del Uruguay. ISSN 3121-2050, V. 1.3. [Data set]. Zenodo. https://doi.org/10.5281/zenodo.20547117 | I1414: https://florauruguaya.org/taxonomias/eragrostis-minor
A1415: =VLOOKUP(especies_20260604_15275645[[#This Row],[Column1]],output__33[[input_name_string]:[wfo_id2]],2,FALSE) -> wfo-0000868110 | B1415: Algarrobales, Palmares, Pastizales xerófilos | C1415: Gramineae | D1415: Eragrostis neesii Trin. | E1415: Eragrostis neesii | F1415: Trin. | G1415: Mém. Acad. Imp. Sci. Saint-Pétersbourg, Sér. 6, Sci. Math., Seconde Pt. Sci. Nat. 1: 405, 1830. | H1415: Marchesi, E., Mailhos, A., & Bonifacino, J. M. (2026). Flora Uruguaya: Flora Vascular del Uruguay. ISSN 3121-2050, V. 1.3. [Data set]. Zenodo. https://doi.org/10.5281/zenodo.20547117 | I1415: https://florauruguaya.org/taxonomias/eragrostis-neesii
A1416: =VLOOKUP(especies_20260604_15275645[[#This Row],[Column1]],output__33[[input_name_string]:[wfo_id2]],2,FALSE) -> wfo-0000868188 | B1416: Ambientes ruderales | C1416: Gramineae | D1416: Eragrostis pectinacea (Michx.) Nees | E1416: Eragrostis pectinacea | F1416: (Michx.) Nees | G1416: Fl. Afr. Austral. Ill. 406, 1841. | H1416: Marchesi, E., Mailhos, A., & Bonifacino, J. M. (2026). Flora Uruguaya: Flora Vascular del Uruguay. ISSN 3121-2050, V. 1.3. [Data set]. Zenodo. https://doi.org/10.5281/zenodo.20547117 | I1416: https://florauruguaya.org/taxonomias/eragrostis-pectinacea
A1417: =VLOOKUP(especies_20260604_15275645[[#This Row],[Column1]],output__33[[input_name_string]:[wfo_id2]],2,FALSE) -> wfo-0000868200 | B1417: Pastizales xerófilos | C1417: Gramineae | D1417: Eragrostis perennis Döll | E1417: Eragrostis perennis | F1417: Döll | G1417: Fl. Bras. [Martius] 2(3): 144, 1878. | H1417: Marchesi, E., Mailhos, A., & Bonifacino, J. M. (2026). Flora Uruguaya: Flora Vascular del Uruguay. ISSN 3121-2050, V. 1.3. [Data set]. Zenodo. https://doi.org/10.5281/zenodo.20547117 | I1417: https://florauruguaya.org/taxonomias/eragrostis-perennis
A1418: =VLOOKUP(especies_20260604_15275645[[#This Row],[Column1]],output__33[[input_name_string]:[wfo_id2]],2,FALSE) -> wfo-0000868222 | B1418: Bosques ribereños | C1418: Gramineae | D1418: Eragrostis pilosa (L.) P.Beauv. | E1418: Eragrostis pilosa | F1418: (L.) P.Beauv. | G1418: Ess. Agrostogr. 71, 1812. | H1418: Marchesi, E., Mailhos, A., & Bonifacino, J. M. (2026). Flora Uruguaya: Flora Vascular del Uruguay. ISSN 3121-2050, V. 1.3. [Data set]. Zenodo. https://doi.org/10.5281/zenodo.20547117 | I1418: https://florauruguaya.org/taxonomias/eragrostis-pilosa
A1419: =VLOOKUP(especies_20260604_15275645[[#This Row],[Column1]],output__33[[input_name_string]:[wfo_id2]],2,FALSE) -> wfo-0000868250 | B1419: Ambientes ruderales, Algarrobales, Pastizales xerófilos | C1419: Gramineae | D1419: Eragrostis plana Nees | E1419: Eragrostis plana | F1419: Nees | G1419: Fl. Afr. Austral. Ill. 390, 1841. | H1419: Marchesi, E., Mailhos, A., & Bonifacino, J. M. (2026). Flora Uruguaya: Flora Vascular del Uruguay. ISSN 3121-2050, V. 1.3. [Data set]. Zenodo. https://doi.org/10.5281/zenodo.20547117 | I1419: https://florauruguaya.org/taxonomias/eragrostis-plana
... A1836: =VLOOKUP(especies_20260604_15275645[[#This Row],[Column1]],output__33[[input_name_string]:[wfo_id2]],2,FALSE) -> wfo-0000216782 | B1836: Algarrobales, Palmares, Pastizales higrófilos | C1836: Labiatae | D1836: Hyptis lappacea Benth. | E1836: Hyptis lappacea | F1836: Benth. | G1836: Labiat. Gen. Spec. 103, 1833. | H1836: Marchesi, E., Mailhos, A., & Bonifacino, J. M. (2026). Flora Uruguaya: Flora Vascular del Uruguay. ISSN 3121-2050, V. 1.3. [Data set]. Zenodo. https://doi.org/10.5281/zenodo.20547117 | I1836: https://florauruguaya.org/taxonomias/hyptis-lappacea
A1837: =VLOOKUP(especies_20260604_15275645[[#This Row],[Column1]],output__33[[input_name_string]:[wfo_id2]],2,FALSE) -> wfo-0000216818 | B1837: Bosques ribereños | C1837: Labiatae | D1837: Hyptis lorentziana O.Hoffm. | E1837: Hyptis lorentziana | F1837: O.Hoffm. | H1837: Marchesi, E., Mailhos, A., & Bonifacino, J. M. (2026). Flora Uruguaya: Flora Vascular del Uruguay. ISSN 3121-2050, V. 1.3. [Data set]. Zenodo. https://doi.org/10.5281/zenodo.20547117 | I1837: https://florauruguaya.org/taxonomias/hyptis-lorentziana
A1838: =VLOOKUP(especies_20260604_15275645[[#This Row],[Column1]],output__33[[input_name_string]:[wfo_id2]],2,FALSE) -> wfo-0000216872 | B1838: Herbazales hidrófilos | C1838: Labiatae | D1838: Hyptis muelleri Briq. | E1838: Hyptis muelleri | F1838: Briq. | G1838: Bull. Soc. Bot. Genève 5: 112, 1889. | H1838: Marchesi, E., Mailhos, A., & Bonifacino, J. M. (2026). Flora Uruguaya: Flora Vascular del Uruguay. ISSN 3121-2050, V. 1.3. [Data set]. Zenodo. https://doi.org/10.5281/zenodo.20547117 | I1838: https://florauruguaya.org/taxonomias/hyptis-muelleri
A1839: =VLOOKUP(especies_20260604_15275645[[#This Row],[Column1]],output__33[[input_name_string]:[wfo_id2]],2,FALSE) -> wfo-0000222440 | B1839: Ambientes ruderales | C1839: Labiatae | D1839: Lamium amplexicaule L. | E1839: Lamium amplexicaule | F1839: L. | G1839: Sp. Pl. [Linnaeus] 2: 579, 1753. | H1839: Marchesi, E., Mailhos, A., & Bonifacino, J. M. (2026). Flora Uruguaya: Flora Vascular del Uruguay. ISSN 3121-2050, V. 1.3. [Data set]. Zenodo. https://doi.org/10.5281/zenodo.20547117 | I1839: https://florauruguaya.org/taxonomias/lamium-amplexicaule
A1840: =VLOOKUP(especies_20260604_15275645[[#This Row],[Column1]],output__33[[input_name_string]:[wfo_id2]],2,FALSE) -> wfo-0000224580 | B1840: Ambientes ruderales | C1840: Labiatae | D1840: Leonotis leonurus (L.) R.Br. | E1840: Leonotis leonurus | F1840: (L.) R.Br. | G1840: Hort. Kew., ed. 2 [W.T. Aiton] 3: 410, 1811. | H1840: Marchesi, E., Mailhos, A., & Bonifacino, J. M. (2026). Flora Uruguaya: Flora Vascular del Uruguay. ISSN 3121-2050, V. 1.3. [Data set]. Zenodo. https://doi.org/10.5281/zenodo.20547117 | I1840: https://florauruguaya.org/taxonomias/leonotis-leonurus
A1841: =VLOOKUP(especies_20260604_15275645[[#This Row],[Column1]],output__33[[input_name_string]:[wfo_id2]],2,FALSE) -> wfo-0000224588 | B1841: Ambientes ruderales | C1841: Labiatae | D1841: Leonotis nepetifolia (L.) R.Br. | E1841: Leonotis nepetifolia | F1841: (L.) R.Br. | G1841: Hort. Kew., ed. 2 [W.T. Aiton] 3: 409, 1811. | H1841: Marchesi, E., Mailhos, A., & Bonifacino, J. M. (2026). Flora Uruguaya: Flora Vascular del Uruguay. ISSN 3121-2050, V. 1.3. [Data set]. Zenodo. https://doi.org/10.5281/zenodo.20547117 | I1841: https://florauruguaya.org/taxonomias/leonotis-nepetifolia
A1842: =VLOOKUP(especies_20260604_15275645[[#This Row],[Column1]],output__33[[input_name_string]:[wfo_id2]],2,FALSE) -> wfo-0000224677 | B1842: Ambientes urbanos | C1842: Labiatae | D1842: Leonurus japonicus Houtt. | E1842: Leonurus japonicus | F1842: Houtt. | G1842: Nat. hist.. | H1842: Marchesi, E., Mailhos, A., & Bonifacino, J. M. (2026). Flora Uruguaya: Flora Vascular del Uruguay. ISSN 3121-2050, V. 1.3. [Data set]. Zenodo. https://doi.org/10.5281/zenodo.20547117 | I1842: https://florauruguaya.org/taxonomias/leonurus-japonicus
A1843: =VLOOKUP(especies_20260604_15275645[[#This Row],[Column1]],output__33[[input_name_string]:[wfo_id2]],2,FALSE) -> wfo-0000236711 | B1843: Ambientes ruderales, Algarrobales | C1843: Labiatae | D1843: Marrubium vulgare L. | E1843: Marrubium vulgare | F1843: L. | G1843: Sp. Pl. [Linnaeus] 2: 583, 1753. | H1843: Marchesi, E., Mailhos, A., & Bonifacino, J. M. (2026). Flora Uruguaya: Flora Vascular del Uruguay. ISSN 3121-2050, V. 1.3. [Data set]. Zenodo. https://doi.org/10.5281/zenodo.20547117 | I1843: https://florauruguaya.org/taxonomias/marrubium-vulgare
A1844: =VLOOKUP(especies_20260604_15275645[[#This Row],[Column1]],output__33[[input_name_string]:[wfo_id2]],2,FALSE) -> wfo-0000240053 | B1844: Ambientes ruderales | C1844: Labiatae | D1844: Melissa officinalis L. | E1844: Melissa officinalis | F1844: L. | G1844: Sp. Pl. [Linnaeus] 2: 592, 1753. | H1844: Marchesi, E., Mailhos, A., & Bonifacino, J. M. (2026). Flora Uruguaya: Flora Vascular del Uruguay. ISSN 3121-2050, V. 1.3. [Data set]. Zenodo. https://doi.org/10.5281/zenodo.20547117 | I1844: https://florauruguaya.org/taxonomias/melissa-officinalis
A1845: =VLOOKUP(especies_20260604_15275645[[#This Row],[Column1]],output__33[[input_name_string]:[wfo_id2]],2,FALSE) -> wfo-0000240328 | B1845: Ambientes urbanos | C1845: Labiatae | D1845: Mentha aquatica L. | E1845: Mentha aquatica | F1845: L. | G1845: Sp. Pl. [Linnaeus] 2: 576, 1753. | H1845: Marchesi, E., Mailhos, A., & Bonifacino, J. M. (2026). Flora Uruguaya: Flora Vascular del Uruguay. ISSN 3121-2050, V. 1.3. [Data set]. Zenodo. https://doi.org/10.5281/zenodo.20547117 | I1845: https://florauruguaya.org/taxonomias/mentha-aquatica
A1846: =VLOOKUP(especies_20260604_15275645[[#This Row],[Column1]],output__33[[input_name_string]:[wfo_id2]],2,FALSE) -> wfo-0000241235 | B1846: Ambientes ruderales, Pastizales higrófilos | C1846: Labiatae | D1846: Mentha pulegium L. | E1846: Mentha pulegium | F1846: L. | G1846: Sp. Pl. [Linnaeus] 2: 577, 1753. | H1846: Marchesi, E., Mailhos, A., & Bonifacino, J. M. (2026). Flora Uruguaya: Flora Vascular del Uruguay. ISSN 3121-2050, V. 1.3. [Data set]. Zenodo. https://doi.org/10.5281/zenodo.20547117 | I1846: https://florauruguaya.org/taxonomias/mentha-pulegium
A1847: =VLOOKUP(especies_20260604_15275645[[#This Row],[Column1]],output__33[[input_name_string]:[wfo_id2]],2,FALSE) -> wfo-0000241298 | B1847: Ambientes urbanos | C1847: Labiatae | D1847: Mentha rotundifolia (L.) Huds. | E1847: Mentha rotundifolia | F1847: (L.) Huds. | G1847: Fl. Angl. [Hudson] 221, 1762. | H1847: Marchesi, E., Mailhos, A., & Bonifacino, J. M. (2026). Flora Uruguaya: Flora Vascular del Uruguay. ISSN 3121-2050, V. 1.3. [Data set]. Zenodo. https://doi.org/10.5281/zenodo.20547117 | I1847: https://florauruguaya.org/taxonomias/mentha-rotundifolia
A1848: =VLOOKUP(especies_20260604_15275645[[#This Row],[Column1]],output__33[[input_name_string]:[wfo_id2]],2,FALSE) -> wfo-0000241390 | B1848: Ambientes ruderales, Ambientes urbanos | C1848: Labiatae | D1848: Mentha spicata L. | E1848: Mentha spicata | F1848: L. | G1848: Sp. Pl. [Linnaeus] 2: 576, 1753. | H1848: Marchesi, E., Mailhos, A., & Bonifacino, J. M. (2026). Flora Uruguaya: Flora Vascular del Uruguay. ISSN 3121-2050, V. 1.3. [Data set]. Zenodo. https://doi.org/10.5281/zenodo.20547117 | I1848: https://florauruguaya.org/taxonomias/mentha-spicata
A1849: =VLOOKUP(especies_20260604_15275645[[#This Row],[Column1]],output__33[[input_name_string]:[wfo_id2]],2,FALSE) -> wfo-0000253253 | B1849: Bosques de quebradas, Bosques ribereños, Bosques psamófilos, Algarrobales, Palmares, Matorrales mesófilos | C1849: Labiatae | D1849: Ocimum carnosum (Spreng.) Link & Otto ex Benth. | E1849: Ocimum carnosum | F1849: (Spreng.) Link & Otto ex Benth. | G1849: Labiat. Gen. Spec. 11, 1832. | H1849: Marchesi, E., Mailhos, A., & Bonifacino, J. M. (2026). Flora Uruguaya: Flora Vascular del Uruguay. ISSN 3121-2050, V. 1.3. [Data set]. Zenodo. https://doi.org/10.5281/zenodo.20547117 | I1849: https://florauruguaya.org/taxonomias/ocimum-carnosum
... A1972: =VLOOKUP(especies_20260604_15275645[[#This Row],[Column1]],output__33[[input_name_string]:[wfo_id2]],2,FALSE) -> wfo-0000212180 | B1972: Ambientes ruderales, Ambientes urbanos, Algarrobales, Palmares, Pastizales mesófilos | C1972: Leguminosae | D1972: Lotus corniculatus L. | E1972: Lotus corniculatus | F1972: L. | G1972: Sp. Pl. [Linnaeus] 2: 775, 1753. | H1972: Marchesi, E., Mailhos, A., & Bonifacino, J. M. (2026). Flora Uruguaya: Flora Vascular del Uruguay. ISSN 3121-2050, V. 1.3. [Data set]. Zenodo. https://doi.org/10.5281/zenodo.20547117 | I1972: https://florauruguaya.org/taxonomias/lotus-corniculatus
A1973: =VLOOKUP(especies_20260604_15275645[[#This Row],[Column1]],output__33[[input_name_string]:[wfo_id2]],2,FALSE) -> #N/A | B1973: Ambientes ruderales, Ambientes urbanos, Algarrobales, Palmares, Pastizales mesófilos | C1973: Leguminosae | D1973: Lotus suaveolens | E1973: Lotus suaveolens | G1973: Syn. Pl. [Persoon] 2(2): 354, 1807. | H1973: Marchesi, E., Mailhos, A., & Bonifacino, J. M. (2026). Flora Uruguaya: Flora Vascular del Uruguay. ISSN 3121-2050, V. 1.3. [Data set]. Zenodo. https://doi.org/10.5281/zenodo.20547117 | I1973: https://florauruguaya.org/taxonomias/lotus-suaveolens
A1974: =VLOOKUP(especies_20260604_15275645[[#This Row],[Column1]],output__33[[input_name_string]:[wfo_id2]],2,FALSE) -> wfo-0001053826 | B1974: Ambientes ruderales, Pastizales higrófilos | C1974: Leguminosae | D1974: Lotus tenuis Waldst. & Kit. ex Willd. | E1974: Lotus tenuis | F1974: Waldst. & Kit. ex Willd. | G1974: Enum. Pl. [Willdenow] 2: 797, 1809. | H1974: Marchesi, E., Mailhos, A., & Bonifacino, J. M. (2026). Flora Uruguaya: Flora Vascular del Uruguay. ISSN 3121-2050, V. 1.3. [Data set]. Zenodo. https://doi.org/10.5281/zenodo.20547117 | I1974: https://florauruguaya.org/taxonomias/lotus-tenuis
A1975: =VLOOKUP(especies_20260604_15275645[[#This Row],[Column1]],output__33[[input_name_string]:[wfo_id2]],2,FALSE) -> wfo-0000174682 | B1975: Matorrales psamófilos, Pastizales mesófilos, Herbazales psamófilos | C1975: Leguminosae | D1975: Lupinus albescens Hook. & Arn. | E1975: Lupinus albescens | F1975: Hook. & Arn. | G1975: Bot. Misc. 3: 201, 1830. | H1975: Marchesi, E., Mailhos, A., & Bonifacino, J. M. (2026). Flora Uruguaya: Flora Vascular del Uruguay. ISSN 3121-2050, V. 1.3. [Data set]. Zenodo. https://doi.org/10.5281/zenodo.20547117 | I1975: https://florauruguaya.org/taxonomias/lupinus-albescens
A1976: =VLOOKUP(especies_20260604_15275645[[#This Row],[Column1]],output__33[[input_name_string]:[wfo_id2]],2,FALSE) -> wfo-0000174699 | B1976: Palmares, Matorrales xerófilos, Pastizales xerófilos, Pastizales mesófilos, Herbazales psamófilos | C1976: Leguminosae | D1976: Lupinus bracteolaris Desr. | E1976: Lupinus bracteolaris | F1976: Desr. | G1976: Encycl. [J. Lamarck & al.] 3(2): 622, 1792. | H1976: Marchesi, E., Mailhos, A., & Bonifacino, J. M. (2026). Flora Uruguaya: Flora Vascular del Uruguay. ISSN 3121-2050, V. 1.3. [Data set]. Zenodo. https://doi.org/10.5281/zenodo.20547117 | I1976: https://florauruguaya.org/taxonomias/lupinus-bracteolaris
A1977: =VLOOKUP(especies_20260604_15275645[[#This Row],[Column1]],output__33[[input_name_string]:[wfo_id2]],2,FALSE) -> wfo-0000184670 | B1977: Matorrales xerófilos, Pastizales xerófilos, Pastizales mesófilos | C1977: Leguminosae | D1977: Lupinus heptaphyllus (Vell.) Hassl. | E1977: Lupinus heptaphyllus | F1977: (Vell.) Hassl. | G1977: Repert. Spec. Nov. Regni Veg. 16: 158, 1919. | H1977: Marchesi, E., Mailhos, A., & Bonifacino, J. M. (2026). Flora Uruguaya: Flora Vascular del Uruguay. ISSN 3121-2050, V. 1.3. [Data set]. Zenodo. https://doi.org/10.5281/zenodo.20547117 | I1977: https://florauruguaya.org/taxonomias/lupinus-heptaphyllus
A1978: =VLOOKUP(especies_20260604_15275645[[#This Row],[Column1]],output__33[[input_name_string]:[wfo_id2]],2,FALSE) -> wfo-0000174723 | B1978: Pastizales xerófilos, Pastizales mesófilos | C1978: Leguminosae | D1978: Lupinus lanatus Benth. | E1978: Lupinus lanatus | F1978: Benth. | G1978: Fl. Bras. [Martius] 15(1): 16, 1859. | H1978: Marchesi, E., Mailhos, A., & Bonifacino, J. M. (2026). Flora Uruguaya: Flora Vascular del Uruguay. ISSN 3121-2050, V. 1.3. [Data set]. Zenodo. https://doi.org/10.5281/zenodo.20547117 | I1978: https://florauruguaya.org/taxonomias/lupinus-lanatus
A1979: =VLOOKUP(especies_20260604_15275645[[#This Row],[Column1]],output__33[[input_name_string]:[wfo_id2]],2,FALSE) -> wfo-0000174729 | B1979: Pastizales xerófilos, Pastizales mesófilos, Herbazales psamófilos | C1979: Leguminosae | D1979: Lupinus linearis Desr. | E1979: Lupinus linearis | F1979: Desr. | G1979: Encycl. [J. Lamarck & al.] 3(2): 625, 1792. | H1979: Marchesi, E., Mailhos, A., & Bonifacino, J. M. (2026). Flora Uruguaya: Flora Vascular del Uruguay. ISSN 3121-2050, V. 1.3. [Data set]. Zenodo. https://doi.org/10.5281/zenodo.20547117 | I1979: https://florauruguaya.org/taxonomias/lupinus-linearis
A1980: =VLOOKUP(especies_20260604_15275645[[#This Row],[Column1]],output__33[[input_name_string]:[wfo_id2]],2,FALSE) -> wfo-0000174740 | B1980: Pastizales xerófilos, Pastizales mesófilos, Herbazales psamófilos | C1980: Leguminosae | D1980: Lupinus multiflorus Desr. | E1980: Lupinus multiflorus | F1980: Desr. | G1980: Encycl. [J. Lamarck & al.] 3(2): 624, 1792. | H1980: Marchesi, E., Mailhos, A., & Bonifacino, J. M. (2026). Flora Uruguaya: Flora Vascular del Uruguay. ISSN 3121-2050, V. 1.3. [Data set]. Zenodo. https://doi.org/10.5281/zenodo.20547117 | I1980: https://florauruguaya.org/taxonomias/lupinus-multiflorus
A1981: =VLOOKUP(especies_20260604_15275645[[#This Row],[Column1]],output__33[[input_name_string]:[wfo_id2]],2,FALSE) -> wfo-0000169168 | B1981: Pastizales xerófilos, Pastizales mesófilos | C1981: Leguminosae | D1981: Lupinus paraguariensis Chodat & Hassl. | E1981: Lupinus paraguariensis | F1981: Chodat & Hassl. | G1981: Bull. Herb. Boissier sér. 2, 4: 836, 1904. | H1981: Marchesi, E., Mailhos, A., & Bonifacino, J. M. (2026). Flora Uruguaya: Flora Vascular del Uruguay. ISSN 3121-2050, V. 1.3. [Data set]. Zenodo. https://doi.org/10.5281/zenodo.20547117 | I1981: https://florauruguaya.org/taxonomias/lupinus-paraguariensis
A1982: =VLOOKUP(especies_20260604_15275645[[#This Row],[Column1]],output__33[[input_name_string]:[wfo_id2]],2,FALSE) -> wfo-0000169338 | B1982: Bosques ribereños | C1982: Leguminosae | D1982: Machaerium paraguariense Hassl. | E1982: Machaerium paraguariense | F1982: Hassl. | G1982: Bull. Herb. Boissier sér. 2, 7: 358, 1907. | H1982: Marchesi, E., Mailhos, A., & Bonifacino, J. M. (2026). Flora Uruguaya: Flora Vascular del Uruguay. ISSN 3121-2050, V. 1.3. [Data set]. Zenodo. https://doi.org/10.5281/zenodo.20547117 | I1982: https://florauruguaya.org/taxonomias/machaerium-paraguariense
A1983: =VLOOKUP(especies_20260604_15275645[[#This Row],[Column1]],output__33[[input_name_string]:[wfo_id2]],2,FALSE) -> wfo-0000169421 | B1983: Herbazales psamófilos | C1983: Leguminosae | D1983: Macroptilium erythroloma (Mart. ex Benth.) Urb. | E1983: Macroptilium erythroloma | F1983: (Mart. ex Benth.) Urb. | G1983: Symb. Antill. [Urban] 9(4): 457, 1928. | H1983: Marchesi, E., Mailhos, A., & Bonifacino, J. M. (2026). Flora Uruguaya: Flora Vascular del Uruguay. ISSN 3121-2050, V. 1.3. [Data set]. Zenodo. https://doi.org/10.5281/zenodo.20547117 | I1983: https://florauruguaya.org/taxonomias/macroptilium-erythroloma
A1984: =VLOOKUP(especies_20260604_15275645[[#This Row],[Column1]],output__33[[input_name_string]:[wfo_id2]],2,FALSE) -> wfo-0000181730 | B1984: Ambientes ruderales, Herbazales hidrófilos | C1984: Leguminosae | D1984: Macroptilium lathyroides (L.) Urb. | E1984: Macroptilium lathyroides | F1984: (L.) Urb. | G1984: Symb. Antill. [Urban] 9(4): 457, 1928. | H1984: Marchesi, E., Mailhos, A., & Bonifacino, J. M. (2026). Flora Uruguaya: Flora Vascular del Uruguay. ISSN 3121-2050, V. 1.3. [Data set]. Zenodo. https://doi.org/10.5281/zenodo.20547117 | I1984: https://florauruguaya.org/taxonomias/macroptilium-lathyroides
A1985: =VLOOKUP(especies_20260604_15275645[[#This Row],[Column1]],output__33[[input_name_string]:[wfo_id2]],2,FALSE) -> wfo-0000169424 | B1985: Palmares, Pastizales xerófilos, Pastizales mesófilos | C1985: Leguminosae | D1985: Macroptilium prostratum (Benth.) Urb. | E1985: Macroptilium prostratum | F1985: (Benth.) Urb. | G1985: Symb. Antill. [Urban] 9(4): 457, 1928. | H1985: Marchesi, E., Mailhos, A., & Bonifacino, J. M. (2026). Flora Uruguaya: Flora Vascular del Uruguay. ISSN 3121-2050, V. 1.3. [Data set]. Zenodo. https://doi.org/10.5281/zenodo.20547117 | I1985: https://florauruguaya.org/taxonomias/macroptilium-prostratum
... A2256: =VLOOKUP(especies_20260604_15275645[[#This Row],[Column1]],output__33[[input_name_string]:[wfo_id2]],2,FALSE) -> wfo-0001076988 | B2256: Pastizales higrófilos, Herbazales hidrófilos | C2256: Malvaceae | D2256: Sida potentilloides A.St.-Hil. | E2256: Sida potentilloides | F2256: A.St.-Hil. | G2256: Fl. Bras. Merid. [A. St.-Hil.] 1(5): 178, 1827. | H2256: Marchesi, E., Mailhos, A., & Bonifacino, J. M. (2026). Flora Uruguaya: Flora Vascular del Uruguay. ISSN 3121-2050, V. 1.3. [Data set]. Zenodo. https://doi.org/10.5281/zenodo.20547117 | I2256: https://florauruguaya.org/taxonomias/sida-potentilloides
A2257: =VLOOKUP(especies_20260604_15275645[[#This Row],[Column1]],output__33[[input_name_string]:[wfo_id2]],2,FALSE) -> wfo-0001077885 | B2257: Matorrales mesófilos | C2257: Malvaceae | D2257: Sida regnellii R.E.Fr. | E2257: Sida regnellii | F2257: R.E.Fr. | H2257: Marchesi, E., Mailhos, A., & Bonifacino, J. M. (2026). Flora Uruguaya: Flora Vascular del Uruguay. ISSN 3121-2050, V. 1.3. [Data set]. Zenodo. https://doi.org/10.5281/zenodo.20547117 | I2257: https://florauruguaya.org/taxonomias/sida-regnellii
A2258: =VLOOKUP(especies_20260604_15275645[[#This Row],[Column1]],output__33[[input_name_string]:[wfo_id2]],2,FALSE) -> wfo-0000505360 | B2258: Ambientes ruderales, Ambientes urbanos, Algarrobales, Palmares, Matorrales mesófilos, Pastizales xerófilos, Pastizales mesófilos, Herbazales halófilos | C2258: Malvaceae | D2258: Sida rhombifolia L. | E2258: Sida rhombifolia | F2258: L. | G2258: Sp. Pl. [Linnaeus] 2: 684, 1753. | H2258: Marchesi, E., Mailhos, A., & Bonifacino, J. M. (2026). Flora Uruguaya: Flora Vascular del Uruguay. ISSN 3121-2050, V. 1.3. [Data set]. Zenodo. https://doi.org/10.5281/zenodo.20547117 | I2258: https://florauruguaya.org/taxonomias/sida-rhombifolia
A2259: =VLOOKUP(especies_20260604_15275645[[#This Row],[Column1]],output__33[[input_name_string]:[wfo_id2]],2,FALSE) -> wfo-0000505218 | B2259: Ambientes ruderales, Bosques ribereños, Algarrobales, Pastizales mesófilos | C2259: Malvaceae | D2259: Sida spinosa L. | E2259: Sida spinosa | F2259: L. | G2259: Sp. Pl. [Linnaeus] 2: 683, 1753. | H2259: Marchesi, E., Mailhos, A., & Bonifacino, J. M. (2026). Flora Uruguaya: Flora Vascular del Uruguay. ISSN 3121-2050, V. 1.3. [Data set]. Zenodo. https://doi.org/10.5281/zenodo.20547117 | I2259: https://florauruguaya.org/taxonomias/sida-spinosa
A2260: =VLOOKUP(especies_20260604_15275645[[#This Row],[Column1]],output__33[[input_name_string]:[wfo_id2]],2,FALSE) -> wfo-0000505474 | B2260: Ambientes ruderales, Pastizales mesófilos | C2260: Malvaceae | D2260: Sida tuberculata R.E.Fr. | E2260: Sida tuberculata | F2260: R.E.Fr. | G2260: Kungl. Svenska Vetenskapsakad. Handl. n.f., 42(12): 33, t. 3, 1908. | H2260: Marchesi, E., Mailhos, A., & Bonifacino, J. M. (2026). Flora Uruguaya: Flora Vascular del Uruguay. ISSN 3121-2050, V. 1.3. [Data set]. Zenodo. https://doi.org/10.5281/zenodo.20547117 | I2260: https://florauruguaya.org/taxonomias/sida-tuberculata
A2261: =VLOOKUP(especies_20260604_15275645[[#This Row],[Column1]],output__33[[input_name_string]:[wfo_id2]],2,FALSE) -> wfo-0000505486 | B2261: Algarrobales, Pastizales xerófilos, Pastizales mesófilos | C2261: Malvaceae | D2261: Sida urens L. | E2261: Sida urens | F2261: L. | G2261: Syst. Nat., ed. 10. 2: 1145, 1759. | H2261: Marchesi, E., Mailhos, A., & Bonifacino, J. M. (2026). Flora Uruguaya: Flora Vascular del Uruguay. ISSN 3121-2050, V. 1.3. [Data set]. Zenodo. https://doi.org/10.5281/zenodo.20547117 | I2261: https://florauruguaya.org/taxonomias/sida-urens
A2262: =VLOOKUP(especies_20260604_15275645[[#This Row],[Column1]],output__33[[input_name_string]:[wfo_id2]],2,FALSE) -> wfo-0001268111 | B2262: Pastizales mesófilos | C2262: Malvaceae | D2262: Sida variegata (Griseb.) Krapov. | E2262: Sida variegata | F2262: (Griseb.) Krapov. | G2262: Bol. Soc. Argent. Bot. 4(3): 187, 1952. | H2262: Marchesi, E., Mailhos, A., & Bonifacino, J. M. (2026). Flora Uruguaya: Flora Vascular del Uruguay. ISSN 3121-2050, V. 1.3. [Data set]. Zenodo. https://doi.org/10.5281/zenodo.20547117 | I2262: https://florauruguaya.org/taxonomias/sida-variegata
A2263: =VLOOKUP(especies_20260604_15275645[[#This Row],[Column1]],output__33[[input_name_string]:[wfo_id2]],2,FALSE) -> wfo-0001077015 | B2263: Ambientes ruderales, Bosques ribereños, Algarrobales | C2263: Malvaceae | D2263: Sphaeralcea bonariensis (Cav.) Griseb. | E2263: Sphaeralcea bonariensis | F2263: (Cav.) Griseb. | G2263: Abh. Königl. Ges. Wiss. Göttingen 19: 92, 1874. | H2263: Marchesi, E., Mailhos, A., & Bonifacino, J. M. (2026). Flora Uruguaya: Flora Vascular del Uruguay. ISSN 3121-2050, V. 1.3. [Data set]. Zenodo. https://doi.org/10.5281/zenodo.20547117 | I2263: https://florauruguaya.org/taxonomias/sphaeralcea-bonariensis
A2264: =VLOOKUP(especies_20260604_15275645[[#This Row],[Column1]],output__33[[input_name_string]:[wfo_id2]],2,FALSE) -> wfo-0000505400 | B2264: Ambientes ruderales, Ambientes urbanos, Pastizales mesófilos | C2264: Malvaceae | D2264: Sphaeralcea decipiens (A.St.-Hil. & Naudin) Krapov. | E2264: Sphaeralcea decipiens | F2264: (A.St.-Hil. & Naudin) Krapov. | G2264: Lilloa 17: 216, 1950. | H2264: Marchesi, E., Mailhos, A., & Bonifacino, J. M. (2026). Flora Uruguaya: Flora Vascular del Uruguay. ISSN 3121-2050, V. 1.3. [Data set]. Zenodo. https://doi.org/10.5281/zenodo.20547117 | I2264: https://florauruguaya.org/taxonomias/sphaeralcea-decipiens
A2265: =VLOOKUP(especies_20260604_15275645[[#This Row],[Column1]],output__33[[input_name_string]:[wfo_id2]],2,FALSE) -> wfo-0000427342 | B2265: Matorrales xerófilos, Pastizales xerófilos, Pastizales mesófilos | C2265: Malvaceae | D2265: Waltheria communis A.St.-Hil. | E2265: Waltheria communis | F2265: A.St.-Hil. | G2265: Fl. Bras. Merid. [A. St.-Hil.] 1(4): 155, 1825. | H2265: Marchesi, E., Mailhos, A., & Bonifacino, J. M. (2026). Flora Uruguaya: Flora Vascular del Uruguay. ISSN 3121-2050, V. 1.3. [Data set]. Zenodo. https://doi.org/10.5281/zenodo.20547117 | I2265: https://florauruguaya.org/taxonomias/waltheria-communis
A2266: =VLOOKUP(especies_20260604_15275645[[#This Row],[Column1]],output__33[[input_name_string]:[wfo_id2]],2,FALSE) -> wfo-0001327819 | B2266: Algarrobales, Matorrales xerófilos, Pastizales xerófilos, Pastizales mesófilos | C2266: Malvaceae | D2266: Wissadula glechomifolia (A.St.-Hil.) R.E.Fr. | E2266: Wissadula glechomifolia | F2266: (A.St.-Hil.) R.E.Fr. | G2266: Kongl. Svenska Vetensk.-Akad. Handl. n.f., 43(4): 79, t. 3, 7, 1908. | H2266: Marchesi, E., Mailhos, A., & Bonifacino, J. M. (2026). Flora Uruguaya: Flora Vascular del Uruguay. ISSN 3121-2050, V. 1.3. [Data set]. Zenodo. https://doi.org/10.5281/zenodo.20547117 | I2266: https://florauruguaya.org/taxonomias/wissadula-glechomifolia
A2267: =VLOOKUP(especies_20260604_15275645[[#This Row],[Column1]],output__33[[input_name_string]:[wfo_id2]],2,FALSE) -> wfo-0000467850 | B2267: Herbazales hidrófilos | C2267: Marantaceae | D2267: Maranta sobolifera L.Andersson | E2267: Maranta sobolifera | F2267: L.Andersson | G2267: Nordic J. Bot. 6: 742, 1986. | H2267: Marchesi, E., Mailhos, A., & Bonifacino, J. M. (2026). Flora Uruguaya: Flora Vascular del Uruguay. ISSN 3121-2050, V. 1.3. [Data set]. Zenodo. https://doi.org/10.5281/zenodo.20547117 | I2267: https://florauruguaya.org/taxonomias/maranta-sobolifera
A2268: =VLOOKUP(especies_20260604_15275645[[#This Row],[Column1]],output__33[[input_name_string]:[wfo_id2]],2,FALSE) -> wfo-0000570363 | B2268: Herbazales hidrófilos, Dulce y salobre | C2268: Marantaceae | D2268: Thalia geniculata L. | E2268: Thalia geniculata | F2268: L. | G2268: Sp. Pl. [Linnaeus] 2: 1193, 1753. | H2268: Marchesi, E., Mailhos, A., & Bonifacino, J. M. (2026). Flora Uruguaya: Flora Vascular del Uruguay. ISSN 3121-2050, V. 1.3. [Data set]. Zenodo. https://doi.org/10.5281/zenodo.20547117 | I2268: https://florauruguaya.org/taxonomias/thalia-geniculata
A2269: =VLOOKUP(especies_20260604_15275645[[#This Row],[Column1]],output__33[[input_name_string]:[wfo_id2]],2,FALSE) -> wfo-0000570413 | B2269: Bosques higrófilos, Herbazales hidrófilos, Dulce y salobre | C2269: Marantaceae | D2269: Thalia multiflora Horkel ex Körn. | E2269: Thalia multiflora | F2269: Horkel ex Körn. | G2269: Bull. Soc. Imp. Naturalistes Moscou 35(1): 76, 1862. | H2269: Marchesi, E., Mailhos, A., & Bonifacino, J. M. (2026). Flora Uruguaya: Flora Vascular del Uruguay. ISSN 3121-2050, V. 1.3. [Data set]. Zenodo. https://doi.org/10.5281/zenodo.20547117 | I2269: https://florauruguaya.org/taxonomias/thalia-multiflora
... A3089: =VLOOKUP(especies_20260604_15275645[[#This Row],[Column1]],output__33[[input_name_string]:[wfo_id2]],2,FALSE) -> wfo-0000457857 | B3089: Ambientes ruderales | C3089: Zygophyllaceae | D3089: Tribulus terrestris L. | E3089: Tribulus terrestris | F3089: L. | G3089: Sp. Pl. [Linnaeus] 1: 387, 1753. | H3089: Marchesi, E., Mailhos, A., & Bonifacino, J. M. (2026). Flora Uruguaya: Flora Vascular del Uruguay. ISSN 3121-2050, V. 1.3. [Data set]. Zenodo. https://doi.org/10.5281/zenodo.20547117 | I3089: https://florauruguaya.org/taxonomias/tribulus-terrestris

Sheet Sheet2
A1: Forma de vida
A2: Caméfita | B2: subshrub
A3: Nanofanerófita
A4: Hemicriptófita
A5: Fanerófita | W5: Caméfita
A6: Terófita | B6: annual
A7: Hidrófita | B7: Aquatic
A8: Geófita | B8: Geophyte
A9: Epífita | B9: Epiphyte
